{"ok":1,"data":{"cards":[{"itemid":"hotword","show_type":0,"title":"\u5b9e\u65f6\u70ed\u70b9\uff0c\u6bcf\u5206\u949f\u66f4\u65b0\u4e00\u6b21","card_type":11,"card_group":[{"itemid":"t:51|lcate:5000|cate:10103|key:\u65b0\u65f6\u4ee3\u7684\u65b0\u7586\u5bcc\u6c11\u5174\u7586|c_type:51|pos:1-2-0||type:25","actionlog":{"act_code":554,"ext":"seqid:16579839450170435141369|pos:0_0|cate:10113|key:#\u65b0\u65f6\u4ee3\u7684\u65b0\u7586\u5bcc\u6c11\u5174\u7586#|c_type:51|t:51|page:1|type:25|dgr:0","luicode":"","act_type":1,"uicode":"","fid":"106003type=25&t=3&disable_hot=1&filter_type=realtimehot","lfid":""},"icon":"https:\/\/simg.s.weibo.com\/20210226_hot.png","desc":"\u65b0\u65f6\u4ee3\u7684\u65b0\u7586\u5bcc\u6c11\u5174\u7586","pic":"https:\/\/simg.s.weibo.com\/20180205110043_img_search_stick%403x.png","card_type":4,"scheme":"https:\/\/m.weibo.cn\/search?containerid=100103type%3D1%26t%3D10%26q%3D%23%E6%96%B0%E6%97%B6%E4%BB%A3%E7%9A%84%E6%96%B0%E7%96%86%E5%AF%8C%E6%B0%91%E5%85%B4%E7%96%86%23&stream_entry_id=51&isnewpage=1&extparam=seat%3D1%26pos%3D0%26filter_type%3Drealtimehot%26cate%3D10103%26c_type%3D51%26dgr%3D0%26display_time%3D1657983945%26pre_seqid%3D16579839450170435141369&luicode=10000011&lfid=106003type%253D25%2526t%253D3%2526disable_hot%253D1%2526filter_type%253Drealtimehot"},{"actionlog":{"act_code":554,"ext":"seqid:16579839450170435141369|t:31|cate:10103|key:#\u5de5\u4eba\u6536\u5de5\u8def\u4e0a\u56e0\u70ed\u5c04\u75c5\u53bb\u4e16#|c_type:31|pos:1_0|page:1|type:25|dgr:0","luicode":"","act_type":1,"uicode":"","fid":"106003type=25&t=3&disable_hot=1&filter_type=realtimehot","lfid":""},"desc":"\u5de5\u4eba\u6536\u5de5\u8def\u4e0a\u56e0\u70ed\u5c04\u75c5\u53bb\u4e16","desc_extr":3110519,"itemid":"t:31|cate:10103|key:#\u5de5\u4eba\u6536\u5de5\u8def\u4e0a\u56e0\u70ed\u5c04\u75c5\u53bb\u4e16#|c_type:31|pos:1-1-0||type:25","scheme":"https:\/\/m.weibo.cn\/search?containerid=100103type%3D1%26t%3D10%26q%3D%23%E5%B7%A5%E4%BA%BA%E6%94%B6%E5%B7%A5%E8%B7%AF%E4%B8%8A%E5%9B%A0%E7%83%AD%E5%B0%84%E7%97%85%E5%8E%BB%E4%B8%96%23&stream_entry_id=31&isnewpage=1&extparam=seat%3D1%26pos%3D0%26filter_type%3Drealtimehot%26dgr%3D0%26c_type%3D31%26flag%3D1%26cate%3D0%26realpos%3D1%26lcate%3D5001%26display_time%3D1657983945%26pre_seqid%3D16579839450170435141369&luicode=10000011&lfid=106003type%253D25%2526t%253D3%2526disable_hot%253D1%2526filter_type%253Drealtimehot","icon_height":24,"icon":"https:\/\/simg.s.weibo.com\/20210226_new.png","icon_width":24,"card_type":4,"pic":"https:\/\/simg.s.weibo.com\/20170303_img_search_1.png"},{"actionlog":{"act_code":554,"ext":"seqid:16579839450170435141369|t:31|cate:10103|key:\u9ec4\u8001\u5e08|c_type:31|pos:1_1|page:1|type:25|dgr:0","luicode":"","act_type":1,"uicode":"","fid":"106003type=25&t=3&disable_hot=1&filter_type=realtimehot","lfid":""},"desc":"\u9ec4\u8001\u5e08","desc_extr":2820784,"itemid":"t:31|cate:10103|key:\u9ec4\u8001\u5e08|c_type:31|pos:1-1-0||type:25","scheme":"https:\/\/m.weibo.cn\/search?containerid=100103type%3D1%26t%3D10%26q%3D%E9%BB%84%E8%80%81%E5%B8%88&stream_entry_id=31&isnewpage=1&extparam=seat%3D1%26pos%3D1%26filter_type%3Drealtimehot%26dgr%3D0%26c_type%3D31%26flag%3D2%26cate%3D0%26realpos%3D2%26lcate%3D5001%26display_time%3D1657983945%26pre_seqid%3D16579839450170435141369&luicode=10000011&lfid=106003type%253D25%2526t%253D3%2526disable_hot%253D1%2526filter_type%253Drealtimehot","icon_height":24,"icon":"https:\/\/simg.s.weibo.com\/20210226_hot.png","icon_width":24,"card_type":4,"pic":"https:\/\/simg.s.weibo.com\/20170303_img_search_2.png"},{"actionlog":{"act_code":554,"ext":"seqid:16579839450170435141369|t:31|cate:10103|key:#\u70c8\u65e5\u4e0b\u7684\u52b3\u52a8\u8005\u8f9b\u82e6\u4e86#|c_type:31|pos:1_2|page:1|type:25|dgr:0","luicode":"","act_type":1,"uicode":"","fid":"106003type=25&t=3&disable_hot=1&filter_type=realtimehot","lfid":""},"desc":"\u70c8\u65e5\u4e0b\u7684\u52b3\u52a8\u8005\u8f9b\u82e6\u4e86","desc_extr":2015839,"itemid":"t:31|cate:10103|key:#\u70c8\u65e5\u4e0b\u7684\u52b3\u52a8\u8005\u8f9b\u82e6\u4e86#|c_type:31|pos:1-1-0||type:25","scheme":"https:\/\/m.weibo.cn\/search?containerid=100103type%3D1%26t%3D10%26q%3D%23%E7%83%88%E6%97%A5%E4%B8%8B%E7%9A%84%E5%8A%B3%E5%8A%A8%E8%80%85%E8%BE%9B%E8%8B%A6%E4%BA%86%23&stream_entry_id=31&isnewpage=1&extparam=seat%3D1%26pos%3D2%26filter_type%3Drealtimehot%26dgr%3D0%26c_type%3D31%26flag%3D0%26cate%3D0%26realpos%3D3%26lcate%3D5001%26display_time%3D1657983945%26pre_seqid%3D16579839450170435141369&luicode=10000011&lfid=106003type%253D25%2526t%253D3%2526disable_hot%253D1%2526filter_type%253Drealtimehot","icon_height":24,"card_type":4,"icon_width":24,"pic":"https:\/\/simg.s.weibo.com\/20170303_img_search_3.png"},{"actionlog":{"act_code":554,"ext":"seqid:16579839450170435141369|t:31|cate:10103|key:\u6a0a\u632f\u4e1c|c_type:31|pos:1_3|page:1|type:25|dgr:0","luicode":"","act_type":1,"uicode":"","fid":"106003type=25&t=3&disable_hot=1&filter_type=realtimehot","lfid":""},"desc":"\u6a0a\u632f\u4e1c","desc_extr":1710983,"itemid":"t:31|cate:10103|key:\u6a0a\u632f\u4e1c|c_type:31|pos:1-1-0||type:25","scheme":"https:\/\/m.weibo.cn\/search?containerid=100103type%3D1%26t%3D10%26q%3D%E6%A8%8A%E6%8C%AF%E4%B8%9C&stream_entry_id=31&isnewpage=1&extparam=seat%3D1%26pos%3D3%26filter_type%3Drealtimehot%26dgr%3D0%26c_type%3D31%26flag%3D0%26cate%3D0%26realpos%3D4%26lcate%3D5001%26display_time%3D1657983945%26pre_seqid%3D16579839450170435141369&luicode=10000011&lfid=106003type%253D25%2526t%253D3%2526disable_hot%253D1%2526filter_type%253Drealtimehot","icon_height":24,"card_type":4,"icon_width":24,"pic":"https:\/\/simg.s.weibo.com\/20170303_img_search_4.png"},{"actionlog":{"act_code":554,"ext":"seqid:16579839450170435141369|t:31|cate:10103|key:\u738b\u6f84\u6f84|c_type:31|pos:1_4|page:1|type:25|dgr:0","luicode":"","act_type":1,"uicode":"","fid":"106003type=25&t=3&disable_hot=1&filter_type=realtimehot","lfid":""},"desc":"\u738b\u6f84\u6f84","desc_extr":1461960,"itemid":"t:31|cate:10103|key:\u738b\u6f84\u6f84|c_type:31|pos:1-1-0||type:25","scheme":"https:\/\/m.weibo.cn\/search?containerid=100103type%3D1%26t%3D10%26q%3D%E7%8E%8B%E6%BE%84%E6%BE%84&stream_entry_id=31&isnewpage=1&extparam=seat%3D1%26pos%3D4%26filter_type%3Drealtimehot%26dgr%3D0%26c_type%3D31%26flag%3D1%26cate%3D0%26realpos%3D5%26lcate%3D5001%26display_time%3D1657983945%26pre_seqid%3D16579839450170435141369&luicode=10000011&lfid=106003type%253D25%2526t%253D3%2526disable_hot%253D1%2526filter_type%253Drealtimehot","icon_height":24,"icon":"https:\/\/simg.s.weibo.com\/20210226_new.png","icon_width":24,"card_type":4,"pic":"https:\/\/simg.s.weibo.com\/20170303_img_search_5.png"},{"actionlog":{"act_code":554,"ext":"seqid:16579839450170435141369|t:31|cate:10103|key:#\u7528\u9ad8\u5fb7\u6253\u8f66\u9047\u8f66\u7978\u8eab\u4ea1\u5973\u751f\u54e5\u54e5\u53d1\u58f0#|c_type:31|pos:1_5|page:1|type:25|dgr:0","luicode":"","act_type":1,"uicode":"","fid":"106003type=25&t=3&disable_hot=1&filter_type=realtimehot","lfid":""},"desc":"\u7528\u9ad8\u5fb7\u6253\u8f66\u9047\u8f66\u7978\u8eab\u4ea1\u5973\u751f\u54e5\u54e5\u53d1\u58f0","desc_extr":1267916,"itemid":"t:31|cate:10103|key:#\u7528\u9ad8\u5fb7\u6253\u8f66\u9047\u8f66\u7978\u8eab\u4ea1\u5973\u751f\u54e5\u54e5\u53d1\u58f0#|c_type:31|pos:1-1-0||type:25","scheme":"https:\/\/m.weibo.cn\/search?containerid=100103type%3D1%26t%3D10%26q%3D%23%E7%94%A8%E9%AB%98%E5%BE%B7%E6%89%93%E8%BD%A6%E9%81%87%E8%BD%A6%E7%A5%B8%E8%BA%AB%E4%BA%A1%E5%A5%B3%E7%94%9F%E5%93%A5%E5%93%A5%E5%8F%91%E5%A3%B0%23&stream_entry_id=31&isnewpage=1&extparam=seat%3D1%26pos%3D5%26filter_type%3Drealtimehot%26dgr%3D0%26c_type%3D31%26flag%3D2%26cate%3D0%26realpos%3D6%26lcate%3D5001%26display_time%3D1657983945%26pre_seqid%3D16579839450170435141369&luicode=10000011&lfid=106003type%253D25%2526t%253D3%2526disable_hot%253D1%2526filter_type%253Drealtimehot","icon_height":24,"icon":"https:\/\/simg.s.weibo.com\/20210226_hot.png","icon_width":24,"card_type":4,"pic":"https:\/\/simg.s.weibo.com\/20170303_img_search_6.png"},{"actionlog":{"act_code":554,"ext":"seqid:16579839450170435141369|t:31|cate:10103|key:#\u661f\u6c49\u707f\u70c2\u8c46\u74e3\u5f00\u52067.4\u5206#|c_type:31|pos:1_6|page:1|type:25|dgr:0","luicode":"","act_type":1,"uicode":"","fid":"106003type=25&t=3&disable_hot=1&filter_type=realtimehot","lfid":""},"desc":"\u661f\u6c49\u707f\u70c2\u8c46\u74e3\u5f00\u52067.4\u5206","desc_extr":"\u5267\u96c6 961303","itemid":"t:31|cate:10103|key:#\u661f\u6c49\u707f\u70c2\u8c46\u74e3\u5f00\u52067.4\u5206#|c_type:31|pos:1-1-0||type:25","scheme":"https:\/\/m.weibo.cn\/search?containerid=100103type%3D1%26t%3D10%26q%3D%23%E6%98%9F%E6%B1%89%E7%81%BF%E7%83%82%E8%B1%86%E7%93%A3%E5%BC%80%E5%88%867.4%E5%88%86%23&stream_entry_id=31&isnewpage=1&extparam=seat%3D1%26pos%3D6%26filter_type%3Drealtimehot%26dgr%3D0%26c_type%3D31%26flag%3D1%26cate%3D0%26realpos%3D7%26lcate%3D5001%26display_time%3D1657983945%26pre_seqid%3D16579839450170435141369&luicode=10000011&lfid=106003type%253D25%2526t%253D3%2526disable_hot%253D1%2526filter_type%253Drealtimehot","icon_height":24,"icon":"https:\/\/simg.s.weibo.com\/20210226_new.png","icon_width":24,"card_type":4,"pic":"https:\/\/simg.s.weibo.com\/20170303_img_search_7.png"},{"actionlog":{"act_code":554,"ext":"seqid:16579839450170435141369|t:31|cate:10103|key:#\u738b\u695a\u94a6\u738b\u66fc\u6631vs\u5f20\u672c\u667a\u548c\u65e9\u7530\u5e0c\u5a1c#|c_type:31|pos:1_7|page:1|type:25|dgr:0","luicode":"","act_type":1,"uicode":"","fid":"106003type=25&t=3&disable_hot=1&filter_type=realtimehot","lfid":""},"desc":"\u738b\u695a\u94a6\u738b\u66fc\u6631vs\u5f20\u672c\u667a\u548c\u65e9\u7530\u5e0c\u5a1c","desc_extr":952087,"itemid":"t:31|cate:10103|key:#\u738b\u695a\u94a6\u738b\u66fc\u6631vs\u5f20\u672c\u667a\u548c\u65e9\u7530\u5e0c\u5a1c#|c_type:31|pos:1-1-0||type:25","scheme":"https:\/\/m.weibo.cn\/search?containerid=100103type%3D1%26t%3D10%26q%3D%23%E7%8E%8B%E6%A5%9A%E9%92%A6%E7%8E%8B%E6%9B%BC%E6%98%B1vs%E5%BC%A0%E6%9C%AC%E6%99%BA%E5%92%8C%E6%97%A9%E7%94%B0%E5%B8%8C%E5%A8%9C%23&stream_entry_id=31&isnewpage=1&extparam=seat%3D1%26pos%3D7%26filter_type%3Drealtimehot%26dgr%3D0%26c_type%3D31%26flag%3D1%26cate%3D0%26realpos%3D8%26lcate%3D5001%26display_time%3D1657983945%26pre_seqid%3D16579839450170435141369&luicode=10000011&lfid=106003type%253D25%2526t%253D3%2526disable_hot%253D1%2526filter_type%253Drealtimehot","icon_height":24,"icon":"https:\/\/simg.s.weibo.com\/20210226_new.png","icon_width":24,"card_type":4,"pic":"https:\/\/simg.s.weibo.com\/20170303_img_search_8.png"},{"actionlog":{"act_code":554,"ext":"seqid:16579839450170435141369|t:31|cate:10103|key:#\u5fae\u5e97\u5d29\u4e86#|c_type:31|pos:1_8|page:1|type:25|dgr:0","luicode":"","act_type":1,"uicode":"","fid":"106003type=25&t=3&disable_hot=1&filter_type=realtimehot","lfid":""},"desc":"\u5fae\u5e97\u5d29\u4e86","desc_extr":806264,"itemid":"t:31|cate:10103|key:#\u5fae\u5e97\u5d29\u4e86#|c_type:31|pos:1-1-0||type:25","scheme":"https:\/\/m.weibo.cn\/search?containerid=100103type%3D1%26t%3D10%26q%3D%23%E5%BE%AE%E5%BA%97%E5%B4%A9%E4%BA%86%23&stream_entry_id=31&isnewpage=1&extparam=seat%3D1%26pos%3D8%26filter_type%3Drealtimehot%26dgr%3D0%26c_type%3D31%26flag%3D1%26cate%3D0%26realpos%3D9%26lcate%3D5001%26display_time%3D1657983945%26pre_seqid%3D16579839450170435141369&luicode=10000011&lfid=106003type%253D25%2526t%253D3%2526disable_hot%253D1%2526filter_type%253Drealtimehot","icon_height":24,"icon":"https:\/\/simg.s.weibo.com\/20210226_new.png","icon_width":24,"card_type":4,"pic":"https:\/\/simg.s.weibo.com\/20170303_img_search_9.png"},{"actionlog":{"act_code":554,"ext":"seqid:16579839450170435141369|t:31|cate:10103|key:#\u961a\u6e05\u5b50\u6a80\u5065\u6b21\u5b8b\u4ee3\u5a5a\u793c\u9020\u578b#|c_type:31|pos:1_9|page:1|type:25|dgr:0","luicode":"","act_type":1,"uicode":"","fid":"106003type=25&t=3&disable_hot=1&filter_type=realtimehot","lfid":""},"desc":"\u961a\u6e05\u5b50\u6a80\u5065\u6b21\u5b8b\u4ee3\u5a5a\u793c\u9020\u578b","desc_extr":"\u7efc\u827a 760471","itemid":"t:31|cate:10103|key:#\u961a\u6e05\u5b50\u6a80\u5065\u6b21\u5b8b\u4ee3\u5a5a\u793c\u9020\u578b#|c_type:31|pos:1-1-0||type:25","scheme":"https:\/\/m.weibo.cn\/search?containerid=100103type%3D1%26t%3D10%26q%3D%23%E9%98%9A%E6%B8%85%E5%AD%90%E6%AA%80%E5%81%A5%E6%AC%A1%E5%AE%8B%E4%BB%A3%E5%A9%9A%E7%A4%BC%E9%80%A0%E5%9E%8B%23&stream_entry_id=31&isnewpage=1&extparam=seat%3D1%26pos%3D9%26filter_type%3Drealtimehot%26dgr%3D0%26c_type%3D31%26flag%3D1%26cate%3D0%26realpos%3D10%26lcate%3D5001%26display_time%3D1657983945%26pre_seqid%3D16579839450170435141369&luicode=10000011&lfid=106003type%253D25%2526t%253D3%2526disable_hot%253D1%2526filter_type%253Drealtimehot","icon_height":24,"icon":"https:\/\/simg.s.weibo.com\/20210226_new.png","icon_width":24,"card_type":4,"pic":"https:\/\/simg.s.weibo.com\/20170303_img_search_10.png"},{"actionlog":{"act_code":554,"ext":"seqid:16579839450170435141369|t:31|cate:10103|key:#\u738b\u4fca\u51ef\u76f4\u64ad#|c_type:31|pos:1_10|page:1|type:25|dgr:0","luicode":"","act_type":1,"uicode":"","fid":"106003type=25&t=3&disable_hot=1&filter_type=realtimehot","lfid":""},"desc":"\u738b\u4fca\u51ef\u76f4\u64ad","desc_extr":751234,"itemid":"t:31|cate:10103|key:#\u738b\u4fca\u51ef\u76f4\u64ad#|c_type:31|pos:1-1-0||type:25","scheme":"https:\/\/m.weibo.cn\/search?containerid=100103type%3D1%26t%3D10%26q%3D%23%E7%8E%8B%E4%BF%8A%E5%87%AF%E7%9B%B4%E6%92%AD%23&stream_entry_id=31&isnewpage=1&extparam=seat%3D1%26pos%3D10%26filter_type%3Drealtimehot%26dgr%3D0%26c_type%3D31%26flag%3D0%26cate%3D0%26realpos%3D11%26lcate%3D5001%26display_time%3D1657983945%26pre_seqid%3D16579839450170435141369&luicode=10000011&lfid=106003type%253D25%2526t%253D3%2526disable_hot%253D1%2526filter_type%253Drealtimehot","icon_height":24,"card_type":4,"icon_width":24,"pic":"https:\/\/simg.s.weibo.com\/20170303_img_search_11.png"},{"actionlog":{"act_code":554,"ext":"seqid:16579839450170435141369|t:31|cate:10103|key:#\u4e0d\u914d\u5403\u996d#|c_type:31|pos:1_11|page:1|type:25|dgr:0","luicode":"","act_type":1,"uicode":"","fid":"106003type=25&t=3&disable_hot=1&filter_type=realtimehot","lfid":""},"desc":"\u4e0d\u914d\u5403\u996d","desc_extr":716804,"itemid":"t:31|cate:10103|key:#\u4e0d\u914d\u5403\u996d#|c_type:31|pos:1-1-0||type:25","scheme":"https:\/\/m.weibo.cn\/search?containerid=100103type%3D1%26t%3D10%26q%3D%23%E4%B8%8D%E9%85%8D%E5%90%83%E9%A5%AD%23&stream_entry_id=31&isnewpage=1&extparam=seat%3D1%26pos%3D11%26filter_type%3Drealtimehot%26dgr%3D0%26c_type%3D31%26flag%3D1%26cate%3D0%26realpos%3D12%26lcate%3D5001%26display_time%3D1657983945%26pre_seqid%3D16579839450170435141369&luicode=10000011&lfid=106003type%253D25%2526t%253D3%2526disable_hot%253D1%2526filter_type%253Drealtimehot","icon_height":24,"icon":"https:\/\/simg.s.weibo.com\/20210226_new.png","icon_width":24,"card_type":4,"pic":"https:\/\/simg.s.weibo.com\/20170303_img_search_12.png"},{"actionlog":{"act_code":554,"ext":"seqid:16579839450170435141369|t:31|cate:10103|key:#Angelababy\u90ed\u8299\u84c9\u9020\u578b#|c_type:31|pos:1_12|page:1|type:25|dgr:0","luicode":"","act_type":1,"uicode":"","fid":"106003type=25&t=3&disable_hot=1&filter_type=realtimehot","lfid":""},"desc":"Angelababy\u90ed\u8299\u84c9\u9020\u578b","desc_extr":"\u7efc\u827a 672732","itemid":"t:31|cate:10103|key:#Angelababy\u90ed\u8299\u84c9\u9020\u578b#|c_type:31|pos:1-1-0||type:25","scheme":"https:\/\/m.weibo.cn\/search?containerid=100103type%3D1%26t%3D10%26q%3D%23Angelababy%E9%83%AD%E8%8A%99%E8%93%89%E9%80%A0%E5%9E%8B%23&stream_entry_id=31&isnewpage=1&extparam=seat%3D1%26pos%3D12%26filter_type%3Drealtimehot%26dgr%3D0%26c_type%3D31%26flag%3D0%26cate%3D0%26realpos%3D13%26lcate%3D5001%26display_time%3D1657983945%26pre_seqid%3D16579839450170435141369&luicode=10000011&lfid=106003type%253D25%2526t%253D3%2526disable_hot%253D1%2526filter_type%253Drealtimehot","icon_height":24,"card_type":4,"icon_width":24,"pic":"https:\/\/simg.s.weibo.com\/20170303_img_search_13.png"},{"actionlog":{"act_code":554,"ext":"seqid:16579839450170435141369|t:31|cate:10103|key:#\u5317\u75352022\u7ea7\u8868\u6f14\u4e13\u4e1a\u672c\u79d1\u65b0\u751f\u540d\u5355#|c_type:31|pos:1_13|page:1|type:25|dgr:0","luicode":"","act_type":1,"uicode":"","fid":"106003type=25&t=3&disable_hot=1&filter_type=realtimehot","lfid":""},"desc":"\u5317\u75352022\u7ea7\u8868\u6f14\u4e13\u4e1a\u672c\u79d1\u65b0\u751f\u540d\u5355","desc_extr":654320,"itemid":"t:31|cate:10103|key:#\u5317\u75352022\u7ea7\u8868\u6f14\u4e13\u4e1a\u672c\u79d1\u65b0\u751f\u540d\u5355#|c_type:31|pos:1-1-0||type:25","scheme":"https:\/\/m.weibo.cn\/search?containerid=100103type%3D1%26t%3D10%26q%3D%23%E5%8C%97%E7%94%B52022%E7%BA%A7%E8%A1%A8%E6%BC%94%E4%B8%93%E4%B8%9A%E6%9C%AC%E7%A7%91%E6%96%B0%E7%94%9F%E5%90%8D%E5%8D%95%23&stream_entry_id=31&isnewpage=1&extparam=seat%3D1%26pos%3D13%26filter_type%3Drealtimehot%26dgr%3D0%26c_type%3D31%26flag%3D0%26cate%3D0%26realpos%3D14%26lcate%3D5001%26display_time%3D1657983945%26pre_seqid%3D16579839450170435141369&luicode=10000011&lfid=106003type%253D25%2526t%253D3%2526disable_hot%253D1%2526filter_type%253Drealtimehot","icon_height":24,"card_type":4,"icon_width":24,"pic":"https:\/\/simg.s.weibo.com\/20170303_img_search_14.png"},{"actionlog":{"act_code":554,"ext":"seqid:16579839450170435141369|t:31|cate:10103|key:#\u8857\u9053\u529e\u56de\u5e94\u6d12\u6c34\u8f66\u96e8\u5929\u516c\u56ed\u91cc\u8f6c\u5708\u6d12\u6c34#|c_type:31|pos:1_14|page:1|type:25|dgr:0","luicode":"","act_type":1,"uicode":"","fid":"106003type=25&t=3&disable_hot=1&filter_type=realtimehot","lfid":""},"desc":"\u8857\u9053\u529e\u56de\u5e94\u6d12\u6c34\u8f66\u96e8\u5929\u516c\u56ed\u91cc\u8f6c\u5708\u6d12\u6c34","desc_extr":625454,"itemid":"t:31|cate:10103|key:#\u8857\u9053\u529e\u56de\u5e94\u6d12\u6c34\u8f66\u96e8\u5929\u516c\u56ed\u91cc\u8f6c\u5708\u6d12\u6c34#|c_type:31|pos:1-1-0||type:25","scheme":"https:\/\/m.weibo.cn\/search?containerid=100103type%3D1%26t%3D10%26q%3D%23%E8%A1%97%E9%81%93%E5%8A%9E%E5%9B%9E%E5%BA%94%E6%B4%92%E6%B0%B4%E8%BD%A6%E9%9B%A8%E5%A4%A9%E5%85%AC%E5%9B%AD%E9%87%8C%E8%BD%AC%E5%9C%88%E6%B4%92%E6%B0%B4%23&stream_entry_id=31&isnewpage=1&extparam=seat%3D1%26pos%3D14%26filter_type%3Drealtimehot%26dgr%3D0%26c_type%3D31%26flag%3D1%26cate%3D0%26realpos%3D15%26lcate%3D5001%26display_time%3D1657983945%26pre_seqid%3D16579839450170435141369&luicode=10000011&lfid=106003type%253D25%2526t%253D3%2526disable_hot%253D1%2526filter_type%253Drealtimehot","icon_height":24,"icon":"https:\/\/simg.s.weibo.com\/20210226_new.png","icon_width":24,"card_type":4,"pic":"https:\/\/simg.s.weibo.com\/20170303_img_search_15.png"},{"actionlog":{"act_code":554,"ext":"seqid:16579839450170435141369|t:31|cate:10103|key:#\u8c2d\u7ef4\u7ef4\u5fae\u535a\u81ea\u52a8\u56de\u590d#|c_type:31|pos:1_15|page:1|type:25|dgr:0","luicode":"","act_type":1,"uicode":"","fid":"106003type=25&t=3&disable_hot=1&filter_type=realtimehot","lfid":""},"desc":"\u8c2d\u7ef4\u7ef4\u5fae\u535a\u81ea\u52a8\u56de\u590d","desc_extr":619504,"itemid":"t:31|cate:10103|key:#\u8c2d\u7ef4\u7ef4\u5fae\u535a\u81ea\u52a8\u56de\u590d#|c_type:31|pos:1-1-0||type:25","scheme":"https:\/\/m.weibo.cn\/search?containerid=100103type%3D1%26t%3D10%26q%3D%23%E8%B0%AD%E7%BB%B4%E7%BB%B4%E5%BE%AE%E5%8D%9A%E8%87%AA%E5%8A%A8%E5%9B%9E%E5%A4%8D%23&stream_entry_id=31&isnewpage=1&extparam=seat%3D1%26pos%3D15%26filter_type%3Drealtimehot%26dgr%3D0%26c_type%3D31%26flag%3D1%26cate%3D0%26realpos%3D16%26lcate%3D5001%26display_time%3D1657983945%26pre_seqid%3D16579839450170435141369&luicode=10000011&lfid=106003type%253D25%2526t%253D3%2526disable_hot%253D1%2526filter_type%253Drealtimehot","icon_height":24,"icon":"https:\/\/simg.s.weibo.com\/20210226_new.png","icon_width":24,"card_type":4,"pic":"https:\/\/simg.s.weibo.com\/20170303_img_search_16.png"},{"actionlog":{"act_code":554,"ext":"seqid:16579839450170435141369|t:31|cate:10103|key:\u80e1\u660e\u8f69|c_type:31|pos:1_16|page:1|type:25|dgr:0","luicode":"","act_type":1,"uicode":"","fid":"106003type=25&t=3&disable_hot=1&filter_type=realtimehot","lfid":""},"desc":"\u80e1\u660e\u8f69","desc_extr":605771,"itemid":"t:31|cate:10103|key:\u80e1\u660e\u8f69|c_type:31|pos:1-1-0||type:25","scheme":"https:\/\/m.weibo.cn\/search?containerid=100103type%3D1%26t%3D10%26q%3D%E8%83%A1%E6%98%8E%E8%BD%A9&stream_entry_id=31&isnewpage=1&extparam=seat%3D1%26pos%3D16%26filter_type%3Drealtimehot%26dgr%3D0%26c_type%3D31%26flag%3D1%26cate%3D0%26realpos%3D17%26lcate%3D5001%26display_time%3D1657983945%26pre_seqid%3D16579839450170435141369&luicode=10000011&lfid=106003type%253D25%2526t%253D3%2526disable_hot%253D1%2526filter_type%253Drealtimehot","icon_height":24,"icon":"https:\/\/simg.s.weibo.com\/20210226_new.png","icon_width":24,"card_type":4,"pic":"https:\/\/simg.s.weibo.com\/20170303_img_search_17.png"},{"actionlog":{"act_code":554,"ext":"seqid:16579839450170435141369|t:31|cate:10103|key:#RNG\u6210\u5458\u60bc\u5ff5\u9ec4\u83c1#|c_type:31|pos:1_17|page:1|type:25|dgr:0","luicode":"","act_type":1,"uicode":"","fid":"106003type=25&t=3&disable_hot=1&filter_type=realtimehot","lfid":""},"desc":"RNG\u6210\u5458\u60bc\u5ff5\u9ec4\u83c1","desc_extr":546412,"itemid":"t:31|cate:10103|key:#RNG\u6210\u5458\u60bc\u5ff5\u9ec4\u83c1#|c_type:31|pos:1-1-0||type:25","scheme":"https:\/\/m.weibo.cn\/search?containerid=100103type%3D1%26t%3D10%26q%3D%23RNG%E6%88%90%E5%91%98%E6%82%BC%E5%BF%B5%E9%BB%84%E8%8F%81%23&stream_entry_id=31&isnewpage=1&extparam=seat%3D1%26pos%3D17%26filter_type%3Drealtimehot%26dgr%3D0%26c_type%3D31%26flag%3D1%26cate%3D0%26realpos%3D18%26lcate%3D5001%26display_time%3D1657983945%26pre_seqid%3D16579839450170435141369&luicode=10000011&lfid=106003type%253D25%2526t%253D3%2526disable_hot%253D1%2526filter_type%253Drealtimehot","icon_height":24,"icon":"https:\/\/simg.s.weibo.com\/20210226_new.png","icon_width":24,"card_type":4,"pic":"https:\/\/simg.s.weibo.com\/20170303_img_search_18.png"},{"actionlog":{"act_code":554,"ext":"seqid:16579839450170435141369|t:31|cate:10103|key:#\u6709\u8c61\u7ea6\u8f66\u56de\u5e94\u5973\u751f\u8eab\u4ea1#|c_type:31|pos:1_18|page:1|type:25|dgr:0","luicode":"","act_type":1,"uicode":"","fid":"106003type=25&t=3&disable_hot=1&filter_type=realtimehot","lfid":""},"desc":"\u6709\u8c61\u7ea6\u8f66\u56de\u5e94\u5973\u751f\u8eab\u4ea1","desc_extr":469557,"itemid":"t:31|cate:10103|key:#\u6709\u8c61\u7ea6\u8f66\u56de\u5e94\u5973\u751f\u8eab\u4ea1#|c_type:31|pos:1-1-0||type:25","scheme":"https:\/\/m.weibo.cn\/search?containerid=100103type%3D1%26t%3D10%26q%3D%23%E6%9C%89%E8%B1%A1%E7%BA%A6%E8%BD%A6%E5%9B%9E%E5%BA%94%E5%A5%B3%E7%94%9F%E8%BA%AB%E4%BA%A1%23&stream_entry_id=31&isnewpage=1&extparam=seat%3D1%26pos%3D18%26filter_type%3Drealtimehot%26dgr%3D0%26c_type%3D31%26flag%3D0%26cate%3D0%26realpos%3D19%26lcate%3D5001%26display_time%3D1657983945%26pre_seqid%3D16579839450170435141369&luicode=10000011&lfid=106003type%253D25%2526t%253D3%2526disable_hot%253D1%2526filter_type%253Drealtimehot","icon_height":24,"card_type":4,"icon_width":24,"pic":"https:\/\/simg.s.weibo.com\/20170303_img_search_19.png"},{"actionlog":{"act_code":554,"ext":"seqid:16579839450170435141369|t:31|cate:10103|key:#\u4e2d\u56fd\u961f6\u4eba\u5168\u6ee1\u5206\u83b7\u56fd\u9645\u5965\u6570\u51a0\u519b#|c_type:31|pos:1_19|page:1|type:25|dgr:0","luicode":"","act_type":1,"uicode":"","fid":"106003type=25&t=3&disable_hot=1&filter_type=realtimehot","lfid":""},"desc":"\u4e2d\u56fd\u961f6\u4eba\u5168\u6ee1\u5206\u83b7\u56fd\u9645\u5965\u6570\u51a0\u519b","desc_extr":432392,"itemid":"t:31|cate:10103|key:#\u4e2d\u56fd\u961f6\u4eba\u5168\u6ee1\u5206\u83b7\u56fd\u9645\u5965\u6570\u51a0\u519b#|c_type:31|pos:1-1-0||type:25","scheme":"https:\/\/m.weibo.cn\/search?containerid=100103type%3D1%26t%3D10%26q%3D%23%E4%B8%AD%E5%9B%BD%E9%98%9F6%E4%BA%BA%E5%85%A8%E6%BB%A1%E5%88%86%E8%8E%B7%E5%9B%BD%E9%99%85%E5%A5%A5%E6%95%B0%E5%86%A0%E5%86%9B%23&stream_entry_id=31&isnewpage=1&extparam=seat%3D1%26pos%3D19%26filter_type%3Drealtimehot%26dgr%3D0%26c_type%3D31%26flag%3D0%26cate%3D0%26realpos%3D20%26lcate%3D5001%26display_time%3D1657983945%26pre_seqid%3D16579839450170435141369&luicode=10000011&lfid=106003type%253D25%2526t%253D3%2526disable_hot%253D1%2526filter_type%253Drealtimehot","icon_height":24,"card_type":4,"icon_width":24,"pic":"https:\/\/simg.s.weibo.com\/20170303_img_search_20.png"},{"actionlog":{"act_code":554,"ext":"seqid:16579839450170435141369|t:31|cate:10103|key:#\u4f60\u597d\u661f\u671f\u516d\u4e0b\u671f\u9884\u544a\u6709\u6768\u7d2b#|c_type:31|pos:1_20|page:1|type:25|dgr:0","luicode":"","act_type":1,"uicode":"","fid":"106003type=25&t=3&disable_hot=1&filter_type=realtimehot","lfid":""},"desc":"\u4f60\u597d\u661f\u671f\u516d\u4e0b\u671f\u9884\u544a\u6709\u6768\u7d2b","desc_extr":"\u7efc\u827a 431906","itemid":"t:31|cate:10103|key:#\u4f60\u597d\u661f\u671f\u516d\u4e0b\u671f\u9884\u544a\u6709\u6768\u7d2b#|c_type:31|pos:1-1-0||type:25","scheme":"https:\/\/m.weibo.cn\/search?containerid=100103type%3D1%26t%3D10%26q%3D%23%E4%BD%A0%E5%A5%BD%E6%98%9F%E6%9C%9F%E5%85%AD%E4%B8%8B%E6%9C%9F%E9%A2%84%E5%91%8A%E6%9C%89%E6%9D%A8%E7%B4%AB%23&stream_entry_id=31&isnewpage=1&extparam=seat%3D1%26pos%3D20%26filter_type%3Drealtimehot%26dgr%3D0%26c_type%3D31%26flag%3D1%26cate%3D0%26realpos%3D21%26lcate%3D5001%26display_time%3D1657983945%26pre_seqid%3D16579839450170435141369&luicode=10000011&lfid=106003type%253D25%2526t%253D3%2526disable_hot%253D1%2526filter_type%253Drealtimehot","icon_height":24,"icon":"https:\/\/simg.s.weibo.com\/20210226_new.png","icon_width":24,"card_type":4,"pic":"https:\/\/simg.s.weibo.com\/20170303_img_search_21.png"},{"actionlog":{"act_code":554,"ext":"seqid:16579839450170435141369|t:31|cate:10103|key:#\u5085\u83c1\u97f3\u4e50\u4f1a\u7968\u4ef7#|c_type:31|pos:1_21|page:1|type:25|dgr:0","luicode":"","act_type":1,"uicode":"","fid":"106003type=25&t=3&disable_hot=1&filter_type=realtimehot","lfid":""},"desc":"\u5085\u83c1\u97f3\u4e50\u4f1a\u7968\u4ef7","desc_extr":"\u97f3\u4e50 430826","itemid":"t:31|cate:10103|key:#\u5085\u83c1\u97f3\u4e50\u4f1a\u7968\u4ef7#|c_type:31|pos:1-1-0||type:25","scheme":"https:\/\/m.weibo.cn\/search?containerid=100103type%3D1%26t%3D10%26q%3D%23%E5%82%85%E8%8F%81%E9%9F%B3%E4%B9%90%E4%BC%9A%E7%A5%A8%E4%BB%B7%23&stream_entry_id=31&isnewpage=1&extparam=seat%3D1%26pos%3D21%26filter_type%3Drealtimehot%26dgr%3D0%26c_type%3D31%26flag%3D0%26cate%3D0%26realpos%3D22%26lcate%3D5001%26display_time%3D1657983945%26pre_seqid%3D16579839450170435141369&luicode=10000011&lfid=106003type%253D25%2526t%253D3%2526disable_hot%253D1%2526filter_type%253Drealtimehot","icon_height":24,"card_type":4,"icon_width":24,"pic":"https:\/\/simg.s.weibo.com\/20170303_img_search_22.png"},{"actionlog":{"act_code":554,"ext":"seqid:16579839450170435141369|t:31|cate:10103|key:\u72fc\u961f \u5c0f\u80d6|c_type:31|pos:1_22|page:1|type:25|dgr:0","luicode":"","act_type":1,"uicode":"","fid":"106003type=25&t=3&disable_hot=1&filter_type=realtimehot","lfid":""},"desc":"\u72fc\u961f \u5c0f\u80d6","desc_extr":423654,"itemid":"t:31|cate:10103|key:\u72fc\u961f \u5c0f\u80d6|c_type:31|pos:1-1-0||type:25","scheme":"https:\/\/m.weibo.cn\/search?containerid=100103type%3D1%26t%3D10%26q%3D%E7%8B%BC%E9%98%9F+%E5%B0%8F%E8%83%96&stream_entry_id=31&isnewpage=1&extparam=seat%3D1%26pos%3D22%26filter_type%3Drealtimehot%26dgr%3D0%26c_type%3D31%26flag%3D0%26cate%3D0%26realpos%3D23%26lcate%3D5001%26display_time%3D1657983945%26pre_seqid%3D16579839450170435141369&luicode=10000011&lfid=106003type%253D25%2526t%253D3%2526disable_hot%253D1%2526filter_type%253Drealtimehot","icon_height":24,"card_type":4,"icon_width":24,"pic":"https:\/\/simg.s.weibo.com\/20170303_img_search_23.png"},{"actionlog":{"act_code":554,"ext":"seqid:16579839450170435141369|t:31|cate:10103|key:#\u5468\u7426\u5927\u5e3d#|c_type:31|pos:1_23|page:1|type:25|dgr:0","luicode":"","act_type":1,"uicode":"","fid":"106003type=25&t=3&disable_hot=1&filter_type=realtimehot","lfid":""},"desc":"\u5468\u7426\u5927\u5e3d","desc_extr":376908,"itemid":"t:31|cate:10103|key:#\u5468\u7426\u5927\u5e3d#|c_type:31|pos:1-1-0||type:25","scheme":"https:\/\/m.weibo.cn\/search?containerid=100103type%3D1%26t%3D10%26q%3D%23%E5%91%A8%E7%90%A6%E5%A4%A7%E5%B8%BD%23&stream_entry_id=31&isnewpage=1&extparam=seat%3D1%26pos%3D23%26filter_type%3Drealtimehot%26dgr%3D0%26c_type%3D31%26flag%3D1%26cate%3D0%26realpos%3D24%26lcate%3D5001%26display_time%3D1657983945%26pre_seqid%3D16579839450170435141369&luicode=10000011&lfid=106003type%253D25%2526t%253D3%2526disable_hot%253D1%2526filter_type%253Drealtimehot","icon_height":24,"icon":"https:\/\/simg.s.weibo.com\/20210226_new.png","icon_width":24,"card_type":4,"pic":"https:\/\/simg.s.weibo.com\/20170303_img_search_24.png"},{"actionlog":{"act_code":554,"ext":"seqid:16579839450170435141369|t:31|cate:10103|key:\u6df7\u53cc|c_type:31|pos:1_24|page:1|type:25|dgr:0","luicode":"","act_type":1,"uicode":"","fid":"106003type=25&t=3&disable_hot=1&filter_type=realtimehot","lfid":""},"desc":"\u6df7\u53cc","desc_extr":347225,"itemid":"t:31|cate:10103|key:\u6df7\u53cc|c_type:31|pos:1-1-0||type:25","scheme":"https:\/\/m.weibo.cn\/search?containerid=100103type%3D1%26t%3D10%26q%3D%E6%B7%B7%E5%8F%8C&stream_entry_id=31&isnewpage=1&extparam=seat%3D1%26pos%3D24%26filter_type%3Drealtimehot%26dgr%3D0%26c_type%3D31%26flag%3D1%26cate%3D0%26realpos%3D25%26lcate%3D5001%26display_time%3D1657983945%26pre_seqid%3D16579839450170435141369&luicode=10000011&lfid=106003type%253D25%2526t%253D3%2526disable_hot%253D1%2526filter_type%253Drealtimehot","icon_height":24,"icon":"https:\/\/simg.s.weibo.com\/20210226_new.png","icon_width":24,"card_type":4,"pic":"https:\/\/simg.s.weibo.com\/20170303_img_search_25.png"},{"actionlog":{"act_code":554,"ext":"seqid:16579839450170435141369|t:31|cate:10103|key:\u8bb8\u5d69 \u4f60\u597d\u661f\u671f\u516d|c_type:31|pos:1_25|page:1|type:25|dgr:0","luicode":"","act_type":1,"uicode":"","fid":"106003type=25&t=3&disable_hot=1&filter_type=realtimehot","lfid":""},"desc":"\u8bb8\u5d69 \u4f60\u597d\u661f\u671f\u516d","desc_extr":"\u7efc\u827a 338982","itemid":"t:31|cate:10103|key:\u8bb8\u5d69 \u4f60\u597d\u661f\u671f\u516d|c_type:31|pos:1-1-0||type:25","scheme":"https:\/\/m.weibo.cn\/search?containerid=100103type%3D1%26t%3D10%26q%3D%E8%AE%B8%E5%B5%A9+%E4%BD%A0%E5%A5%BD%E6%98%9F%E6%9C%9F%E5%85%AD&stream_entry_id=31&isnewpage=1&extparam=seat%3D1%26pos%3D25%26filter_type%3Drealtimehot%26dgr%3D0%26c_type%3D31%26flag%3D1%26cate%3D0%26realpos%3D26%26lcate%3D5001%26display_time%3D1657983945%26pre_seqid%3D16579839450170435141369&luicode=10000011&lfid=106003type%253D25%2526t%253D3%2526disable_hot%253D1%2526filter_type%253Drealtimehot","icon_height":24,"icon":"https:\/\/simg.s.weibo.com\/20210226_new.png","icon_width":24,"card_type":4,"pic":"https:\/\/simg.s.weibo.com\/20170303_img_search_26.png"},{"actionlog":{"act_code":554,"ext":"seqid:16579839450170435141369|t:31|cate:10103|key:#\u738b\u695a\u94a6\u738b\u66fc\u6631\u6df7\u53cc\u593a\u51a0#|c_type:31|pos:1_26|page:1|type:25|dgr:0","luicode":"","act_type":1,"uicode":"","fid":"106003type=25&t=3&disable_hot=1&filter_type=realtimehot","lfid":""},"desc":"\u738b\u695a\u94a6\u738b\u66fc\u6631\u6df7\u53cc\u593a\u51a0","desc_extr":328423,"itemid":"t:31|cate:10103|key:#\u738b\u695a\u94a6\u738b\u66fc\u6631\u6df7\u53cc\u593a\u51a0#|c_type:31|pos:1-1-0||type:25","scheme":"https:\/\/m.weibo.cn\/search?containerid=100103type%3D1%26t%3D10%26q%3D%23%E7%8E%8B%E6%A5%9A%E9%92%A6%E7%8E%8B%E6%9B%BC%E6%98%B1%E6%B7%B7%E5%8F%8C%E5%A4%BA%E5%86%A0%23&stream_entry_id=31&isnewpage=1&extparam=seat%3D1%26pos%3D26%26filter_type%3Drealtimehot%26dgr%3D0%26c_type%3D31%26flag%3D1%26cate%3D0%26realpos%3D27%26lcate%3D5001%26display_time%3D1657983945%26pre_seqid%3D16579839450170435141369&luicode=10000011&lfid=106003type%253D25%2526t%253D3%2526disable_hot%253D1%2526filter_type%253Drealtimehot","icon_height":24,"icon":"https:\/\/simg.s.weibo.com\/20210226_new.png","icon_width":24,"card_type":4,"pic":"https:\/\/simg.s.weibo.com\/20170303_img_search_27.png"},{"actionlog":{"act_code":554,"ext":"seqid:16579839450170435141369|t:31|cate:10103|key:#\u5988\u5988\u9669\u88ab\u649e\u5c0f\u5973\u5b69\u558a\u8bdd\u8f66\u4e3b\u4e0b\u6765\u9053\u6b49#|c_type:31|pos:1_27|page:1|type:25|dgr:0","luicode":"","act_type":1,"uicode":"","fid":"106003type=25&t=3&disable_hot=1&filter_type=realtimehot","lfid":""},"desc":"\u5988\u5988\u9669\u88ab\u649e\u5c0f\u5973\u5b69\u558a\u8bdd\u8f66\u4e3b\u4e0b\u6765\u9053\u6b49","desc_extr":309347,"itemid":"t:31|cate:10103|key:#\u5988\u5988\u9669\u88ab\u649e\u5c0f\u5973\u5b69\u558a\u8bdd\u8f66\u4e3b\u4e0b\u6765\u9053\u6b49#|c_type:31|pos:1-1-0||type:25","scheme":"https:\/\/m.weibo.cn\/search?containerid=100103type%3D1%26t%3D10%26q%3D%23%E5%A6%88%E5%A6%88%E9%99%A9%E8%A2%AB%E6%92%9E%E5%B0%8F%E5%A5%B3%E5%AD%A9%E5%96%8A%E8%AF%9D%E8%BD%A6%E4%B8%BB%E4%B8%8B%E6%9D%A5%E9%81%93%E6%AD%89%23&stream_entry_id=31&isnewpage=1&extparam=seat%3D1%26pos%3D27%26filter_type%3Drealtimehot%26dgr%3D0%26c_type%3D31%26flag%3D0%26cate%3D0%26realpos%3D28%26lcate%3D5001%26display_time%3D1657983945%26pre_seqid%3D16579839450170435141369&luicode=10000011&lfid=106003type%253D25%2526t%253D3%2526disable_hot%253D1%2526filter_type%253Drealtimehot","icon_height":24,"card_type":4,"icon_width":24,"pic":"https:\/\/simg.s.weibo.com\/20170303_img_search_28.png"},{"actionlog":{"act_code":554,"ext":"seqid:16579839450170435141369|t:31|cate:10103|key:#\u738b\u695a\u94a6\u738b\u66fc\u66313\u6bd42\u5f20\u672c\u667a\u548c\u65e9\u7530\u5e0c\u5a1c#|c_type:31|pos:1_28|page:1|type:25|dgr:0","luicode":"","act_type":1,"uicode":"","fid":"106003type=25&t=3&disable_hot=1&filter_type=realtimehot","lfid":""},"desc":"\u738b\u695a\u94a6\u738b\u66fc\u66313\u6bd42\u5f20\u672c\u667a\u548c\u65e9\u7530\u5e0c\u5a1c","desc_extr":306515,"itemid":"t:31|cate:10103|key:#\u738b\u695a\u94a6\u738b\u66fc\u66313\u6bd42\u5f20\u672c\u667a\u548c\u65e9\u7530\u5e0c\u5a1c#|c_type:31|pos:1-1-0||type:25","scheme":"https:\/\/m.weibo.cn\/search?containerid=100103type%3D1%26t%3D10%26q%3D%23%E7%8E%8B%E6%A5%9A%E9%92%A6%E7%8E%8B%E6%9B%BC%E6%98%B13%E6%AF%942%E5%BC%A0%E6%9C%AC%E6%99%BA%E5%92%8C%E6%97%A9%E7%94%B0%E5%B8%8C%E5%A8%9C%23&stream_entry_id=31&isnewpage=1&extparam=seat%3D1%26pos%3D28%26filter_type%3Drealtimehot%26dgr%3D0%26c_type%3D31%26flag%3D1%26cate%3D0%26realpos%3D29%26lcate%3D5001%26display_time%3D1657983945%26pre_seqid%3D16579839450170435141369&luicode=10000011&lfid=106003type%253D25%2526t%253D3%2526disable_hot%253D1%2526filter_type%253Drealtimehot","icon_height":24,"icon":"https:\/\/simg.s.weibo.com\/20210226_new.png","icon_width":24,"card_type":4,"pic":"https:\/\/simg.s.weibo.com\/20170303_img_search_29.png"},{"actionlog":{"act_code":554,"ext":"seqid:16579839450170435141369|t:31|cate:10103|key:#\u7535\u529b\u5de5\u4eba\u572879\u7c73\u9ad8\u7a7a\u5403\u897f\u74dc\u964d\u6691#|c_type:31|pos:1_29|page:1|type:25|dgr:0","luicode":"","act_type":1,"uicode":"","fid":"106003type=25&t=3&disable_hot=1&filter_type=realtimehot","lfid":""},"desc":"\u7535\u529b\u5de5\u4eba\u572879\u7c73\u9ad8\u7a7a\u5403\u897f\u74dc\u964d\u6691","desc_extr":303061,"itemid":"t:31|cate:10103|key:#\u7535\u529b\u5de5\u4eba\u572879\u7c73\u9ad8\u7a7a\u5403\u897f\u74dc\u964d\u6691#|c_type:31|pos:1-1-0||type:25","scheme":"https:\/\/m.weibo.cn\/search?containerid=100103type%3D1%26t%3D10%26q%3D%23%E7%94%B5%E5%8A%9B%E5%B7%A5%E4%BA%BA%E5%9C%A879%E7%B1%B3%E9%AB%98%E7%A9%BA%E5%90%83%E8%A5%BF%E7%93%9C%E9%99%8D%E6%9A%91%23&stream_entry_id=31&isnewpage=1&extparam=seat%3D1%26pos%3D29%26filter_type%3Drealtimehot%26dgr%3D0%26c_type%3D31%26flag%3D0%26cate%3D0%26realpos%3D30%26lcate%3D5001%26display_time%3D1657983945%26pre_seqid%3D16579839450170435141369&luicode=10000011&lfid=106003type%253D25%2526t%253D3%2526disable_hot%253D1%2526filter_type%253Drealtimehot","icon_height":24,"card_type":4,"icon_width":24,"pic":"https:\/\/simg.s.weibo.com\/20170303_img_search_30.png"},{"actionlog":{"act_code":554,"ext":"seqid:16579839450170435141369|t:31|cate:10103|key:#\u4ec0\u4e48\u65f6\u5019\u624d\u80fd\u4e0d\u4e3a\u53cb\u8c0aemo#|c_type:31|pos:1_30|page:1|type:25|dgr:0","luicode":"","act_type":1,"uicode":"","fid":"106003type=25&t=3&disable_hot=1&filter_type=realtimehot","lfid":""},"desc":"\u4ec0\u4e48\u65f6\u5019\u624d\u80fd\u4e0d\u4e3a\u53cb\u8c0aemo","desc_extr":296268,"itemid":"t:31|cate:10103|key:#\u4ec0\u4e48\u65f6\u5019\u624d\u80fd\u4e0d\u4e3a\u53cb\u8c0aemo#|c_type:31|pos:1-1-0||type:25","scheme":"https:\/\/m.weibo.cn\/search?containerid=100103type%3D1%26t%3D10%26q%3D%23%E4%BB%80%E4%B9%88%E6%97%B6%E5%80%99%E6%89%8D%E8%83%BD%E4%B8%8D%E4%B8%BA%E5%8F%8B%E8%B0%8Aemo%23&stream_entry_id=31&isnewpage=1&extparam=seat%3D1%26pos%3D30%26filter_type%3Drealtimehot%26dgr%3D0%26c_type%3D31%26flag%3D1%26cate%3D0%26realpos%3D31%26lcate%3D5001%26display_time%3D1657983945%26pre_seqid%3D16579839450170435141369&luicode=10000011&lfid=106003type%253D25%2526t%253D3%2526disable_hot%253D1%2526filter_type%253Drealtimehot","icon_height":24,"icon":"https:\/\/simg.s.weibo.com\/20210226_new.png","icon_width":24,"card_type":4,"pic":"https:\/\/simg.s.weibo.com\/20170303_img_search_31.png"},{"actionlog":{"act_code":554,"ext":"seqid:16579839450170435141369|t:31|cate:10103|key:\u4e9a\u59ae\u5988\u5988|c_type:31|pos:1_31|page:1|type:25|dgr:0","luicode":"","act_type":1,"uicode":"","fid":"106003type=25&t=3&disable_hot=1&filter_type=realtimehot","lfid":""},"desc":"\u4e9a\u59ae\u5988\u5988","desc_extr":"\u5267\u96c6 280891","itemid":"t:31|cate:10103|key:\u4e9a\u59ae\u5988\u5988|c_type:31|pos:1-1-0||type:25","scheme":"https:\/\/m.weibo.cn\/search?containerid=100103type%3D1%26t%3D10%26q%3D%E4%BA%9A%E5%A6%AE%E5%A6%88%E5%A6%88&stream_entry_id=31&isnewpage=1&extparam=seat%3D1%26pos%3D31%26filter_type%3Drealtimehot%26dgr%3D0%26c_type%3D31%26flag%3D0%26cate%3D0%26realpos%3D32%26lcate%3D5001%26display_time%3D1657983945%26pre_seqid%3D16579839450170435141369&luicode=10000011&lfid=106003type%253D25%2526t%253D3%2526disable_hot%253D1%2526filter_type%253Drealtimehot","icon_height":24,"card_type":4,"icon_width":24,"pic":"https:\/\/simg.s.weibo.com\/20170303_img_search_32.png"},{"actionlog":{"act_code":554,"ext":"seqid:16579839450170435141369|t:31|cate:10103|key:#\u4e2d\u56fd\u7537\u7beevs\u4e2d\u56fd\u53f0\u5317\u7537\u7bee#|c_type:31|pos:1_32|page:1|type:25|dgr:0","luicode":"","act_type":1,"uicode":"","fid":"106003type=25&t=3&disable_hot=1&filter_type=realtimehot","lfid":""},"desc":"\u4e2d\u56fd\u7537\u7beevs\u4e2d\u56fd\u53f0\u5317\u7537\u7bee","desc_extr":272322,"itemid":"t:31|cate:10103|key:#\u4e2d\u56fd\u7537\u7beevs\u4e2d\u56fd\u53f0\u5317\u7537\u7bee#|c_type:31|pos:1-1-0||type:25","scheme":"http:\/\/m.weibo.cn\/c\/wbox?&id=j84w2uenjc&roomid=10798&q=%23%E4%B8%AD%E5%9B%BD%E7%94%B7%E7%AF%AEvs%E4%B8%AD%E5%9B%BD%E5%8F%B0%E5%8C%97%E7%94%B7%E7%AF%AE%23&extparam=seat%3D1%26pos%3D32%26filter_type%3Drealtimehot%26dgr%3D0%26c_type%3D31%26flag%3D0%26cate%3D0%26realpos%3D33%26lcate%3D5001%26display_time%3D1657983945%26pre_seqid%3D16579839450170435141369&luicode=10000011&lfid=106003type%253D25%2526t%253D3%2526disable_hot%253D1%2526filter_type%253Drealtimehot","icon_height":24,"card_type":4,"icon_width":24,"pic":"https:\/\/simg.s.weibo.com\/20170303_img_search_33.png"},{"actionlog":{"act_code":554,"ext":"seqid:16579839450170435141369|t:31|cate:10103|key:#\u82cf\u70b3\u6dfb\u8bf4\u5bf9\u4e0d\u8d77\u5927\u5bb6\u4f46\u4f1a\u7ee7\u7eed\u52aa\u529b#|c_type:31|pos:1_33|page:1|type:25|dgr:0","luicode":"","act_type":1,"uicode":"","fid":"106003type=25&t=3&disable_hot=1&filter_type=realtimehot","lfid":""},"desc":"\u82cf\u70b3\u6dfb\u8bf4\u5bf9\u4e0d\u8d77\u5927\u5bb6\u4f46\u4f1a\u7ee7\u7eed\u52aa\u529b","desc_extr":266771,"itemid":"t:31|cate:10103|key:#\u82cf\u70b3\u6dfb\u8bf4\u5bf9\u4e0d\u8d77\u5927\u5bb6\u4f46\u4f1a\u7ee7\u7eed\u52aa\u529b#|c_type:31|pos:1-1-0||type:25","scheme":"https:\/\/m.weibo.cn\/search?containerid=100103type%3D1%26t%3D10%26q%3D%23%E8%8B%8F%E7%82%B3%E6%B7%BB%E8%AF%B4%E5%AF%B9%E4%B8%8D%E8%B5%B7%E5%A4%A7%E5%AE%B6%E4%BD%86%E4%BC%9A%E7%BB%A7%E7%BB%AD%E5%8A%AA%E5%8A%9B%23&stream_entry_id=31&isnewpage=1&extparam=seat%3D1%26pos%3D33%26filter_type%3Drealtimehot%26dgr%3D0%26c_type%3D31%26flag%3D0%26cate%3D0%26realpos%3D34%26lcate%3D5001%26display_time%3D1657983945%26pre_seqid%3D16579839450170435141369&luicode=10000011&lfid=106003type%253D25%2526t%253D3%2526disable_hot%253D1%2526filter_type%253Drealtimehot","icon_height":24,"card_type":4,"icon_width":24,"pic":"https:\/\/simg.s.weibo.com\/20170303_img_search_34.png"},{"actionlog":{"act_code":554,"ext":"seqid:16579839450170435141369|t:31|cate:10103|key:#\u4e2d\u56fd\u7537\u7bee\u6218\u80dc\u4e2d\u56fd\u53f0\u5317\u7537\u7bee#|c_type:31|pos:1_34|page:1|type:25|dgr:0","luicode":"","act_type":1,"uicode":"","fid":"106003type=25&t=3&disable_hot=1&filter_type=realtimehot","lfid":""},"desc":"\u4e2d\u56fd\u7537\u7bee\u6218\u80dc\u4e2d\u56fd\u53f0\u5317\u7537\u7bee","desc_extr":265180,"itemid":"t:31|cate:10103|key:#\u4e2d\u56fd\u7537\u7bee\u6218\u80dc\u4e2d\u56fd\u53f0\u5317\u7537\u7bee#|c_type:31|pos:1-1-0||type:25","scheme":"https:\/\/m.weibo.cn\/search?containerid=100103type%3D1%26t%3D10%26q%3D%23%E4%B8%AD%E5%9B%BD%E7%94%B7%E7%AF%AE%E6%88%98%E8%83%9C%E4%B8%AD%E5%9B%BD%E5%8F%B0%E5%8C%97%E7%94%B7%E7%AF%AE%23&stream_entry_id=31&isnewpage=1&extparam=seat%3D1%26pos%3D34%26filter_type%3Drealtimehot%26dgr%3D0%26c_type%3D31%26flag%3D1%26cate%3D0%26realpos%3D35%26lcate%3D5001%26display_time%3D1657983945%26pre_seqid%3D16579839450170435141369&luicode=10000011&lfid=106003type%253D25%2526t%253D3%2526disable_hot%253D1%2526filter_type%253Drealtimehot","icon_height":24,"icon":"https:\/\/simg.s.weibo.com\/20210226_new.png","icon_width":24,"card_type":4,"pic":"https:\/\/simg.s.weibo.com\/20170303_img_search_35.png"},{"actionlog":{"act_code":554,"ext":"seqid:16579839450170435141369|t:31|cate:10103|key:#\u539f\u6765\u771f\u7684\u4f1a\u6709\u4eba\u7b11\u7740\u8d70\u51fa\u7406\u53d1\u5e97#|c_type:31|pos:1_35|page:1|type:25|dgr:0","luicode":"","act_type":1,"uicode":"","fid":"106003type=25&t=3&disable_hot=1&filter_type=realtimehot","lfid":""},"desc":"\u539f\u6765\u771f\u7684\u4f1a\u6709\u4eba\u7b11\u7740\u8d70\u51fa\u7406\u53d1\u5e97","desc_extr":258494,"itemid":"t:31|cate:10103|key:#\u539f\u6765\u771f\u7684\u4f1a\u6709\u4eba\u7b11\u7740\u8d70\u51fa\u7406\u53d1\u5e97#|c_type:31|pos:1-1-0||type:25","scheme":"https:\/\/m.weibo.cn\/search?containerid=100103type%3D1%26t%3D10%26q%3D%23%E5%8E%9F%E6%9D%A5%E7%9C%9F%E7%9A%84%E4%BC%9A%E6%9C%89%E4%BA%BA%E7%AC%91%E7%9D%80%E8%B5%B0%E5%87%BA%E7%90%86%E5%8F%91%E5%BA%97%23&stream_entry_id=31&isnewpage=1&extparam=seat%3D1%26pos%3D35%26filter_type%3Drealtimehot%26dgr%3D0%26c_type%3D31%26flag%3D0%26cate%3D0%26realpos%3D36%26lcate%3D5001%26display_time%3D1657983945%26pre_seqid%3D16579839450170435141369&luicode=10000011&lfid=106003type%253D25%2526t%253D3%2526disable_hot%253D1%2526filter_type%253Drealtimehot","icon_height":24,"card_type":4,"icon_width":24,"pic":"https:\/\/simg.s.weibo.com\/20170303_img_search_36.png"},{"actionlog":{"act_code":554,"ext":"seqid:16579839450170435141369|t:31|cate:10103|key:#\u54ea\u4e9b\u884c\u4e3a\u53ef\u80fd\u5bfc\u81f4\u810a\u67f1\u4fa7\u5f2f#|c_type:31|pos:1_36|page:1|type:25|dgr:0","luicode":"","act_type":1,"uicode":"","fid":"106003type=25&t=3&disable_hot=1&filter_type=realtimehot","lfid":""},"desc":"\u54ea\u4e9b\u884c\u4e3a\u53ef\u80fd\u5bfc\u81f4\u810a\u67f1\u4fa7\u5f2f","desc_extr":233804,"itemid":"t:31|cate:10103|key:#\u54ea\u4e9b\u884c\u4e3a\u53ef\u80fd\u5bfc\u81f4\u810a\u67f1\u4fa7\u5f2f#|c_type:31|pos:1-1-0||type:25","scheme":"https:\/\/m.weibo.cn\/search?containerid=100103type%3D1%26t%3D10%26q%3D%23%E5%93%AA%E4%BA%9B%E8%A1%8C%E4%B8%BA%E5%8F%AF%E8%83%BD%E5%AF%BC%E8%87%B4%E8%84%8A%E6%9F%B1%E4%BE%A7%E5%BC%AF%23&stream_entry_id=31&isnewpage=1&extparam=seat%3D1%26pos%3D36%26filter_type%3Drealtimehot%26dgr%3D0%26c_type%3D31%26flag%3D1%26cate%3D0%26realpos%3D37%26lcate%3D5001%26display_time%3D1657983945%26pre_seqid%3D16579839450170435141369&luicode=10000011&lfid=106003type%253D25%2526t%253D3%2526disable_hot%253D1%2526filter_type%253Drealtimehot","icon_height":24,"icon":"https:\/\/simg.s.weibo.com\/20210226_new.png","icon_width":24,"card_type":4,"pic":"https:\/\/simg.s.weibo.com\/20170303_img_search_37.png"},{"actionlog":{"act_code":554,"ext":"seqid:16579839450170435141369|t:31|cate:10103|key:#\u5efa\u8bae\u9648\u66fc\u4e0b\u53cd\u8bc8APP#|c_type:31|pos:1_37|page:1|type:25|dgr:0","luicode":"","act_type":1,"uicode":"","fid":"106003type=25&t=3&disable_hot=1&filter_type=realtimehot","lfid":""},"desc":"\u5efa\u8bae\u9648\u66fc\u4e0b\u53cd\u8bc8APP","desc_extr":"\u5267\u96c6 233677","itemid":"t:31|cate:10103|key:#\u5efa\u8bae\u9648\u66fc\u4e0b\u53cd\u8bc8APP#|c_type:31|pos:1-1-0||type:25","scheme":"https:\/\/m.weibo.cn\/search?containerid=100103type%3D1%26t%3D10%26q%3D%23%E5%BB%BA%E8%AE%AE%E9%99%88%E6%9B%BC%E4%B8%8B%E5%8F%8D%E8%AF%88APP%23&stream_entry_id=31&isnewpage=1&extparam=seat%3D1%26pos%3D37%26filter_type%3Drealtimehot%26dgr%3D0%26c_type%3D31%26flag%3D1%26cate%3D0%26realpos%3D38%26lcate%3D5001%26display_time%3D1657983945%26pre_seqid%3D16579839450170435141369&luicode=10000011&lfid=106003type%253D25%2526t%253D3%2526disable_hot%253D1%2526filter_type%253Drealtimehot","icon_height":24,"icon":"https:\/\/simg.s.weibo.com\/20210226_new.png","icon_width":24,"card_type":4,"pic":"https:\/\/simg.s.weibo.com\/20170303_img_search_38.png"},{"actionlog":{"act_code":554,"ext":"seqid:16579839450170435141369|t:31|cate:10103|key:#\u5468\u7426\u72b6\u6001#|c_type:31|pos:1_38|page:1|type:25|dgr:0","luicode":"","act_type":1,"uicode":"","fid":"106003type=25&t=3&disable_hot=1&filter_type=realtimehot","lfid":""},"desc":"\u5468\u7426\u72b6\u6001","desc_extr":224255,"itemid":"t:31|cate:10103|key:#\u5468\u7426\u72b6\u6001#|c_type:31|pos:1-1-0||type:25","scheme":"https:\/\/m.weibo.cn\/search?containerid=100103type%3D1%26t%3D10%26q%3D%23%E5%91%A8%E7%90%A6%E7%8A%B6%E6%80%81%23&stream_entry_id=31&isnewpage=1&extparam=seat%3D1%26pos%3D38%26filter_type%3Drealtimehot%26dgr%3D0%26c_type%3D31%26flag%3D1%26cate%3D0%26realpos%3D39%26lcate%3D5001%26display_time%3D1657983945%26pre_seqid%3D16579839450170435141369&luicode=10000011&lfid=106003type%253D25%2526t%253D3%2526disable_hot%253D1%2526filter_type%253Drealtimehot","icon_height":24,"icon":"https:\/\/simg.s.weibo.com\/20210226_new.png","icon_width":24,"card_type":4,"pic":"https:\/\/simg.s.weibo.com\/20170303_img_search_39.png"},{"actionlog":{"act_code":554,"ext":"seqid:16579839450170435141369|t:31|cate:10103|key:#\u4e2d\u56fd\u5973\u4e52\u9501\u5b9a\u5973\u5355\u51a0\u519b#|c_type:31|pos:1_39|page:1|type:25|dgr:0","luicode":"","act_type":1,"uicode":"","fid":"106003type=25&t=3&disable_hot=1&filter_type=realtimehot","lfid":""},"desc":"\u4e2d\u56fd\u5973\u4e52\u9501\u5b9a\u5973\u5355\u51a0\u519b","desc_extr":222784,"itemid":"t:31|cate:10103|key:#\u4e2d\u56fd\u5973\u4e52\u9501\u5b9a\u5973\u5355\u51a0\u519b#|c_type:31|pos:1-1-0||type:25","scheme":"https:\/\/m.weibo.cn\/search?containerid=100103type%3D1%26t%3D10%26q%3D%23%E4%B8%AD%E5%9B%BD%E5%A5%B3%E4%B9%92%E9%94%81%E5%AE%9A%E5%A5%B3%E5%8D%95%E5%86%A0%E5%86%9B%23&stream_entry_id=31&isnewpage=1&extparam=seat%3D1%26pos%3D39%26filter_type%3Drealtimehot%26dgr%3D0%26c_type%3D31%26flag%3D1%26cate%3D0%26realpos%3D40%26lcate%3D5001%26display_time%3D1657983945%26pre_seqid%3D16579839450170435141369&luicode=10000011&lfid=106003type%253D25%2526t%253D3%2526disable_hot%253D1%2526filter_type%253Drealtimehot","icon_height":24,"icon":"https:\/\/simg.s.weibo.com\/20210226_new.png","icon_width":24,"card_type":4,"pic":"https:\/\/simg.s.weibo.com\/20170303_img_search_40.png"},{"actionlog":{"act_code":554,"ext":"seqid:16579839450170435141369|t:31|cate:10103|key:#\u6211\u4f55\u5e78\u798f\u4e0d\u597d\u60f9#|c_type:31|pos:1_40|page:1|type:25|dgr:0","luicode":"","act_type":1,"uicode":"","fid":"106003type=25&t=3&disable_hot=1&filter_type=realtimehot","lfid":""},"desc":"\u6211\u4f55\u5e78\u798f\u4e0d\u597d\u60f9","desc_extr":"\u5267\u96c6 221721","itemid":"t:31|cate:10103|key:#\u6211\u4f55\u5e78\u798f\u4e0d\u597d\u60f9#|c_type:31|pos:1-1-0||type:25","scheme":"https:\/\/m.weibo.cn\/search?containerid=100103type%3D1%26t%3D10%26q%3D%23%E6%88%91%E4%BD%95%E5%B9%B8%E7%A6%8F%E4%B8%8D%E5%A5%BD%E6%83%B9%23&stream_entry_id=31&isnewpage=1&extparam=seat%3D1%26pos%3D40%26filter_type%3Drealtimehot%26dgr%3D0%26c_type%3D31%26flag%3D0%26cate%3D0%26realpos%3D41%26lcate%3D5001%26display_time%3D1657983945%26pre_seqid%3D16579839450170435141369&luicode=10000011&lfid=106003type%253D25%2526t%253D3%2526disable_hot%253D1%2526filter_type%253Drealtimehot","icon_height":24,"card_type":4,"icon_width":24,"pic":"https:\/\/simg.s.weibo.com\/20170303_img_search_41.png"},{"actionlog":{"act_code":554,"ext":"seqid:16579839450170435141369|t:31|cate:10103|key:#\u9a6c\u9f99\u738b\u695a\u94a62\u6bd43\u8d75\u5927\u6210\u674e\u5c1a\u6d19#|c_type:31|pos:1_41|page:1|type:25|dgr:0","luicode":"","act_type":1,"uicode":"","fid":"106003type=25&t=3&disable_hot=1&filter_type=realtimehot","lfid":""},"desc":"\u9a6c\u9f99\u738b\u695a\u94a62\u6bd43\u8d75\u5927\u6210\u674e\u5c1a\u6d19","desc_extr":219825,"itemid":"t:31|cate:10103|key:#\u9a6c\u9f99\u738b\u695a\u94a62\u6bd43\u8d75\u5927\u6210\u674e\u5c1a\u6d19#|c_type:31|pos:1-1-0||type:25","scheme":"https:\/\/m.weibo.cn\/search?containerid=100103type%3D1%26t%3D10%26q%3D%23%E9%A9%AC%E9%BE%99%E7%8E%8B%E6%A5%9A%E9%92%A62%E6%AF%943%E8%B5%B5%E5%A4%A7%E6%88%90%E6%9D%8E%E5%B0%9A%E6%B4%99%23&stream_entry_id=31&isnewpage=1&extparam=seat%3D1%26pos%3D41%26filter_type%3Drealtimehot%26dgr%3D0%26c_type%3D31%26flag%3D0%26cate%3D0%26realpos%3D42%26lcate%3D5001%26display_time%3D1657983945%26pre_seqid%3D16579839450170435141369&luicode=10000011&lfid=106003type%253D25%2526t%253D3%2526disable_hot%253D1%2526filter_type%253Drealtimehot","icon_height":24,"card_type":4,"icon_width":24,"pic":"https:\/\/simg.s.weibo.com\/20170303_img_search_42.png"},{"actionlog":{"act_code":554,"ext":"seqid:16579839450170435141369|t:31|cate:10103|key:#\u9648\u54f2\u8fdccos\u82b1\u65e0\u7f3a#|c_type:31|pos:1_42|page:1|type:25|dgr:0","luicode":"","act_type":1,"uicode":"","fid":"106003type=25&t=3&disable_hot=1&filter_type=realtimehot","lfid":""},"desc":"\u9648\u54f2\u8fdccos\u82b1\u65e0\u7f3a","desc_extr":"\u7efc\u827a 219052","itemid":"t:31|cate:10103|key:#\u9648\u54f2\u8fdccos\u82b1\u65e0\u7f3a#|c_type:31|pos:1-1-0||type:25","scheme":"https:\/\/m.weibo.cn\/search?containerid=100103type%3D1%26t%3D10%26q%3D%23%E9%99%88%E5%93%B2%E8%BF%9Ccos%E8%8A%B1%E6%97%A0%E7%BC%BA%23&stream_entry_id=31&isnewpage=1&extparam=seat%3D1%26pos%3D42%26filter_type%3Drealtimehot%26dgr%3D0%26c_type%3D31%26flag%3D1%26cate%3D0%26realpos%3D43%26lcate%3D5001%26display_time%3D1657983945%26pre_seqid%3D16579839450170435141369&luicode=10000011&lfid=106003type%253D25%2526t%253D3%2526disable_hot%253D1%2526filter_type%253Drealtimehot","icon_height":24,"icon":"https:\/\/simg.s.weibo.com\/20210226_new.png","icon_width":24,"card_type":4,"pic":"https:\/\/simg.s.weibo.com\/20170303_img_search_43.png"},{"actionlog":{"act_code":554,"ext":"seqid:16579839450170435141369|t:31|cate:10103|key:#\u95f5\u73a7\u5176psy\u5408\u4f5c\u821e\u53f0#|c_type:31|pos:1_43|page:1|type:25|dgr:0","luicode":"","act_type":1,"uicode":"","fid":"106003type=25&t=3&disable_hot=1&filter_type=realtimehot","lfid":""},"desc":"\u95f5\u73a7\u5176psy\u5408\u4f5c\u821e\u53f0","desc_extr":"\u97f3\u4e50 209909","itemid":"t:31|cate:10103|key:#\u95f5\u73a7\u5176psy\u5408\u4f5c\u821e\u53f0#|c_type:31|pos:1-1-0||type:25","scheme":"https:\/\/m.weibo.cn\/search?containerid=100103type%3D1%26t%3D10%26q%3D%23%E9%97%B5%E7%8E%A7%E5%85%B6psy%E5%90%88%E4%BD%9C%E8%88%9E%E5%8F%B0%23&stream_entry_id=31&isnewpage=1&extparam=seat%3D1%26pos%3D43%26filter_type%3Drealtimehot%26dgr%3D0%26c_type%3D31%26flag%3D1%26cate%3D0%26realpos%3D44%26lcate%3D5001%26display_time%3D1657983945%26pre_seqid%3D16579839450170435141369&luicode=10000011&lfid=106003type%253D25%2526t%253D3%2526disable_hot%253D1%2526filter_type%253Drealtimehot","icon_height":24,"icon":"https:\/\/simg.s.weibo.com\/20210226_new.png","icon_width":24,"card_type":4,"pic":"https:\/\/simg.s.weibo.com\/20170303_img_search_44.png"},{"actionlog":{"act_code":554,"ext":"seqid:16579839450170435141369|t:31|cate:10103|key:#\u661f\u6c49\u707f\u70c2\u8881\u614e\u697c\u579a\u76f4\u64ad#|c_type:31|pos:1_44|page:1|type:25|dgr:0","luicode":"","act_type":1,"uicode":"","fid":"106003type=25&t=3&disable_hot=1&filter_type=realtimehot","lfid":""},"desc":"\u661f\u6c49\u707f\u70c2\u8881\u614e\u697c\u579a\u76f4\u64ad","desc_extr":"\u5267\u96c6 202340","itemid":"t:31|cate:10103|key:#\u661f\u6c49\u707f\u70c2\u8881\u614e\u697c\u579a\u76f4\u64ad#|c_type:31|pos:1-1-0||type:25","scheme":"https:\/\/m.weibo.cn\/search?containerid=100103type%3D1%26t%3D10%26q%3D%23%E6%98%9F%E6%B1%89%E7%81%BF%E7%83%82%E8%A2%81%E6%85%8E%E6%A5%BC%E5%9E%9A%E7%9B%B4%E6%92%AD%23&stream_entry_id=31&isnewpage=1&extparam=seat%3D1%26pos%3D44%26filter_type%3Drealtimehot%26dgr%3D0%26c_type%3D31%26flag%3D0%26cate%3D0%26realpos%3D45%26lcate%3D5001%26display_time%3D1657983945%26pre_seqid%3D16579839450170435141369&luicode=10000011&lfid=106003type%253D25%2526t%253D3%2526disable_hot%253D1%2526filter_type%253Drealtimehot","icon_height":24,"card_type":4,"icon_width":24,"pic":"https:\/\/simg.s.weibo.com\/20170303_img_search_45.png"},{"actionlog":{"act_code":554,"ext":"seqid:16579839450170435141369|t:31|cate:10103|key:\u6211\u53ea\u559c\u6b22\u4f60\u7684\u4eba\u8bbe|c_type:31|pos:1_45|page:1|type:25|dgr:0","luicode":"","act_type":1,"uicode":"","fid":"106003type=25&t=3&disable_hot=1&filter_type=realtimehot","lfid":""},"desc":"\u6211\u53ea\u559c\u6b22\u4f60\u7684\u4eba\u8bbe","desc_extr":202150,"itemid":"t:31|cate:10103|key:\u6211\u53ea\u559c\u6b22\u4f60\u7684\u4eba\u8bbe|c_type:31|pos:1-1-0||type:25","scheme":"https:\/\/m.weibo.cn\/search?containerid=100103type%3D1%26t%3D10%26q%3D%E6%88%91%E5%8F%AA%E5%96%9C%E6%AC%A2%E4%BD%A0%E7%9A%84%E4%BA%BA%E8%AE%BE&stream_entry_id=31&isnewpage=1&extparam=seat%3D1%26pos%3D45%26filter_type%3Drealtimehot%26dgr%3D0%26c_type%3D31%26flag%3D0%26cate%3D0%26realpos%3D46%26lcate%3D5001%26display_time%3D1657983945%26pre_seqid%3D16579839450170435141369&luicode=10000011&lfid=106003type%253D25%2526t%253D3%2526disable_hot%253D1%2526filter_type%253Drealtimehot","icon_height":24,"card_type":4,"icon_width":24,"pic":"https:\/\/simg.s.weibo.com\/20170303_img_search_46.png"},{"actionlog":{"act_code":554,"ext":"seqid:16579839450170435141369|t:31|cate:10103|key:#EDG\u5bf9\u6218TES#|c_type:31|pos:1_46|page:1|type:25|dgr:0","luicode":"","act_type":1,"uicode":"","fid":"106003type=25&t=3&disable_hot=1&filter_type=realtimehot","lfid":""},"desc":"EDG\u5bf9\u6218TES","desc_extr":187929,"itemid":"t:31|cate:10103|key:#EDG\u5bf9\u6218TES#|c_type:31|pos:1-1-0||type:25","scheme":"https:\/\/m.weibo.cn\/search?containerid=100103type%3D1%26t%3D10%26q%3D%23EDG%E5%AF%B9%E6%88%98TES%23&stream_entry_id=31&isnewpage=1&extparam=seat%3D1%26pos%3D46%26filter_type%3Drealtimehot%26dgr%3D0%26c_type%3D31%26flag%3D0%26cate%3D0%26realpos%3D47%26lcate%3D5001%26display_time%3D1657983945%26pre_seqid%3D16579839450170435141369&luicode=10000011&lfid=106003type%253D25%2526t%253D3%2526disable_hot%253D1%2526filter_type%253Drealtimehot","icon_height":24,"card_type":4,"icon_width":24,"pic":"https:\/\/simg.s.weibo.com\/20170303_img_search_47.png"},{"actionlog":{"act_code":554,"ext":"seqid:16579839450170435141369|t:31|cate:10103|key:#\u5c0f\u5e03\u4e01\u5927\u5e03\u4e01\u96ea\u7cd5\u62bd\u68c0\u4e0d\u5408\u683c#|c_type:31|pos:1_47|page:1|type:25|dgr:0","luicode":"","act_type":1,"uicode":"","fid":"106003type=25&t=3&disable_hot=1&filter_type=realtimehot","lfid":""},"desc":"\u5c0f\u5e03\u4e01\u5927\u5e03\u4e01\u96ea\u7cd5\u62bd\u68c0\u4e0d\u5408\u683c","desc_extr":186848,"itemid":"t:31|cate:10103|key:#\u5c0f\u5e03\u4e01\u5927\u5e03\u4e01\u96ea\u7cd5\u62bd\u68c0\u4e0d\u5408\u683c#|c_type:31|pos:1-1-0||type:25","scheme":"https:\/\/m.weibo.cn\/search?containerid=100103type%3D1%26t%3D10%26q%3D%23%E5%B0%8F%E5%B8%83%E4%B8%81%E5%A4%A7%E5%B8%83%E4%B8%81%E9%9B%AA%E7%B3%95%E6%8A%BD%E6%A3%80%E4%B8%8D%E5%90%88%E6%A0%BC%23&stream_entry_id=31&isnewpage=1&extparam=seat%3D1%26pos%3D47%26filter_type%3Drealtimehot%26dgr%3D0%26c_type%3D31%26flag%3D0%26cate%3D0%26realpos%3D48%26lcate%3D5001%26display_time%3D1657983945%26pre_seqid%3D16579839450170435141369&luicode=10000011&lfid=106003type%253D25%2526t%253D3%2526disable_hot%253D1%2526filter_type%253Drealtimehot","icon_height":24,"card_type":4,"icon_width":24,"pic":"https:\/\/simg.s.weibo.com\/20170303_img_search_48.png"},{"actionlog":{"act_code":554,"ext":"seqid:16579839450170435141369|t:31|cate:10103|key:#\u5468\u7426\u590d\u51fa#|c_type:31|pos:1_48|page:1|type:25|dgr:0","luicode":"","act_type":1,"uicode":"","fid":"106003type=25&t=3&disable_hot=1&filter_type=realtimehot","lfid":""},"desc":"\u5468\u7426\u590d\u51fa","desc_extr":166001,"itemid":"t:31|cate:10103|key:#\u5468\u7426\u590d\u51fa#|c_type:31|pos:1-1-0||type:25","scheme":"https:\/\/m.weibo.cn\/search?containerid=100103type%3D1%26t%3D10%26q%3D%23%E5%91%A8%E7%90%A6%E5%A4%8D%E5%87%BA%23&stream_entry_id=31&isnewpage=1&extparam=seat%3D1%26pos%3D48%26filter_type%3Drealtimehot%26dgr%3D0%26c_type%3D31%26flag%3D1%26cate%3D0%26realpos%3D49%26lcate%3D5001%26display_time%3D1657983945%26pre_seqid%3D16579839450170435141369&luicode=10000011&lfid=106003type%253D25%2526t%253D3%2526disable_hot%253D1%2526filter_type%253Drealtimehot","icon_height":24,"icon":"https:\/\/simg.s.weibo.com\/20210226_new.png","icon_width":24,"card_type":4,"pic":"https:\/\/simg.s.weibo.com\/20170303_img_search_49.png"},{"actionlog":{"act_code":554,"ext":"seqid:16579839450170435141369|t:31|cate:10103|key:#7\u5c81\u7537\u5b69\u79bb\u4e16\u6350\u732e\u5668\u5b98\u6551\u52a95\u4eba#|c_type:31|pos:1_49|page:1|type:25|dgr:0","luicode":"","act_type":1,"uicode":"","fid":"106003type=25&t=3&disable_hot=1&filter_type=realtimehot","lfid":""},"desc":"7\u5c81\u7537\u5b69\u79bb\u4e16\u6350\u732e\u5668\u5b98\u6551\u52a95\u4eba","desc_extr":162930,"itemid":"t:31|cate:10103|key:#7\u5c81\u7537\u5b69\u79bb\u4e16\u6350\u732e\u5668\u5b98\u6551\u52a95\u4eba#|c_type:31|pos:1-1-0||type:25","scheme":"https:\/\/m.weibo.cn\/search?containerid=100103type%3D1%26t%3D10%26q%3D%237%E5%B2%81%E7%94%B7%E5%AD%A9%E7%A6%BB%E4%B8%96%E6%8D%90%E7%8C%AE%E5%99%A8%E5%AE%98%E6%95%91%E5%8A%A95%E4%BA%BA%23&stream_entry_id=31&isnewpage=1&extparam=seat%3D1%26pos%3D49%26filter_type%3Drealtimehot%26dgr%3D0%26c_type%3D31%26flag%3D0%26cate%3D0%26realpos%3D50%26lcate%3D5001%26display_time%3D1657983945%26pre_seqid%3D16579839450170435141369&luicode=10000011&lfid=106003type%253D25%2526t%253D3%2526disable_hot%253D1%2526filter_type%253Drealtimehot","icon_height":24,"card_type":4,"icon_width":24,"pic":"https:\/\/simg.s.weibo.com\/20170303_img_search_50.png"}]},{"show_type":0,"title":"\u5b9e\u65f6\u4e0a\u5347\u70ed\u70b9","card_type":11,"card_group":[{"actionlog":{"act_code":554,"ext":"seqid:16579839450170435141369|pos:1_1|c_type:25|cate:10103|key:#\u592e\u884c\u539f\u884c\u957f\u8c08\u697c\u5e02\u56f0\u5883#|t:25|prop:0|page:1|type:25|dgr:0","luicode":"","act_type":1,"uicode":"","fid":"106003type=25&t=3&disable_hot=1&filter_type=realtimehot","lfid":""},"desc":"\u592e\u884c\u539f\u884c\u957f\u8c08\u697c\u5e02\u56f0\u5883","desc_extr":53326,"itemid":"t:25|cate:10103|key:\u592e\u884c\u539f\u884c\u957f\u8c08\u697c\u5e02\u56f0\u5883|c_type:25|pos:1-3-0||type:25","scheme":"https:\/\/m.weibo.cn\/search?containerid=100103type%3D1%26t%3D10%26q%3D%23%E5%A4%AE%E8%A1%8C%E5%8E%9F%E8%A1%8C%E9%95%BF%E8%B0%88%E6%A5%BC%E5%B8%82%E5%9B%B0%E5%A2%83%23&stream_entry_id=25&isnewpage=1&extparam=seat%3D1%26mi_cid%3D100103%26c_type%3D25%26lcate%3D5002%26cate%3D%26q%3D%2523%25E5%25A4%25AE%25E8%25A1%258C%25E5%258E%259F%25E8%25A1%258C%25E9%2595%25BF%25E8%25B0%2588%25E6%25A5%25BC%25E5%25B8%2582%25E5%259B%25B0%25E5%25A2%2583%2523%26pos%3D0%26dgr%3D0%26filter_type%3Dpersonal%26display_time%3D1657983945%26pre_seqid%3D16579839450170435141369&luicode=10000011&lfid=106003type%253D25%2526t%253D3%2526disable_hot%253D1%2526filter_type%253Drealtimehot","icon":"https:\/\/simg.s.weibo.com\/20210226_plus.png","card_type":4,"pic":"https:\/\/simg.s.weibo.com\/20170306_plus_new1.png"},{"actionlog":{"act_code":554,"ext":"seqid:16579839450170435141369|pos:1_2|c_type:25|cate:10103|key:\u6597\u9c7c|t:25|prop:0|page:1|type:25|dgr:0","luicode":"","act_type":1,"uicode":"","fid":"106003type=25&t=3&disable_hot=1&filter_type=realtimehot","lfid":""},"desc":"\u6597\u9c7c","desc_extr":126005,"itemid":"t:25|cate:10103|key:\u6597\u9c7c|c_type:25|pos:1-3-0||type:25","scheme":"https:\/\/m.weibo.cn\/search?containerid=100103type%3D1%26t%3D10%26q%3D%E6%96%97%E9%B1%BC&stream_entry_id=25&isnewpage=1&extparam=seat%3D1%26mi_cid%3D100103%26c_type%3D25%26lcate%3D5002%26cate%3D%26q%3D%25E6%2596%2597%25E9%25B1%25BC%26pos%3D1%26dgr%3D0%26filter_type%3Dpersonal%26display_time%3D1657983945%26pre_seqid%3D16579839450170435141369&luicode=10000011&lfid=106003type%253D25%2526t%253D3%2526disable_hot%253D1%2526filter_type%253Drealtimehot","icon":"https:\/\/simg.s.weibo.com\/20210226_plus.png","card_type":4,"pic":"https:\/\/simg.s.weibo.com\/20170306_plus_new1.png"},{"actionlog":{"act_code":554,"ext":"seqid:16579839450170435141369|pos:1_3|c_type:25|cate:10103|key:#\u5982\u4f55\u8bc4\u4ef7\u661f\u6c49\u707f\u70c2\u8c46\u74e3\u5f00\u5206#|t:25|prop:0|page:1|type:25|dgr:0","luicode":"","act_type":1,"uicode":"","fid":"106003type=25&t=3&disable_hot=1&filter_type=realtimehot","lfid":""},"desc":"\u5982\u4f55\u8bc4\u4ef7\u661f\u6c49\u707f\u70c2\u8c46\u74e3\u5f00\u5206","desc_extr":26660,"itemid":"t:25|cate:10103|key:\u5982\u4f55\u8bc4\u4ef7\u661f\u6c49\u707f\u70c2\u8c46\u74e3\u5f00\u5206|c_type:25|pos:1-3-0||type:25","scheme":"https:\/\/m.weibo.cn\/search?containerid=100103type%3D1%26t%3D10%26q%3D%23%E5%A6%82%E4%BD%95%E8%AF%84%E4%BB%B7%E6%98%9F%E6%B1%89%E7%81%BF%E7%83%82%E8%B1%86%E7%93%A3%E5%BC%80%E5%88%86%23&stream_entry_id=25&isnewpage=1&extparam=seat%3D1%26mi_cid%3D100103%26c_type%3D25%26lcate%3D5002%26cate%3D%26q%3D%2523%25E5%25A6%2582%25E4%25BD%2595%25E8%25AF%2584%25E4%25BB%25B7%25E6%2598%259F%25E6%25B1%2589%25E7%2581%25BF%25E7%2583%2582%25E8%25B1%2586%25E7%2593%25A3%25E5%25BC%2580%25E5%2588%2586%2523%26pos%3D2%26dgr%3D0%26filter_type%3Dpersonal%26display_time%3D1657983945%26pre_seqid%3D16579839450170435141369&luicode=10000011&lfid=106003type%253D25%2526t%253D3%2526disable_hot%253D1%2526filter_type%253Drealtimehot","icon":"https:\/\/simg.s.weibo.com\/20210226_plus.png","card_type":4,"pic":"https:\/\/simg.s.weibo.com\/20170306_plus_new1.png"},{"itemid":"t:25|cate:10103|key:\u738b\u4fca\u51ef\u5c0f\u9c7c\u4eba\u56db\u6740|c_type:25|pos:1-3-0||type:25","actionlog":{"act_code":554,"ext":"seqid:16579839450170435141369|pos:1_4|c_type:25|cate:10103|key:#\u738b\u4fca\u51ef\u5c0f\u9c7c\u4eba\u56db\u6740#|t:25|prop:0|page:1|type:25|dgr:0","luicode":"","act_type":1,"uicode":"","fid":"106003type=25&t=3&disable_hot=1&filter_type=realtimehot","lfid":""},"desc":"\u738b\u4fca\u51ef\u5c0f\u9c7c\u4eba\u56db\u6740","desc_extr":130210,"pic":"https:\/\/simg.s.weibo.com\/20170306_plus_new1.png","scheme":"https:\/\/m.weibo.cn\/search?containerid=100103type%3D1%26t%3D10%26q%3D%23%E7%8E%8B%E4%BF%8A%E5%87%AF%E5%B0%8F%E9%B1%BC%E4%BA%BA%E5%9B%9B%E6%9D%80%23&stream_entry_id=25&isnewpage=1&extparam=seat%3D1%26mi_cid%3D100103%26c_type%3D25%26lcate%3D5002%26cate%3D%26q%3D%2523%25E7%258E%258B%25E4%25BF%258A%25E5%2587%25AF%25E5%25B0%258F%25E9%25B1%25BC%25E4%25BA%25BA%25E5%259B%259B%25E6%259D%2580%2523%26pos%3D3%26dgr%3D0%26filter_type%3Dpersonal%26display_time%3D1657983945%26pre_seqid%3D16579839450170435141369&luicode=10000011&lfid=106003type%253D25%2526t%253D3%2526disable_hot%253D1%2526filter_type%253Drealtimehot","card_type":4},{"itemid":"t:25|cate:10103|key:\u6821\u56ed\u771f\u662f\u4e00\u4e2a\u795e\u5947\u7684\u5730\u65b9|c_type:25|pos:1-3-0||type:25","actionlog":{"act_code":554,"ext":"seqid:16579839450170435141369|pos:1_5|c_type:25|cate:10103|key:#\u6821\u56ed\u771f\u662f\u4e00\u4e2a\u795e\u5947\u7684\u5730\u65b9#|t:25|prop:0|page:1|type:25|dgr:0","luicode":"","act_type":1,"uicode":"","fid":"106003type=25&t=3&disable_hot=1&filter_type=realtimehot","lfid":""},"desc":"\u6821\u56ed\u771f\u662f\u4e00\u4e2a\u795e\u5947\u7684\u5730\u65b9","desc_extr":91173,"pic":"https:\/\/simg.s.weibo.com\/20170306_plus_new1.png","scheme":"https:\/\/m.weibo.cn\/search?containerid=100103type%3D1%26t%3D10%26q%3D%23%E6%A0%A1%E5%9B%AD%E7%9C%9F%E6%98%AF%E4%B8%80%E4%B8%AA%E7%A5%9E%E5%A5%87%E7%9A%84%E5%9C%B0%E6%96%B9%23&stream_entry_id=25&isnewpage=1&extparam=seat%3D1%26mi_cid%3D100103%26c_type%3D25%26lcate%3D5002%26cate%3D%26q%3D%2523%25E6%25A0%25A1%25E5%259B%25AD%25E7%259C%259F%25E6%2598%25AF%25E4%25B8%2580%25E4%25B8%25AA%25E7%25A5%259E%25E5%25A5%2587%25E7%259A%2584%25E5%259C%25B0%25E6%2596%25B9%2523%26pos%3D4%26dgr%3D0%26filter_type%3Dpersonal%26display_time%3D1657983945%26pre_seqid%3D16579839450170435141369&luicode=10000011&lfid=106003type%253D25%2526t%253D3%2526disable_hot%253D1%2526filter_type%253Drealtimehot","card_type":4},{"itemid":"t:25|cate:10103|key:\u6a80\u5065\u6b21\u961a\u6e05\u5b50\u516d\u8fde\u6bd4\u5fc3|c_type:25|pos:1-3-0||type:25","actionlog":{"act_code":554,"ext":"seqid:16579839450170435141369|pos:1_6|c_type:25|cate:10103|key:#\u6a80\u5065\u6b21\u961a\u6e05\u5b50\u516d\u8fde\u6bd4\u5fc3#|t:25|prop:0|page:1|type:25|dgr:0","luicode":"","act_type":1,"uicode":"","fid":"106003type=25&t=3&disable_hot=1&filter_type=realtimehot","lfid":""},"desc":"\u6a80\u5065\u6b21\u961a\u6e05\u5b50\u516d\u8fde\u6bd4\u5fc3","desc_extr":26634,"pic":"https:\/\/simg.s.weibo.com\/20170306_plus_new1.png","scheme":"https:\/\/m.weibo.cn\/search?containerid=100103type%3D1%26t%3D10%26q%3D%23%E6%AA%80%E5%81%A5%E6%AC%A1%E9%98%9A%E6%B8%85%E5%AD%90%E5%85%AD%E8%BF%9E%E6%AF%94%E5%BF%83%23&stream_entry_id=25&isnewpage=1&extparam=seat%3D1%26mi_cid%3D100103%26c_type%3D25%26lcate%3D5002%26cate%3D%26q%3D%2523%25E6%25AA%2580%25E5%2581%25A5%25E6%25AC%25A1%25E9%2598%259A%25E6%25B8%2585%25E5%25AD%2590%25E5%2585%25AD%25E8%25BF%259E%25E6%25AF%2594%25E5%25BF%2583%2523%26pos%3D5%26dgr%3D0%26filter_type%3Dpersonal%26display_time%3D1657983945%26pre_seqid%3D16579839450170435141369&luicode=10000011&lfid=106003type%253D25%2526t%253D3%2526disable_hot%253D1%2526filter_type%253Drealtimehot","card_type":4},{"itemid":"t:25|cate:10103|key:\u6a80\u5065\u6b21\u5b59\u5929\u5b87\u90ed\u4fca\u8fb0\u776b\u6bdb\u5f2f\u5f2f\u6367\u8138\u6740|c_type:25|pos:1-3-0||type:25","actionlog":{"act_code":554,"ext":"seqid:16579839450170435141369|pos:1_7|c_type:25|cate:10103|key:#\u6a80\u5065\u6b21\u5b59\u5929\u5b87\u90ed\u4fca\u8fb0\u776b\u6bdb\u5f2f\u5f2f\u6367\u8138\u6740#|t:25|prop:0|page:1|type:25|dgr:0","luicode":"","act_type":1,"uicode":"","fid":"106003type=25&t=3&disable_hot=1&filter_type=realtimehot","lfid":""},"desc":"\u6a80\u5065\u6b21\u5b59\u5929\u5b87\u90ed\u4fca\u8fb0\u776b\u6bdb\u5f2f\u5f2f\u6367\u8138\u6740","desc_extr":100643,"pic":"https:\/\/simg.s.weibo.com\/20170306_plus_new1.png","scheme":"https:\/\/m.weibo.cn\/search?containerid=100103type%3D1%26t%3D10%26q%3D%23%E6%AA%80%E5%81%A5%E6%AC%A1%E5%AD%99%E5%A4%A9%E5%AE%87%E9%83%AD%E4%BF%8A%E8%BE%B0%E7%9D%AB%E6%AF%9B%E5%BC%AF%E5%BC%AF%E6%8D%A7%E8%84%B8%E6%9D%80%23&stream_entry_id=25&isnewpage=1&extparam=seat%3D1%26mi_cid%3D100103%26c_type%3D25%26lcate%3D5002%26cate%3D%26q%3D%2523%25E6%25AA%2580%25E5%2581%25A5%25E6%25AC%25A1%25E5%25AD%2599%25E5%25A4%25A9%25E5%25AE%2587%25E9%2583%25AD%25E4%25BF%258A%25E8%25BE%25B0%25E7%259D%25AB%25E6%25AF%259B%25E5%25BC%25AF%25E5%25BC%25AF%25E6%258D%25A7%25E8%2584%25B8%25E6%259D%2580%2523%26pos%3D6%26dgr%3D0%26filter_type%3Dpersonal%26display_time%3D1657983945%26pre_seqid%3D16579839450170435141369&luicode=10000011&lfid=106003type%253D25%2526t%253D3%2526disable_hot%253D1%2526filter_type%253Drealtimehot","card_type":4},{"itemid":"t:25|cate:10103|key:\u5f20\u5609\u502acos\u4f5f\u638c\u67dc|c_type:25|pos:1-3-0||type:25","actionlog":{"act_code":554,"ext":"seqid:16579839450170435141369|pos:1_8|c_type:25|cate:10103|key:#\u5f20\u5609\u502acos\u4f5f\u638c\u67dc#|t:25|prop:0|page:1|type:25|dgr:0","luicode":"","act_type":1,"uicode":"","fid":"106003type=25&t=3&disable_hot=1&filter_type=realtimehot","lfid":""},"desc":"\u5f20\u5609\u502acos\u4f5f\u638c\u67dc","desc_extr":26611,"pic":"https:\/\/simg.s.weibo.com\/20170306_plus_new1.png","scheme":"https:\/\/m.weibo.cn\/search?containerid=100103type%3D1%26t%3D10%26q%3D%23%E5%BC%A0%E5%98%89%E5%80%AAcos%E4%BD%9F%E6%8E%8C%E6%9F%9C%23&stream_entry_id=25&isnewpage=1&extparam=seat%3D1%26mi_cid%3D100103%26c_type%3D25%26lcate%3D5002%26cate%3D%26q%3D%2523%25E5%25BC%25A0%25E5%2598%2589%25E5%2580%25AAcos%25E4%25BD%259F%25E6%258E%258C%25E6%259F%259C%2523%26pos%3D7%26dgr%3D0%26filter_type%3Dpersonal%26display_time%3D1657983945%26pre_seqid%3D16579839450170435141369&luicode=10000011&lfid=106003type%253D25%2526t%253D3%2526disable_hot%253D1%2526filter_type%253Drealtimehot","card_type":4},{"itemid":"t:25|cate:10103|key:\u6d12\u6c34\u8f66\u96e8\u5929\u7ed5\u5708\u6d12\u6c34|c_type:25|pos:1-3-0||type:25","actionlog":{"act_code":554,"ext":"seqid:16579839450170435141369|pos:1_9|c_type:25|cate:10103|key:#\u6d12\u6c34\u8f66\u96e8\u5929\u7ed5\u5708\u6d12\u6c34#|t:25|prop:0|page:1|type:25|dgr:0","luicode":"","act_type":1,"uicode":"","fid":"106003type=25&t=3&disable_hot=1&filter_type=realtimehot","lfid":""},"desc":"\u6d12\u6c34\u8f66\u96e8\u5929\u7ed5\u5708\u6d12\u6c34","desc_extr":91839,"pic":"https:\/\/simg.s.weibo.com\/20170306_plus_new1.png","scheme":"https:\/\/m.weibo.cn\/search?containerid=100103type%3D1%26t%3D10%26q%3D%23%E6%B4%92%E6%B0%B4%E8%BD%A6%E9%9B%A8%E5%A4%A9%E7%BB%95%E5%9C%88%E6%B4%92%E6%B0%B4%23&stream_entry_id=25&isnewpage=1&extparam=seat%3D1%26mi_cid%3D100103%26c_type%3D25%26lcate%3D5002%26cate%3D%26q%3D%2523%25E6%25B4%2592%25E6%25B0%25B4%25E8%25BD%25A6%25E9%259B%25A8%25E5%25A4%25A9%25E7%25BB%2595%25E5%259C%2588%25E6%25B4%2592%25E6%25B0%25B4%2523%26pos%3D8%26dgr%3D0%26filter_type%3Dpersonal%26display_time%3D1657983945%26pre_seqid%3D16579839450170435141369&luicode=10000011&lfid=106003type%253D25%2526t%253D3%2526disable_hot%253D1%2526filter_type%253Drealtimehot","card_type":4},{"actionlog":{"act_code":554,"ext":"seqid:16579839450170435141369|pos:1_10|c_type:25|cate:10103|key:#\u4f60\u597d\u661f\u671f\u516d#|t:25|prop:0|page:1|type:25|dgr:0","luicode":"","act_type":1,"uicode":"","fid":"106003type=25&t=3&disable_hot=1&filter_type=realtimehot","lfid":""},"desc":"\u4f60\u597d\u661f\u671f\u516d","desc_extr":99696,"itemid":"t:25|cate:10103|key:\u4f60\u597d\u661f\u671f\u516d|c_type:25|pos:1-3-0||type:25","scheme":"http:\/\/m.weibo.cn\/c\/wbox?&id=j84w2uenjc&roomid=8094&q=%23%E4%BD%A0%E5%A5%BD%E6%98%9F%E6%9C%9F%E5%85%AD%23&extparam=seat%3D1%26mi_cid%3D100103%26c_type%3D25%26lcate%3D5002%26cate%3D%26q%3D%2523%25E4%25BD%25A0%25E5%25A5%25BD%25E6%2598%259F%25E6%259C%259F%25E5%2585%25AD%2523%26pos%3D9%26dgr%3D0%26filter_type%3Dpersonal%26display_time%3D1657983945%26pre_seqid%3D16579839450170435141369&luicode=10000011&lfid=106003type%253D25%2526t%253D3%2526disable_hot%253D1%2526filter_type%253Drealtimehot","icon":"https:\/\/simg.s.weibo.com\/20210226_plus.png","card_type":4,"pic":"https:\/\/simg.s.weibo.com\/20170306_plus_new1.png"},{"itemid":"t:25|cate:10103|key:\u535a\u5e93|c_type:25|pos:1-3-0||type:25","actionlog":{"act_code":554,"ext":"seqid:16579839450170435141369|pos:1_11|c_type:25|cate:10103|key:\u535a\u5e93|t:25|prop:0|page:1|type:25|dgr:0","luicode":"","act_type":1,"uicode":"","fid":"106003type=25&t=3&disable_hot=1&filter_type=realtimehot","lfid":""},"desc":"\u535a\u5e93","desc_extr":76163,"pic":"https:\/\/simg.s.weibo.com\/20170306_plus_new1.png","scheme":"https:\/\/m.weibo.cn\/search?containerid=100103type%3D1%26t%3D10%26q%3D%E5%8D%9A%E5%BA%93&stream_entry_id=25&isnewpage=1&extparam=seat%3D1%26mi_cid%3D100103%26c_type%3D25%26lcate%3D5002%26cate%3D%26q%3D%25E5%258D%259A%25E5%25BA%2593%26pos%3D10%26dgr%3D0%26filter_type%3Dpersonal%26display_time%3D1657983945%26pre_seqid%3D16579839450170435141369&luicode=10000011&lfid=106003type%253D25%2526t%253D3%2526disable_hot%253D1%2526filter_type%253Drealtimehot","card_type":4},{"itemid":"t:25|cate:10103|key:\u8f66\u6f88\u8bf4\u4e43\u4e07\u5766\u8361\u4e0d\u5351\u4e0d\u4ea2|c_type:25|pos:1-3-0||type:25","actionlog":{"act_code":554,"ext":"seqid:16579839450170435141369|pos:1_12|c_type:25|cate:10103|key:#\u8f66\u6f88\u8bf4\u4e43\u4e07\u5766\u8361\u4e0d\u5351\u4e0d\u4ea2#|t:25|prop:0|page:1|type:25|dgr:0","luicode":"","act_type":1,"uicode":"","fid":"106003type=25&t=3&disable_hot=1&filter_type=realtimehot","lfid":""},"desc":"\u8f66\u6f88\u8bf4\u4e43\u4e07\u5766\u8361\u4e0d\u5351\u4e0d\u4ea2","desc_extr":84371,"pic":"https:\/\/simg.s.weibo.com\/20170306_plus_new1.png","scheme":"https:\/\/m.weibo.cn\/search?containerid=100103type%3D1%26t%3D10%26q%3D%23%E8%BD%A6%E6%BE%88%E8%AF%B4%E4%B9%83%E4%B8%87%E5%9D%A6%E8%8D%A1%E4%B8%8D%E5%8D%91%E4%B8%8D%E4%BA%A2%23&stream_entry_id=25&isnewpage=1&extparam=seat%3D1%26mi_cid%3D100103%26c_type%3D25%26lcate%3D5002%26cate%3D%26q%3D%2523%25E8%25BD%25A6%25E6%25BE%2588%25E8%25AF%25B4%25E4%25B9%2583%25E4%25B8%2587%25E5%259D%25A6%25E8%258D%25A1%25E4%25B8%258D%25E5%258D%2591%25E4%25B8%258D%25E4%25BA%25A2%2523%26pos%3D11%26dgr%3D0%26filter_type%3Dpersonal%26display_time%3D1657983945%26pre_seqid%3D16579839450170435141369&luicode=10000011&lfid=106003type%253D25%2526t%253D3%2526disable_hot%253D1%2526filter_type%253Drealtimehot","card_type":4},{"itemid":"t:25|cate:10103|key:\u5b66\u8f66\u524d\u540e\u7684\u80a4\u8272\u53d8\u5316|c_type:25|pos:1-3-0||type:25","actionlog":{"act_code":554,"ext":"seqid:16579839450170435141369|pos:1_13|c_type:25|cate:10103|key:#\u5b66\u8f66\u524d\u540e\u7684\u80a4\u8272\u53d8\u5316#|t:25|prop:0|page:1|type:25|dgr:0","luicode":"","act_type":1,"uicode":"","fid":"106003type=25&t=3&disable_hot=1&filter_type=realtimehot","lfid":""},"desc":"\u5b66\u8f66\u524d\u540e\u7684\u80a4\u8272\u53d8\u5316","desc_extr":69688,"pic":"https:\/\/simg.s.weibo.com\/20170306_plus_new1.png","scheme":"https:\/\/m.weibo.cn\/search?containerid=100103type%3D1%26t%3D10%26q%3D%23%E5%AD%A6%E8%BD%A6%E5%89%8D%E5%90%8E%E7%9A%84%E8%82%A4%E8%89%B2%E5%8F%98%E5%8C%96%23&stream_entry_id=25&isnewpage=1&extparam=seat%3D1%26mi_cid%3D100103%26c_type%3D25%26lcate%3D5002%26cate%3D%26q%3D%2523%25E5%25AD%25A6%25E8%25BD%25A6%25E5%2589%258D%25E5%2590%258E%25E7%259A%2584%25E8%2582%25A4%25E8%2589%25B2%25E5%258F%2598%25E5%258C%2596%2523%26pos%3D12%26dgr%3D0%26filter_type%3Dpersonal%26display_time%3D1657983945%26pre_seqid%3D16579839450170435141369&luicode=10000011&lfid=106003type%253D25%2526t%253D3%2526disable_hot%253D1%2526filter_type%253Drealtimehot","card_type":4},{"actionlog":{"act_code":554,"ext":"seqid:16579839450170435141369|pos:1_14|c_type:25|cate:10103|key:#WTT\u7403\u661f\u6311\u6218\u8d5b\u5e03\u8fbe\u4f69\u65af\u7ad9#|t:25|prop:0|page:1|type:25|dgr:0","luicode":"","act_type":1,"uicode":"","fid":"106003type=25&t=3&disable_hot=1&filter_type=realtimehot","lfid":""},"desc":"WTT\u7403\u661f\u6311\u6218\u8d5b\u5e03\u8fbe\u4f69\u65af\u7ad9","desc_extr":99285,"itemid":"t:25|cate:10103|key:WTT\u7403\u661f\u6311\u6218\u8d5b\u5e03\u8fbe\u4f69\u65af\u7ad9|c_type:25|pos:1-3-0||type:25","scheme":"http:\/\/m.weibo.cn\/c\/wbox?&id=j84w2uenjc&roomid=11076&q=%23WTT%E7%90%83%E6%98%9F%E6%8C%91%E6%88%98%E8%B5%9B%E5%B8%83%E8%BE%BE%E4%BD%A9%E6%96%AF%E7%AB%99%23&extparam=seat%3D1%26mi_cid%3D100103%26c_type%3D25%26lcate%3D5002%26cate%3D%26q%3D%2523WTT%25E7%2590%2583%25E6%2598%259F%25E6%258C%2591%25E6%2588%2598%25E8%25B5%259B%25E5%25B8%2583%25E8%25BE%25BE%25E4%25BD%25A9%25E6%2596%25AF%25E7%25AB%2599%2523%26pos%3D13%26dgr%3D0%26filter_type%3Dpersonal%26display_time%3D1657983945%26pre_seqid%3D16579839450170435141369&luicode=10000011&lfid=106003type%253D25%2526t%253D3%2526disable_hot%253D1%2526filter_type%253Drealtimehot","icon":"https:\/\/simg.s.weibo.com\/20210226_plus.png","card_type":4,"pic":"https:\/\/simg.s.weibo.com\/20170306_plus_new1.png"},{"itemid":"t:25|cate:10103|key:\u4e2d\u56fd\u5973\u7bee\u5fc3\u7406\u6559\u7ec3\u9ec4\u83c1\u56e0\u75c5\u53bb\u4e16|c_type:25|pos:1-3-0||type:25","actionlog":{"act_code":554,"ext":"seqid:16579839450170435141369|pos:1_15|c_type:25|cate:10103|key:#\u4e2d\u56fd\u5973\u7bee\u5fc3\u7406\u6559\u7ec3\u9ec4\u83c1\u56e0\u75c5\u53bb\u4e16#|t:25|prop:0|page:1|type:25|dgr:0","luicode":"","act_type":1,"uicode":"","fid":"106003type=25&t=3&disable_hot=1&filter_type=realtimehot","lfid":""},"desc":"\u4e2d\u56fd\u5973\u7bee\u5fc3\u7406\u6559\u7ec3\u9ec4\u83c1\u56e0\u75c5\u53bb\u4e16","desc_extr":99126,"pic":"https:\/\/simg.s.weibo.com\/20170306_plus_new1.png","scheme":"https:\/\/m.weibo.cn\/search?containerid=100103type%3D1%26t%3D10%26q%3D%23%E4%B8%AD%E5%9B%BD%E5%A5%B3%E7%AF%AE%E5%BF%83%E7%90%86%E6%95%99%E7%BB%83%E9%BB%84%E8%8F%81%E5%9B%A0%E7%97%85%E5%8E%BB%E4%B8%96%23&stream_entry_id=25&isnewpage=1&extparam=seat%3D1%26mi_cid%3D100103%26c_type%3D25%26lcate%3D5002%26cate%3D%26q%3D%2523%25E4%25B8%25AD%25E5%259B%25BD%25E5%25A5%25B3%25E7%25AF%25AE%25E5%25BF%2583%25E7%2590%2586%25E6%2595%2599%25E7%25BB%2583%25E9%25BB%2584%25E8%258F%2581%25E5%259B%25A0%25E7%2597%2585%25E5%258E%25BB%25E4%25B8%2596%2523%26pos%3D14%26dgr%3D0%26filter_type%3Dpersonal%26display_time%3D1657983945%26pre_seqid%3D16579839450170435141369&luicode=10000011&lfid=106003type%253D25%2526t%253D3%2526disable_hot%253D1%2526filter_type%253Drealtimehot","card_type":4}]},{"card_group":[{"is_show_arrow":0,"scheme":"https:\/\/m.weibo.cn\/feature\/applink?scheme=sinaweibo%3A%2F%2Fabc","title":" \u6587\u5a31\u70ed\u641c ","card_type":101,"left_tag_img":"https:\/\/simg.s.weibo.com\/20210604_%E5%A8%B1%E4%B9%90icon%E5%A4%87%E4%BB%BD+2%403x.png","display_arrow":0},{"actionlog":{"act_code":554,"ext":"seqid:16579839450170435141369|pos:1_1|cate:5023|key:#\u4f59\u666f\u5929#|c_type:157|t:157|page:1|type:25|dgr:0","luicode":"","act_type":1,"uicode":"","fid":"106003type=25&t=3&disable_hot=1&filter_type=realtimehot","lfid":""},"desc":"\u4f59\u666f\u5929","desc_extr":3092517,"itemid":"t:157|cate:5023|key:\u4f59\u666f\u5929|c_type:157|pos:1-4-0||type:25","scheme":"https:\/\/m.weibo.cn\/search?containerid=100103type%3D1%26t%3D10%26q%3D%23%E4%BD%99%E6%99%AF%E5%A4%A9%23&stream_entry_id=157&isnewpage=1&extparam=seat%3D1%26mi_cid%3D100103%26c_type%3D157%26lcate%3D5023%26pos%3D0%26cate%3D5023%26filter_type%3Dhotregion%26dgr%3D0%26display_time%3D1657983945%26pre_seqid%3D16579839450170435141369&luicode=10000011&lfid=106003type%253D25%2526t%253D3%2526disable_hot%253D1%2526filter_type%253Drealtimehot","icon":"https:\/\/simg.s.weibo.com\/20210226_hot.png","card_type":4,"pic":"https:\/\/simg.s.weibo.com\/wb_search_img_search_1.png"},{"actionlog":{"act_code":554,"ext":"seqid:16579839450170435141369|pos:1_2|cate:5023|key:\u7411\u513f|c_type:157|t:157|page:1|type:25|dgr:0","luicode":"","act_type":1,"uicode":"","fid":"106003type=25&t=3&disable_hot=1&filter_type=realtimehot","lfid":""},"desc":"\u7411\u513f","desc_extr":2114965,"itemid":"t:157|cate:5023|key:\u7411\u513f|c_type:157|pos:1-4-1||type:25","scheme":"https:\/\/m.weibo.cn\/search?containerid=100103type%3D1%26t%3D10%26q%3D%E7%90%91%E5%84%BF&stream_entry_id=157&isnewpage=1&extparam=seat%3D1%26mi_cid%3D100103%26c_type%3D157%26lcate%3D5023%26pos%3D1%26cate%3D5023%26filter_type%3Dhotregion%26dgr%3D0%26display_time%3D1657983945%26pre_seqid%3D16579839450170435141369&luicode=10000011&lfid=106003type%253D25%2526t%253D3%2526disable_hot%253D1%2526filter_type%253Drealtimehot","icon":"https:\/\/simg.s.weibo.com\/20210226_new.png","card_type":4,"pic":"https:\/\/simg.s.weibo.com\/wb_search_img_search_2.png"},{"actionlog":{"act_code":554,"ext":"seqid:16579839450170435141369|pos:1_3|cate:5023|key:\u738b\u6f84\u6f84|c_type:157|t:157|page:1|type:25|dgr:0","luicode":"","act_type":1,"uicode":"","fid":"106003type=25&t=3&disable_hot=1&filter_type=realtimehot","lfid":""},"desc":"\u738b\u6f84\u6f84","desc_extr":1241210,"itemid":"t:157|cate:5023|key:\u738b\u6f84\u6f84|c_type:157|pos:1-4-2||type:25","scheme":"https:\/\/m.weibo.cn\/search?containerid=100103type%3D1%26t%3D10%26q%3D%E7%8E%8B%E6%BE%84%E6%BE%84&stream_entry_id=157&isnewpage=1&extparam=seat%3D1%26mi_cid%3D100103%26c_type%3D157%26lcate%3D5023%26pos%3D2%26cate%3D5023%26filter_type%3Dhotregion%26dgr%3D0%26display_time%3D1657983945%26pre_seqid%3D16579839450170435141369&luicode=10000011&lfid=106003type%253D25%2526t%253D3%2526disable_hot%253D1%2526filter_type%253Drealtimehot","icon":"https:\/\/simg.s.weibo.com\/20210226_new.png","card_type":4,"pic":"https:\/\/simg.s.weibo.com\/wb_search_img_search_3.png"},{"actionlog":{"act_code":554,"ext":"seqid:16579839450170435141369|pos:1_4|cate:5023|key:\u6587\u8f69|c_type:157|t:157|page:1|type:25|dgr:0","luicode":"","act_type":1,"uicode":"","fid":"106003type=25&t=3&disable_hot=1&filter_type=realtimehot","lfid":""},"desc":"\u6587\u8f69","desc_extr":356708,"itemid":"t:157|cate:5023|key:\u6587\u8f69|c_type:157|pos:1-4-3||type:25","scheme":"https:\/\/m.weibo.cn\/search?containerid=100103type%3D1%26t%3D10%26q%3D%E6%96%87%E8%BD%A9&stream_entry_id=157&isnewpage=1&extparam=seat%3D1%26mi_cid%3D100103%26c_type%3D157%26lcate%3D5023%26pos%3D3%26cate%3D5023%26filter_type%3Dhotregion%26dgr%3D0%26display_time%3D1657983945%26pre_seqid%3D16579839450170435141369&luicode=10000011&lfid=106003type%253D25%2526t%253D3%2526disable_hot%253D1%2526filter_type%253Drealtimehot","icon":"https:\/\/simg.s.weibo.com\/20210226_hot.png","card_type":4,"pic":"https:\/\/simg.s.weibo.com\/20170303_point_orange.png"},{"itemid":"t:157|cate:5023|key:\u738b\u4fca\u51ef\u4e0d\u5f97\u4e0dC|c_type:157|pos:1-4-4||type:25","actionlog":{"act_code":554,"ext":"seqid:16579839450170435141369|pos:1_5|cate:5023|key:#\u738b\u4fca\u51ef\u4e0d\u5f97\u4e0dC#|c_type:157|t:157|page:1|type:25|dgr:0","luicode":"","act_type":1,"uicode":"","fid":"106003type=25&t=3&disable_hot=1&filter_type=realtimehot","lfid":""},"desc":"\u738b\u4fca\u51ef\u4e0d\u5f97\u4e0dC","desc_extr":20110,"pic":"https:\/\/simg.s.weibo.com\/20170303_point_orange.png","scheme":"https:\/\/m.weibo.cn\/search?containerid=100103type%3D1%26t%3D10%26q%3D%23%E7%8E%8B%E4%BF%8A%E5%87%AF%E4%B8%8D%E5%BE%97%E4%B8%8DC%23&stream_entry_id=157&isnewpage=1&extparam=seat%3D1%26mi_cid%3D100103%26c_type%3D157%26lcate%3D5023%26pos%3D4%26cate%3D5023%26filter_type%3Dhotregion%26dgr%3D0%26display_time%3D1657983945%26pre_seqid%3D16579839450170435141369&luicode=10000011&lfid=106003type%253D25%2526t%253D3%2526disable_hot%253D1%2526filter_type%253Drealtimehot","card_type":4},{"itemid":"t:157|cate:5023|key:\u7f51\u4f20\u4e2d\u620f2022\u7ea7\u8868\u6f14\u7cfb\u672c\u79d1\u73ed\u540d\u5355|c_type:157|pos:1-4-5||type:25","actionlog":{"act_code":554,"ext":"seqid:16579839450170435141369|pos:1_6|cate:5023|key:#\u7f51\u4f20\u4e2d\u620f2022\u7ea7\u8868\u6f14\u7cfb\u672c\u79d1\u73ed\u540d\u5355#|c_type:157|t:157|page:1|type:25|dgr:0","luicode":"","act_type":1,"uicode":"","fid":"106003type=25&t=3&disable_hot=1&filter_type=realtimehot","lfid":""},"desc":"\u7f51\u4f20\u4e2d\u620f2022\u7ea7\u8868\u6f14\u7cfb\u672c\u79d1\u73ed\u540d\u5355","desc_extr":27686,"pic":"https:\/\/simg.s.weibo.com\/20170303_point_orange.png","scheme":"https:\/\/m.weibo.cn\/search?containerid=100103type%3D1%26t%3D10%26q%3D%23%E7%BD%91%E4%BC%A0%E4%B8%AD%E6%88%8F2022%E7%BA%A7%E8%A1%A8%E6%BC%94%E7%B3%BB%E6%9C%AC%E7%A7%91%E7%8F%AD%E5%90%8D%E5%8D%95%23&stream_entry_id=157&isnewpage=1&extparam=seat%3D1%26mi_cid%3D100103%26c_type%3D157%26lcate%3D5023%26pos%3D5%26cate%3D5023%26filter_type%3Dhotregion%26dgr%3D0%26display_time%3D1657983945%26pre_seqid%3D16579839450170435141369&luicode=10000011&lfid=106003type%253D25%2526t%253D3%2526disable_hot%253D1%2526filter_type%253Drealtimehot","card_type":4},{"itemid":"t:157|cate:5023|key:\u5e78\u798f\u5230\u4e07\u5bb6|c_type:157|pos:1-4-6||type:25","actionlog":{"act_code":554,"ext":"seqid:16579839450170435141369|pos:1_7|cate:5023|key:#\u5e78\u798f\u5230\u4e07\u5bb6#|c_type:157|t:157|page:1|type:25|dgr:0","luicode":"","act_type":1,"uicode":"","fid":"106003type=25&t=3&disable_hot=1&filter_type=realtimehot","lfid":""},"desc":"\u5e78\u798f\u5230\u4e07\u5bb6","desc_extr":105625,"pic":"https:\/\/simg.s.weibo.com\/20170303_point_orange.png","scheme":"http:\/\/m.weibo.cn\/c\/wbox?&id=j84w2uenjc&roomid=8327&q=%23%E5%B9%B8%E7%A6%8F%E5%88%B0%E4%B8%87%E5%AE%B6%23&extparam=seat%3D1%26mi_cid%3D100103%26c_type%3D157%26lcate%3D5023%26pos%3D6%26cate%3D5023%26filter_type%3Dhotregion%26dgr%3D0%26display_time%3D1657983945%26pre_seqid%3D16579839450170435141369&luicode=10000011&lfid=106003type%253D25%2526t%253D3%2526disable_hot%253D1%2526filter_type%253Drealtimehot","card_type":4},{"itemid":"t:157|cate:5023|key:\u9a6c\u542f\u8d8a|c_type:157|pos:1-4-7||type:25","actionlog":{"act_code":554,"ext":"seqid:16579839450170435141369|pos:1_8|cate:5023|key:\u9a6c\u542f\u8d8a|c_type:157|t:157|page:1|type:25|dgr:0","luicode":"","act_type":1,"uicode":"","fid":"106003type=25&t=3&disable_hot=1&filter_type=realtimehot","lfid":""},"desc":"\u9a6c\u542f\u8d8a","desc_extr":111856,"pic":"https:\/\/simg.s.weibo.com\/20170303_point_orange.png","scheme":"https:\/\/m.weibo.cn\/search?containerid=100103type%3D1%26t%3D10%26q%3D%E9%A9%AC%E5%90%AF%E8%B6%8A&stream_entry_id=157&isnewpage=1&extparam=seat%3D1%26mi_cid%3D100103%26c_type%3D157%26lcate%3D5023%26pos%3D7%26cate%3D5023%26filter_type%3Dhotregion%26dgr%3D0%26display_time%3D1657983945%26pre_seqid%3D16579839450170435141369&luicode=10000011&lfid=106003type%253D25%2526t%253D3%2526disable_hot%253D1%2526filter_type%253Drealtimehot","card_type":4},{"itemid":"t:157|cate:5023|key:\u59da\u741b \u540e\u7a7a\u7ffb\u8df3\u6c34|c_type:157|pos:1-4-8||type:25","actionlog":{"act_code":554,"ext":"seqid:16579839450170435141369|pos:1_9|cate:5023|key:\u59da\u741b \u540e\u7a7a\u7ffb\u8df3\u6c34|c_type:157|t:157|page:1|type:25|dgr:0","luicode":"","act_type":1,"uicode":"","fid":"106003type=25&t=3&disable_hot=1&filter_type=realtimehot","lfid":""},"desc":"\u59da\u741b \u540e\u7a7a\u7ffb\u8df3\u6c34","desc_extr":35536,"pic":"https:\/\/simg.s.weibo.com\/20170303_point_orange.png","scheme":"https:\/\/m.weibo.cn\/search?containerid=100103type%3D1%26t%3D10%26q%3D%E5%A7%9A%E7%90%9B+%E5%90%8E%E7%A9%BA%E7%BF%BB%E8%B7%B3%E6%B0%B4&stream_entry_id=157&isnewpage=1&extparam=seat%3D1%26mi_cid%3D100103%26c_type%3D157%26lcate%3D5023%26pos%3D8%26cate%3D5023%26filter_type%3Dhotregion%26dgr%3D0%26display_time%3D1657983945%26pre_seqid%3D16579839450170435141369&luicode=10000011&lfid=106003type%253D25%2526t%253D3%2526disable_hot%253D1%2526filter_type%253Drealtimehot","card_type":4},{"actionlog":{"act_code":554,"ext":"seqid:16579839450170435141369|pos:1_10|cate:5023|key:#\u5434\u78ca\u4e0d\u6127\u662f\u517b\u6210\u7cfb\u7ec5\u58eb#|c_type:157|t:157|page:1|type:25|dgr:0","luicode":"","act_type":1,"uicode":"","fid":"106003type=25&t=3&disable_hot=1&filter_type=realtimehot","lfid":""},"desc":"\u5434\u78ca\u4e0d\u6127\u662f\u517b\u6210\u7cfb\u7ec5\u58eb","desc_extr":38568,"itemid":"t:157|cate:5023|key:\u5434\u78ca\u4e0d\u6127\u662f\u517b\u6210\u7cfb\u7ec5\u58eb|c_type:157|pos:1-4-9||type:25","scheme":"https:\/\/m.weibo.cn\/search?containerid=100103type%3D1%26t%3D10%26q%3D%23%E5%90%B4%E7%A3%8A%E4%B8%8D%E6%84%A7%E6%98%AF%E5%85%BB%E6%88%90%E7%B3%BB%E7%BB%85%E5%A3%AB%23&stream_entry_id=157&isnewpage=1&extparam=seat%3D1%26mi_cid%3D100103%26c_type%3D157%26lcate%3D5023%26pos%3D9%26cate%3D5023%26filter_type%3Dhotregion%26dgr%3D0%26display_time%3D1657983945%26pre_seqid%3D16579839450170435141369&luicode=10000011&lfid=106003type%253D25%2526t%253D3%2526disable_hot%253D1%2526filter_type%253Drealtimehot","icon":"https:\/\/simg.s.weibo.com\/20210226_new.png","card_type":4,"pic":"https:\/\/simg.s.weibo.com\/20170303_point_orange.png"},{"actionlog":{"act_code":554,"ext":"seqid:16579839450170435141369|pos:1_-5|cate:5023|c_type:157|t:157|nav:more|page:1|type:25|dgr:0","luicode":"","act_type":1,"uicode":"","fid":"106003type=25&t=3&disable_hot=1&filter_type=realtimehot","lfid":""},"show_type":0,"desc":"\u67e5\u770b\u66f4\u591a\u6587\u5a31\u70ed\u641c","card_type":6,"display_arrow":1,"scheme":"https:\/\/m.weibo.cn\/feature\/applink?scheme=sinaweibo%3A%2F%2FpageInfo%3Fcontainerid%3D106003type%253D25%2526t%253D3%2526disable_hot%253D1%2526filter_type%253Dfun%26extparam%3Dseat%253D1%2526lcate%253D5023%2526dgr%253D0%2526display_time%253D1657983945%2526pre_seqid%253D16579839450170435141369"}],"show_type":0,"card_type":11},{"card_group":[{"actionlog":{"act_code":554,"ext":"seqid:16579839450170435141369|pos:0|cate:5081|c_type:558|t:558|nav:top|page:1|type:25|dgr:0","luicode":"","act_type":1,"uicode":"","fid":"106003type=25&t=3&disable_hot=1&filter_type=realtimehot","lfid":""},"desc":"\u66f4\u591a","title":" \u5b9e\u51b5\u70ed\u804a","left_tag_img":"https:\/\/simg.s.weibo.com\/20220608_shikreliao_icon.png","scheme":"http:\/\/m.weibo.cn\/c\/wbox?&id=4spniogr7b&page=pages%2FnewBandList%2Findex&extparam=seat%3D1%26lcate%3D5081%26dgr%3D0%26display_time%3D1657983945%26pre_seqid%3D16579839450170435141369&luicode=10000011&lfid=106003type%253D25%2526t%253D3%2526disable_hot%253D1%2526filter_type%253Drealtimehot","card_type":101},{"card_display_type":0,"actionlog":{"act_code":554,"ext":"seqid:16579839450170435141369|c_type:558|t:558|pos:0|lcat:5081|cate:5081|key:#\u661f\u6c49\u707f\u70c2#|page:1|type:25|dgr:0","luicode":"","act_type":1,"uicode":"","fid":"106003type=25&t=3&disable_hot=1&filter_type=realtimehot","lfid":""},"title_sub":"#\u661f\u6c49\u707f\u70c2#","desc":"@A\u7b71\u7b71\u60a0l\uff1a\u8d39\u5bfc\uff0c\u8d77\u5e8a\u4e86\u5417\uff0c\u5f00\u59cb\u526a\u7247\u4e86\u5427[doge]\u6211\u4eec\u5c31\u662f\u4f60\u7684\u52a8\u529b[\u6253call]\u200b","card_type":25,"pic":"https:\/\/simg.s.weibo.com\/20220704_entertainment_ranking_01.png","scheme":"http:\/\/m.weibo.cn\/c\/wbox?&id=j84w2uenjc&roomid=10576&q=%23%E6%98%9F%E6%B1%89%E7%81%BF%E7%83%82%23&extparam=seat%3D1%26mi_cid%3D100103%26c_type%3D558%26lcate%3D5081%26cate%3D5081%26pos%3D0%26dgr%3D0%26filter_type%3Drealtimehot%26display_time%3D1657983945%26pre_seqid%3D16579839450170435141369&luicode=10000011&lfid=106003type%253D25%2526t%253D3%2526disable_hot%253D1%2526filter_type%253Drealtimehot","display_arrow":0},{"card_display_type":0,"actionlog":{"act_code":554,"ext":"seqid:16579839450170435141369|c_type:558|t:558|pos:1|lcat:5081|cate:5081|key:#\u5e78\u798f\u5230\u4e07\u5bb6#|page:1|type:25|dgr:0","luicode":"","act_type":1,"uicode":"","fid":"106003type=25&t=3&disable_hot=1&filter_type=realtimehot","lfid":""},"title_sub":"#\u5e78\u798f\u5230\u4e07\u5bb6#","desc":"@\u7528\u62376546695055\uff1a\u6709\u65f6\u5019\u4e0d\u8981\uff0c\u548c\u4ed6\u4eec\u6bd4\uff0c\u6211\u4eec\u662f\u6276\u8d2b\u4e0a\u661f\u5267\uff0c\u522b\u62c9\u4f4e\u4e86\u6211\u4eec\u7684\u6863\u6b21\uff0c\u6211\u4eec\u597d\u591a\u592e\u89c6\u5a92\u4f53\u70b9\u8d5e\u5938\u4e86\uff0c\u660e\u5929\u8fd8\u6709\u592e\u89c6\u5a92\u4f53\u76f4\u64ad\u3002\u200b","card_type":25,"pic":"https:\/\/simg.s.weibo.com\/20220704_entertainment_ranking_02.png","scheme":"http:\/\/m.weibo.cn\/c\/wbox?&id=j84w2uenjc&roomid=8327&q=%23%E5%B9%B8%E7%A6%8F%E5%88%B0%E4%B8%87%E5%AE%B6%23&extparam=seat%3D1%26mi_cid%3D100103%26c_type%3D558%26lcate%3D5081%26cate%3D5081%26pos%3D1%26dgr%3D0%26filter_type%3Drealtimehot%26display_time%3D1657983945%26pre_seqid%3D16579839450170435141369&luicode=10000011&lfid=106003type%253D25%2526t%253D3%2526disable_hot%253D1%2526filter_type%253Drealtimehot","display_arrow":0},{"card_display_type":0,"actionlog":{"act_code":554,"ext":"seqid:16579839450170435141369|c_type:558|t:558|pos:2|lcat:5081|cate:5081|key:#\u4e2d\u56fd\u7537\u7beevs\u4e2d\u56fd\u53f0\u5317\u7537\u7bee#|page:1|type:25|dgr:0","luicode":"","act_type":1,"uicode":"","fid":"106003type=25&t=3&disable_hot=1&filter_type=realtimehot","lfid":""},"title_sub":"#\u4e2d\u56fd\u7537\u7beevs\u4e2d\u56fd\u53f0\u5317\u7537\u7bee#","desc":"@\u74a8\u74a8\u74a8\u74a8i\uff1a\u89e3\u8bf4\uff1a\u8d75\u777f\u548c\u88c1\u5224\u6c9f\u901a\u751a\u81f3\u9762\u5e26\u5fae\u7b11\u54c8\u54c8\u54c8\u54c8\u54c8\u54c8\u200b","card_type":25,"pic":"https:\/\/simg.s.weibo.com\/20220704_entertainment_ranking_03.png","scheme":"http:\/\/m.weibo.cn\/c\/wbox?&id=j84w2uenjc&roomid=10798&q=%23%E4%B8%AD%E5%9B%BD%E7%94%B7%E7%AF%AEvs%E4%B8%AD%E5%9B%BD%E5%8F%B0%E5%8C%97%E7%94%B7%E7%AF%AE%23&extparam=seat%3D1%26mi_cid%3D100103%26c_type%3D558%26lcate%3D5081%26cate%3D5081%26pos%3D2%26dgr%3D0%26filter_type%3Drealtimehot%26display_time%3D1657983945%26pre_seqid%3D16579839450170435141369&luicode=10000011&lfid=106003type%253D25%2526t%253D3%2526disable_hot%253D1%2526filter_type%253Drealtimehot","display_arrow":0},{"actionlog":{"act_code":554,"ext":"seqid:16579839450170435141369|pos:1_-5|cate:5081|c_type:558|t:558|nav:more|page:1|type:25|dgr:0","luicode":"","act_type":1,"uicode":"","fid":"106003type=25&t=3&disable_hot=1&filter_type=realtimehot","lfid":""},"show_type":0,"desc":"\u67e5\u770b\u66f4\u591a\u5b9e\u51b5\u70ed\u804a","card_type":6,"display_arrow":1,"scheme":"http:\/\/m.weibo.cn\/c\/wbox?&id=4spniogr7b&page=pages%2FnewBandList%2Findex&extparam=seat%3D1%26lcate%3D5081%26dgr%3D0%26display_time%3D1657983945%26pre_seqid%3D16579839450170435141369&luicode=10000011&lfid=106003type%253D25%2526t%253D3%2526disable_hot%253D1%2526filter_type%253Drealtimehot"}],"show_type":0,"card_type":11},{"card_group":[{"actionlog":{"act_code":554,"ext":"seqid:16579839450170435141369|pos:0|mpos:4|cate:10103|c_type:113|t:113|page:1|type:25|dgr:0","luicode":"","act_type":1,"uicode":"","fid":"106003type=25&t=3&disable_hot=1&filter_type=realtimehot","lfid":""},"sub_title":"\u597d\u53cb\u5708\u7684\u65b0\u9c9c\u70ed\u70b9","title":" \u597d\u53cb\u70ed\u641c","card_type":101,"scheme":"https:\/\/m.weibo.cn\/p\/index?containerid=106003type%3D25%26filter_type%3Dfriends&luicode=10000011&lfid=106003type%253D25%2526t%253D3%2526disable_hot%253D1%2526filter_type%253Drealtimehot","left_tag_img":"https:\/\/simg.s.weibo.com\/20200414_%E5%A5%BD%E5%8F%8B%E7%83%AD%E6%90%9C%403x.png"}],"show_type":0,"card_type":11},{"card_group":[{"scheme":"https:\/\/m.s.weibo.com\/hot\/description?luicode=10000011&lfid=106003type%253D25%2526t%253D3%2526disable_hot%253D1%2526filter_type%253Drealtimehot","title":" \u70ed\u641c\u699c\u89c4\u5219\u8bf4\u660e","left_tag_img":"https:\/\/simg.s.weibo.com\/20210705_search_icon_guize%403x.png","card_type":101}],"show_type":0,"card_type":11}],"cardlistInfo":{"title_top":"\u5fae\u535a\u70ed\u641c","show_style":1,"starttime":1657983945,"can_shared":0,"cardlist_head_cards":[{"show_menu":true,"head_type_name":"immersive","head_data":{"scheme":"https:\/\/m.weibo.cn\/feature\/applink?scheme=sinaweibo%3A%2F%2Fabc","cover_url":"https:\/\/simg.s.weibo.com\/20210521_hot_banner_h5.png","show_navi_mask":false,"data_type":2001,"show_title":false},"head_type":1,"title_top":"\u5fae\u535a\u70ed\u641c"},{"show_menu":false,"head_type_name":"channel_list","channel_list":[{"must_show":1,"default_add":1,"containerid":"106003_-_type:25_-_filter_type:mineband","name":"\u63a8\u8350","scheme":"sinaweibo:\/\/pageinfo?containerid=106003_-_type:25_-_filter_type:mineband&title=\u70ed\u641c\u699c&extparam=","id":1},{"must_show":1,"default_add":1,"containerid":"106003type=25&t=3&disable_hot=1&filter_type=realtimehot","name":"\u70ed\u641c","scheme":"sinaweibo:\/\/pageinfo?containerid=106003type=25&t=3&disable_hot=1&filter_type=realtimehot&title=\u70ed\u641c\u699c&extparam=","id":2},{"must_show":1,"default_add":1,"containerid":"106003type=25&t=3&disable_hot=1&filter_type=fun","name":"\u6587\u5a31","scheme":"sinaweibo:\/\/pageinfo?containerid=106003type=25&t=3&disable_hot=1&filter_type=fun&title=\u70ed\u641c\u699c&extparam=","id":3},{"must_show":1,"default_add":1,"containerid":"231648_-_3","name":"\u8981\u95fb","scheme":"sinaweibo:\/\/pageinfo?containerid=231648_-_3&title=\u70ed\u641c\u699c&extparam=","id":4}],"head_type":0}],"enable_load_imge_scrolling":1,"nick":"\u5fae\u535a\u70ed\u641c","page_title":"\u5fae\u535a\u70ed\u641c","config":{"effective_cache_duration":12},"containerid":"106003type=25&t=3&disable_hot=1&filter_type=realtimehot","total":20,"refresh_configs":{"106003type=25&t=3&disable_hot=1&filter_type=fun":5,"106003_-_type:25_-_filter_type:mineband":5,"106003type=25&t=3&disable_hot=1&filter_type=realtimehot":5,"231648_-_3":5},"v_p":"42","cardlist_menus":[],"headbg_animation":"scale","page_size":20,"page_type":"08","page":null},"scheme":"sinaweibo:\/\/pageinfo?containerid=106003type%253D25%2526t%253D3%2526disable_hot%253D1%2526filter_type%253Drealtimehot&extparam=filter_type%253Drealtimehot%2526mi_cid%253D100103%2526pos%253D0_0%2526c_type%253D30%2526display_time%253D1550505541&luicode=10000011&lfid=231583&_T_WM=52624855073&v_p=42","showAppTips":0}}