{"ok":1,"data":{"cards":[{"title":"\u5b9e\u65f6\u70ed\u70b9\uff0c\u6bcf\u5206\u949f\u66f4\u65b0\u4e00\u6b21","card_group":[{"icon":"https:\/\/simg.s.weibo.com\/moter\/flags\/2_0.png","icon_width":24,"itemid":"seqid:16876538895570640278|c_type:51|key:\u7aef\u5348\u5047\u671f\u56fd\u5185\u65c5\u6e381.06\u4ebf\u4eba\u6b21|cate:5000|t:51|qtime:1687653889|pos:1-2-0|type:25|srid:7bd33e3c6e04148aa87eca12e45a2a54","icon_height":24,"actionlog":{"fid":"106003type=25&t=3&disable_hot=1&filter_type=realtimehot","lfid":"","act_type":1,"act_code":554,"ext":"seqid:16876538895570640278|srid:7bd33e3c6e04148aa87eca12e45a2a54|c_type:51|key:#\u7aef\u5348\u5047\u671f\u56fd\u5185\u65c5\u6e381.06\u4ebf\u4eba\u6b21#|cate:5000|t:51|qtime:1687653889|pos:0_0|page:1|type:25|dgr:0","uicode":"","luicode":""},"desc":"\u7aef\u5348\u5047\u671f\u56fd\u5185\u65c5\u6e381.06\u4ebf\u4eba\u6b21","pic":"https:\/\/simg.s.weibo.com\/20180205110043_img_search_stick%403x.png","scheme":"https:\/\/m.weibo.cn\/search?containerid=100103type%3D1%26t%3D10%26q%3D%23%E7%AB%AF%E5%8D%88%E5%81%87%E6%9C%9F%E5%9B%BD%E5%86%85%E6%97%85%E6%B8%B81.06%E4%BA%BF%E4%BA%BA%E6%AC%A1%23&stream_entry_id=51&isnewpage=1&extparam=seat%3D1%26c_type%3D51%26cate%3D10103%26dgr%3D0%26filter_type%3Drealtimehot%26stream_entry_id%3D51%26pos%3D0%26display_time%3D1687653889%26pre_seqid%3D16876538895570640278&luicode=10000011&lfid=106003type%253D25%2526t%253D3%2526disable_hot%253D1%2526filter_type%253Drealtimehot","card_type":4},{"desc_extr":4179201,"icon":"https:\/\/simg.s.weibo.com\/moter\/flags\/2_0.png","pic":"https:\/\/simg.s.weibo.com\/wb_search_img_search_1.png","itemid":"seqid:16876538895570640278|c_type:31|key:#\u74e6\u683c\u7eb3\u4ece\u4fc4\u5357\u90e8\u519b\u533a\u53f8\u4ee4\u90e8\u64a4\u79bb#|cate:5001|t:31|qtime:1687653889|pos:1-1-0|type:25|srid:7bd33e3c6e04148aa87eca12e45a2a54","icon_height":24,"icon_width":24,"actionlog":{"fid":"106003type=25&t=3&disable_hot=1&filter_type=realtimehot","lfid":"","act_type":1,"act_code":554,"ext":"seqid:16876538895570640278|srid:7bd33e3c6e04148aa87eca12e45a2a54|c_type:31|key:#\u74e6\u683c\u7eb3\u4ece\u4fc4\u5357\u90e8\u519b\u533a\u53f8\u4ee4\u90e8\u64a4\u79bb#|cate:5001|t:31|qtime:1687653889|pos:1_0|page:1|type:25|dgr:0","uicode":"","luicode":""},"desc":"\u74e6\u683c\u7eb3\u4ece\u4fc4\u5357\u90e8\u519b\u533a\u53f8\u4ee4\u90e8\u64a4\u79bb","scheme":"https:\/\/m.weibo.cn\/search?containerid=100103type%3D1%26t%3D10%26q%3D%23%E7%93%A6%E6%A0%BC%E7%BA%B3%E4%BB%8E%E4%BF%84%E5%8D%97%E9%83%A8%E5%86%9B%E5%8C%BA%E5%8F%B8%E4%BB%A4%E9%83%A8%E6%92%A4%E7%A6%BB%23&stream_entry_id=31&isnewpage=1&extparam=seat%3D1%26band_rank%3D1%26flag%3D2%26dgr%3D0%26c_type%3D31%26lcate%3D5001%26cate%3D5001%26stream_entry_id%3D31%26q%3D%2523%25E7%2593%25A6%25E6%25A0%25BC%25E7%25BA%25B3%25E4%25BB%258E%25E4%25BF%2584%25E5%258D%2597%25E9%2583%25A8%25E5%2586%259B%25E5%258C%25BA%25E5%258F%25B8%25E4%25BB%25A4%25E9%2583%25A8%25E6%2592%25A4%25E7%25A6%25BB%2523%26filter_type%3Drealtimehot%26realpos%3D1%26pos%3D0%26display_time%3D1687653889%26pre_seqid%3D16876538895570640278&luicode=10000011&lfid=106003type%253D25%2526t%253D3%2526disable_hot%253D1%2526filter_type%253Drealtimehot","card_type":4},{"desc_extr":"\u5267\u96c6 2179238","icon":"https:\/\/simg.s.weibo.com\/moter\/flags\/1_0.png","pic":"https:\/\/simg.s.weibo.com\/wb_search_img_search_2.png","itemid":"seqid:16876538895570640278|c_type:31|key:\u9648\u98de\u5b87\u5b5f\u5b50\u4e49 \u96be\u54c4|cate:5001|t:31|qtime:1687653889|pos:1-1-1|type:25|srid:7bd33e3c6e04148aa87eca12e45a2a54","icon_height":24,"icon_width":24,"actionlog":{"fid":"106003type=25&t=3&disable_hot=1&filter_type=realtimehot","lfid":"","act_type":1,"act_code":554,"ext":"seqid:16876538895570640278|srid:7bd33e3c6e04148aa87eca12e45a2a54|c_type:31|key:\u9648\u98de\u5b87\u5b5f\u5b50\u4e49 \u96be\u54c4|cate:5001|t:31|qtime:1687653889|pos:1_1|page:1|type:25|dgr:0","uicode":"","luicode":""},"desc":"\u9648\u98de\u5b87\u5b5f\u5b50\u4e49 \u96be\u54c4","scheme":"https:\/\/m.weibo.cn\/search?containerid=100103type%3D1%26t%3D10%26q%3D%E9%99%88%E9%A3%9E%E5%AE%87%E5%AD%9F%E5%AD%90%E4%B9%89+%E9%9A%BE%E5%93%84&stream_entry_id=31&isnewpage=1&extparam=seat%3D1%26band_rank%3D2%26flag%3D1%26dgr%3D0%26c_type%3D31%26lcate%3D5001%26cate%3D5001%26stream_entry_id%3D31%26q%3D%25E9%2599%2588%25E9%25A3%259E%25E5%25AE%2587%25E5%25AD%259F%25E5%25AD%2590%25E4%25B9%2589%2520%25E9%259A%25BE%25E5%2593%2584%26filter_type%3Drealtimehot%26realpos%3D2%26pos%3D1%26display_time%3D1687653889%26pre_seqid%3D16876538895570640278&luicode=10000011&lfid=106003type%253D25%2526t%253D3%2526disable_hot%253D1%2526filter_type%253Drealtimehot","card_type":4},{"desc_extr":1643836,"desc":"\u4e16\u754c\u4e92\u8054\u7f51\u5927\u4f1a\u6570\u5b57\u6587\u660e\u5c3c\u5c71\u5bf9\u8bdd","pic":"https:\/\/simg.s.weibo.com\/wb_search_img_search_3.png","itemid":"seqid:16876538895570640278|c_type:31|key:#\u4e16\u754c\u4e92\u8054\u7f51\u5927\u4f1a\u6570\u5b57\u6587\u660e\u5c3c\u5c71\u5bf9\u8bdd#|cate:5001|t:31|qtime:1687653889|pos:1-1-2|type:25|srid:7bd33e3c6e04148aa87eca12e45a2a54","actionlog":{"fid":"106003type=25&t=3&disable_hot=1&filter_type=realtimehot","lfid":"","act_type":1,"act_code":554,"ext":"seqid:16876538895570640278|srid:7bd33e3c6e04148aa87eca12e45a2a54|c_type:31|key:#\u4e16\u754c\u4e92\u8054\u7f51\u5927\u4f1a\u6570\u5b57\u6587\u660e\u5c3c\u5c71\u5bf9\u8bdd#|cate:5001|t:31|qtime:1687653889|pos:1_2|page:1|type:25|dgr:0","uicode":"","luicode":""},"scheme":"https:\/\/m.weibo.cn\/search?containerid=100103type%3D1%26t%3D10%26q%3D%23%E4%B8%96%E7%95%8C%E4%BA%92%E8%81%94%E7%BD%91%E5%A4%A7%E4%BC%9A%E6%95%B0%E5%AD%97%E6%96%87%E6%98%8E%E5%B0%BC%E5%B1%B1%E5%AF%B9%E8%AF%9D%23&stream_entry_id=31&isnewpage=1&extparam=seat%3D1%26band_rank%3D3%26flag%3D0%26dgr%3D0%26c_type%3D31%26lcate%3D5001%26cate%3D5001%26stream_entry_id%3D31%26q%3D%2523%25E4%25B8%2596%25E7%2595%258C%25E4%25BA%2592%25E8%2581%2594%25E7%25BD%2591%25E5%25A4%25A7%25E4%25BC%259A%25E6%2595%25B0%25E5%25AD%2597%25E6%2596%2587%25E6%2598%258E%25E5%25B0%25BC%25E5%25B1%25B1%25E5%25AF%25B9%25E8%25AF%259D%2523%26filter_type%3Drealtimehot%26realpos%3D3%26pos%3D2%26display_time%3D1687653889%26pre_seqid%3D16876538895570640278&luicode=10000011&lfid=106003type%253D25%2526t%253D3%2526disable_hot%253D1%2526filter_type%253Drealtimehot","card_type":4},{"desc_extr":1581314,"icon":"https:\/\/simg.s.weibo.com\/moter\/flags\/1_0.png","pic":"https:\/\/simg.s.weibo.com\/wb_search_img_search_4.png","itemid":"seqid:16876538895570640278|c_type:31|key:#\u7537\u5b50\u6bcf\u59291\u65a4\u6768\u6885\u72c2\u540320\u5929\u8981\u505a\u8840\u900f#|cate:5001|t:31|qtime:1687653889|pos:1-1-3|type:25|srid:7bd33e3c6e04148aa87eca12e45a2a54","icon_height":24,"icon_width":24,"actionlog":{"fid":"106003type=25&t=3&disable_hot=1&filter_type=realtimehot","lfid":"","act_type":1,"act_code":554,"ext":"seqid:16876538895570640278|srid:7bd33e3c6e04148aa87eca12e45a2a54|c_type:31|key:#\u7537\u5b50\u6bcf\u59291\u65a4\u6768\u6885\u72c2\u540320\u5929\u8981\u505a\u8840\u900f#|cate:5001|t:31|qtime:1687653889|pos:1_3|page:1|type:25|dgr:0","uicode":"","luicode":""},"desc":"\u7537\u5b50\u6bcf\u59291\u65a4\u6768\u6885\u72c2\u540320\u5929\u8981\u505a\u8840\u900f","scheme":"https:\/\/m.weibo.cn\/search?containerid=100103type%3D1%26t%3D10%26q%3D%23%E7%94%B7%E5%AD%90%E6%AF%8F%E5%A4%A91%E6%96%A4%E6%9D%A8%E6%A2%85%E7%8B%82%E5%90%8320%E5%A4%A9%E8%A6%81%E5%81%9A%E8%A1%80%E9%80%8F%23&stream_entry_id=31&isnewpage=1&extparam=seat%3D1%26band_rank%3D4%26flag%3D1%26dgr%3D0%26c_type%3D31%26lcate%3D5001%26cate%3D5001%26stream_entry_id%3D31%26q%3D%2523%25E7%2594%25B7%25E5%25AD%2590%25E6%25AF%258F%25E5%25A4%25A91%25E6%2596%25A4%25E6%259D%25A8%25E6%25A2%2585%25E7%258B%2582%25E5%2590%258320%25E5%25A4%25A9%25E8%25A6%2581%25E5%2581%259A%25E8%25A1%2580%25E9%2580%258F%2523%26filter_type%3Drealtimehot%26realpos%3D4%26pos%3D3%26display_time%3D1687653889%26pre_seqid%3D16876538895570640278&luicode=10000011&lfid=106003type%253D25%2526t%253D3%2526disable_hot%253D1%2526filter_type%253Drealtimehot","card_type":4},{"desc_extr":1211097,"desc":"\u74e6\u683c\u7eb3\u540c\u610f\u505c\u6b62\u5728\u4fc4\u9886\u571f\u4e0a\u7684\u884c\u52a8","pic":"https:\/\/simg.s.weibo.com\/wb_search_img_search_5.png","itemid":"seqid:16876538895570640278|c_type:31|key:#\u74e6\u683c\u7eb3\u540c\u610f\u505c\u6b62\u5728\u4fc4\u9886\u571f\u4e0a\u7684\u884c\u52a8#|cate:5001|t:31|qtime:1687653889|pos:1-1-4|type:25|srid:7bd33e3c6e04148aa87eca12e45a2a54","actionlog":{"fid":"106003type=25&t=3&disable_hot=1&filter_type=realtimehot","lfid":"","act_type":1,"act_code":554,"ext":"seqid:16876538895570640278|srid:7bd33e3c6e04148aa87eca12e45a2a54|c_type:31|key:#\u74e6\u683c\u7eb3\u540c\u610f\u505c\u6b62\u5728\u4fc4\u9886\u571f\u4e0a\u7684\u884c\u52a8#|cate:5001|t:31|qtime:1687653889|pos:1_4|page:1|type:25|dgr:0","uicode":"","luicode":""},"scheme":"https:\/\/m.weibo.cn\/search?containerid=100103type%3D1%26t%3D10%26q%3D%23%E7%93%A6%E6%A0%BC%E7%BA%B3%E5%90%8C%E6%84%8F%E5%81%9C%E6%AD%A2%E5%9C%A8%E4%BF%84%E9%A2%86%E5%9C%9F%E4%B8%8A%E7%9A%84%E8%A1%8C%E5%8A%A8%23&stream_entry_id=31&isnewpage=1&extparam=seat%3D1%26band_rank%3D5%26flag%3D0%26dgr%3D0%26c_type%3D31%26lcate%3D5001%26cate%3D5001%26stream_entry_id%3D31%26q%3D%2523%25E7%2593%25A6%25E6%25A0%25BC%25E7%25BA%25B3%25E5%2590%258C%25E6%2584%258F%25E5%2581%259C%25E6%25AD%25A2%25E5%259C%25A8%25E4%25BF%2584%25E9%25A2%2586%25E5%259C%259F%25E4%25B8%258A%25E7%259A%2584%25E8%25A1%258C%25E5%258A%25A8%2523%26filter_type%3Drealtimehot%26realpos%3D5%26pos%3D4%26display_time%3D1687653889%26pre_seqid%3D16876538895570640278&luicode=10000011&lfid=106003type%253D25%2526t%253D3%2526disable_hot%253D1%2526filter_type%253Drealtimehot","card_type":4},{"desc_extr":"\u7535\u5f71 1182430","icon":"https:\/\/simg.s.weibo.com\/moter\/flags\/2_0.png","pic":"https:\/\/simg.s.weibo.com\/wb_search_img_search_6.png","itemid":"seqid:16876538895570640278|c_type:31|key:\u6d88\u5931\u7684\u5979 \u7edd\u4e16\u5927\u751c\u5267|cate:5001|t:31|qtime:1687653889|pos:1-1-5|type:25|srid:7bd33e3c6e04148aa87eca12e45a2a54","icon_height":24,"icon_width":24,"actionlog":{"fid":"106003type=25&t=3&disable_hot=1&filter_type=realtimehot","lfid":"","act_type":1,"act_code":554,"ext":"seqid:16876538895570640278|srid:7bd33e3c6e04148aa87eca12e45a2a54|c_type:31|key:\u6d88\u5931\u7684\u5979 \u7edd\u4e16\u5927\u751c\u5267|cate:5001|t:31|qtime:1687653889|pos:1_5|page:1|type:25|dgr:0","uicode":"","luicode":""},"desc":"\u6d88\u5931\u7684\u5979 \u7edd\u4e16\u5927\u751c\u5267","scheme":"https:\/\/m.weibo.cn\/search?containerid=100103type%3D1%26t%3D10%26q%3D%E6%B6%88%E5%A4%B1%E7%9A%84%E5%A5%B9+%E7%BB%9D%E4%B8%96%E5%A4%A7%E7%94%9C%E5%89%A7&stream_entry_id=31&isnewpage=1&extparam=seat%3D1%26band_rank%3D6%26flag%3D2%26dgr%3D0%26c_type%3D31%26lcate%3D5001%26cate%3D5001%26stream_entry_id%3D31%26q%3D%25E6%25B6%2588%25E5%25A4%25B1%25E7%259A%2584%25E5%25A5%25B9%2520%25E7%25BB%259D%25E4%25B8%2596%25E5%25A4%25A7%25E7%2594%259C%25E5%2589%25A7%26filter_type%3Drealtimehot%26realpos%3D6%26pos%3D5%26display_time%3D1687653889%26pre_seqid%3D16876538895570640278&luicode=10000011&lfid=106003type%253D25%2526t%253D3%2526disable_hot%253D1%2526filter_type%253Drealtimehot","card_type":4},{"desc_extr":"","icon":"https:\/\/simg.s.weibo.com\/20220424_search_ads_%E5%AE%98%E5%AE%A3.png","pic":"https:\/\/simg.s.weibo.com\/20210408_search_point_orange.png","itemid":"seqid:16876538895570640278|c_type:31|key:#\u8d75\u4e3d\u9896\u6234\u6bd4\u5c14\u65af\u54c1\u724c\u4ee3\u8a00\u4eba#|cate:5001|t:31|qtime:1687653889|pos:1-1-6|type:25|srid:7bd33e3c6e04148aa87eca12e45a2a54","icon_height":24,"icon_width":24,"actionlog":{"fid":"106003type=25&t=3&disable_hot=1&filter_type=realtimehot","lfid":"","act_type":1,"act_code":554,"ext":"seqid:16876538895570640278|srid:7bd33e3c6e04148aa87eca12e45a2a54|c_type:31|key:#\u8d75\u4e3d\u9896\u6234\u6bd4\u5c14\u65af\u54c1\u724c\u4ee3\u8a00\u4eba#|ads_word:#\u8d75\u4e3d\u9896\u6234\u6bd4\u5c14\u65af\u54c1\u724c\u4ee3\u8a00\u4eba#|cate:5001|t:31|adid:194299|qtime:1687653889|pos:1_6|page:1|type:25|dgr:0","uicode":"","luicode":""},"promotion":{"monitor_url":[{"type":"","third_party_click":"","third_party_show":""},{"type":"","third_party_click":"","third_party_show":""}]},"desc":"\u8d75\u4e3d\u9896\u6234\u6bd4\u5c14\u65af\u54c1\u724c\u4ee3\u8a00\u4eba","scheme":"https:\/\/m.weibo.cn\/search?containerid=100103type%3D1%26t%3D10%26q%3D%23%E8%B5%B5%E4%B8%BD%E9%A2%96%E6%88%B4%E6%AF%94%E5%B0%94%E6%96%AF%E5%93%81%E7%89%8C%E4%BB%A3%E8%A8%80%E4%BA%BA%23&stream_entry_id=31&isnewpage=1&extparam=seat%3D1%26band_rank%3D7%26is_ad_pos%3D1%26dgr%3D0%26topic_ad%3D1%26c_type%3D31%26lcate%3D5001%26cate%3D5001%26stream_entry_id%3D31%26adid%3D194299%26filter_type%3Drealtimehot%26q%3D%2523%25E8%25B5%25B5%25E4%25B8%25BD%25E9%25A2%2596%25E6%2588%25B4%25E6%25AF%2594%25E5%25B0%2594%25E6%2596%25AF%25E5%2593%2581%25E7%2589%258C%25E4%25BB%25A3%25E8%25A8%2580%25E4%25BA%25BA%2523%26pos%3D6%26display_time%3D1687653889%26pre_seqid%3D16876538895570640278&luicode=10000011&lfid=106003type%253D25%2526t%253D3%2526disable_hot%253D1%2526filter_type%253Drealtimehot","card_type":4},{"desc_extr":835507,"icon":"https:\/\/simg.s.weibo.com\/moter\/flags\/2_0.png","pic":"https:\/\/simg.s.weibo.com\/wb_search_img_search_7.png","itemid":"seqid:16876538895570640278|c_type:31|key:#\u5f1f\u5f1f\u8003673\u5206\u59d0\u59d0\u54ed\u4e86\u4e00\u5c0f\u65f6#|cate:5001|t:31|qtime:1687653889|pos:1-1-7|type:25|srid:7bd33e3c6e04148aa87eca12e45a2a54","icon_height":24,"icon_width":24,"actionlog":{"fid":"106003type=25&t=3&disable_hot=1&filter_type=realtimehot","lfid":"","act_type":1,"act_code":554,"ext":"seqid:16876538895570640278|srid:7bd33e3c6e04148aa87eca12e45a2a54|c_type:31|key:#\u5f1f\u5f1f\u8003673\u5206\u59d0\u59d0\u54ed\u4e86\u4e00\u5c0f\u65f6#|cate:5001|t:31|qtime:1687653889|pos:1_7|page:1|type:25|dgr:0","uicode":"","luicode":""},"desc":"\u5f1f\u5f1f\u8003673\u5206\u59d0\u59d0\u54ed\u4e86\u4e00\u5c0f\u65f6","scheme":"https:\/\/m.weibo.cn\/search?containerid=100103type%3D1%26t%3D10%26q%3D%23%E5%BC%9F%E5%BC%9F%E8%80%83673%E5%88%86%E5%A7%90%E5%A7%90%E5%93%AD%E4%BA%86%E4%B8%80%E5%B0%8F%E6%97%B6%23&stream_entry_id=31&isnewpage=1&extparam=seat%3D1%26band_rank%3D7%26flag%3D2%26dgr%3D0%26c_type%3D31%26lcate%3D5001%26cate%3D5001%26stream_entry_id%3D31%26q%3D%2523%25E5%25BC%259F%25E5%25BC%259F%25E8%2580%2583673%25E5%2588%2586%25E5%25A7%2590%25E5%25A7%2590%25E5%2593%25AD%25E4%25BA%2586%25E4%25B8%2580%25E5%25B0%258F%25E6%2597%25B6%2523%26filter_type%3Drealtimehot%26realpos%3D7%26pos%3D7%26display_time%3D1687653889%26pre_seqid%3D16876538895570640278&luicode=10000011&lfid=106003type%253D25%2526t%253D3%2526disable_hot%253D1%2526filter_type%253Drealtimehot","card_type":4},{"desc_extr":831449,"icon":"https:\/\/simg.s.weibo.com\/moter\/flags\/1_0.png","pic":"https:\/\/simg.s.weibo.com\/wb_search_img_search_8.png","itemid":"seqid:16876538895570640278|c_type:31|key:#\u5973\u5b69\u5145\u7535\u88ab\u7535\u51fb\u5185\u810f\u53d7\u635f\u9762\u4e34\u622a\u80a2#|cate:5001|t:31|qtime:1687653889|pos:1-1-8|type:25|srid:7bd33e3c6e04148aa87eca12e45a2a54","icon_height":24,"icon_width":24,"actionlog":{"fid":"106003type=25&t=3&disable_hot=1&filter_type=realtimehot","lfid":"","act_type":1,"act_code":554,"ext":"seqid:16876538895570640278|srid:7bd33e3c6e04148aa87eca12e45a2a54|c_type:31|key:#\u5973\u5b69\u5145\u7535\u88ab\u7535\u51fb\u5185\u810f\u53d7\u635f\u9762\u4e34\u622a\u80a2#|cate:5001|t:31|qtime:1687653889|pos:1_8|page:1|type:25|dgr:0","uicode":"","luicode":""},"desc":"\u5973\u5b69\u5145\u7535\u88ab\u7535\u51fb\u5185\u810f\u53d7\u635f\u9762\u4e34\u622a\u80a2","scheme":"https:\/\/m.weibo.cn\/search?containerid=100103type%3D1%26t%3D10%26q%3D%23%E5%A5%B3%E5%AD%A9%E5%85%85%E7%94%B5%E8%A2%AB%E7%94%B5%E5%87%BB%E5%86%85%E8%84%8F%E5%8F%97%E6%8D%9F%E9%9D%A2%E4%B8%B4%E6%88%AA%E8%82%A2%23&stream_entry_id=31&isnewpage=1&extparam=seat%3D1%26band_rank%3D8%26flag%3D1%26dgr%3D0%26c_type%3D31%26lcate%3D5001%26cate%3D5001%26stream_entry_id%3D31%26q%3D%2523%25E5%25A5%25B3%25E5%25AD%25A9%25E5%2585%2585%25E7%2594%25B5%25E8%25A2%25AB%25E7%2594%25B5%25E5%2587%25BB%25E5%2586%2585%25E8%2584%258F%25E5%258F%2597%25E6%258D%259F%25E9%259D%25A2%25E4%25B8%25B4%25E6%2588%25AA%25E8%2582%25A2%2523%26filter_type%3Drealtimehot%26realpos%3D8%26pos%3D8%26display_time%3D1687653889%26pre_seqid%3D16876538895570640278&luicode=10000011&lfid=106003type%253D25%2526t%253D3%2526disable_hot%253D1%2526filter_type%253Drealtimehot","card_type":4},{"desc_extr":"\u97f3\u4e50 796144","icon":"https:\/\/simg.s.weibo.com\/moter\/flags\/2_0.png","pic":"https:\/\/simg.s.weibo.com\/wb_search_img_search_9.png","itemid":"seqid:16876538895570640278|c_type:31|key:#\u5173\u6653\u5f64\u53bb\u4e86\u9e7f\u6657\u7684\u6f14\u5531\u4f1a#|cate:5001|t:31|qtime:1687653889|pos:1-1-9|type:25|srid:7bd33e3c6e04148aa87eca12e45a2a54","icon_height":24,"icon_width":24,"actionlog":{"fid":"106003type=25&t=3&disable_hot=1&filter_type=realtimehot","lfid":"","act_type":1,"act_code":554,"ext":"seqid:16876538895570640278|srid:7bd33e3c6e04148aa87eca12e45a2a54|c_type:31|key:#\u5173\u6653\u5f64\u53bb\u4e86\u9e7f\u6657\u7684\u6f14\u5531\u4f1a#|cate:5001|t:31|qtime:1687653889|pos:1_9|page:1|type:25|dgr:0","uicode":"","luicode":""},"desc":"\u5173\u6653\u5f64\u53bb\u4e86\u9e7f\u6657\u7684\u6f14\u5531\u4f1a","scheme":"https:\/\/m.weibo.cn\/search?containerid=100103type%3D1%26t%3D10%26q%3D%23%E5%85%B3%E6%99%93%E5%BD%A4%E5%8E%BB%E4%BA%86%E9%B9%BF%E6%99%97%E7%9A%84%E6%BC%94%E5%94%B1%E4%BC%9A%23&stream_entry_id=31&isnewpage=1&extparam=seat%3D1%26band_rank%3D9%26flag%3D2%26dgr%3D0%26c_type%3D31%26lcate%3D5001%26cate%3D5001%26stream_entry_id%3D31%26q%3D%2523%25E5%2585%25B3%25E6%2599%2593%25E5%25BD%25A4%25E5%258E%25BB%25E4%25BA%2586%25E9%25B9%25BF%25E6%2599%2597%25E7%259A%2584%25E6%25BC%2594%25E5%2594%25B1%25E4%25BC%259A%2523%26filter_type%3Drealtimehot%26realpos%3D9%26pos%3D9%26display_time%3D1687653889%26pre_seqid%3D16876538895570640278&luicode=10000011&lfid=106003type%253D25%2526t%253D3%2526disable_hot%253D1%2526filter_type%253Drealtimehot","card_type":4},{"desc_extr":721536,"icon":"https:\/\/simg.s.weibo.com\/moter\/flags\/32768_0.png","pic":"https:\/\/simg.s.weibo.com\/wb_search_img_search_10.png","itemid":"seqid:16876538895570640278|c_type:31|key:#\u5bb6\u957f\u4ee5\u4e3a\u4e2d\u8003\u7ba1\u996d\u9001\u5b8c\u5b69\u5b50\u53bb\u90ca\u6e38#|cate:5001|t:31|qtime:1687653889|pos:1-1-10|type:25|srid:7bd33e3c6e04148aa87eca12e45a2a54","icon_height":24,"icon_width":24,"actionlog":{"fid":"106003type=25&t=3&disable_hot=1&filter_type=realtimehot","lfid":"","act_type":1,"act_code":554,"ext":"seqid:16876538895570640278|srid:7bd33e3c6e04148aa87eca12e45a2a54|c_type:31|key:#\u5bb6\u957f\u4ee5\u4e3a\u4e2d\u8003\u7ba1\u996d\u9001\u5b8c\u5b69\u5b50\u53bb\u90ca\u6e38#|cate:5001|t:31|qtime:1687653889|pos:1_10|page:1|type:25|dgr:0","uicode":"","luicode":""},"desc":"\u5bb6\u957f\u4ee5\u4e3a\u4e2d\u8003\u7ba1\u996d\u9001\u5b8c\u5b69\u5b50\u53bb\u90ca\u6e38","scheme":"https:\/\/m.weibo.cn\/search?containerid=100103type%3D1%26t%3D10%26q%3D%23%E5%AE%B6%E9%95%BF%E4%BB%A5%E4%B8%BA%E4%B8%AD%E8%80%83%E7%AE%A1%E9%A5%AD%E9%80%81%E5%AE%8C%E5%AD%A9%E5%AD%90%E5%8E%BB%E9%83%8A%E6%B8%B8%23&stream_entry_id=31&isnewpage=1&extparam=seat%3D1%26band_rank%3D10%26flag%3D32768%26dgr%3D0%26c_type%3D31%26lcate%3D5001%26cate%3D5001%26stream_entry_id%3D31%26q%3D%2523%25E5%25AE%25B6%25E9%2595%25BF%25E4%25BB%25A5%25E4%25B8%25BA%25E4%25B8%25AD%25E8%2580%2583%25E7%25AE%25A1%25E9%25A5%25AD%25E9%2580%2581%25E5%25AE%258C%25E5%25AD%25A9%25E5%25AD%2590%25E5%258E%25BB%25E9%2583%258A%25E6%25B8%25B8%2523%26filter_type%3Drealtimehot%26realpos%3D10%26pos%3D10%26display_time%3D1687653889%26pre_seqid%3D16876538895570640278&luicode=10000011&lfid=106003type%253D25%2526t%253D3%2526disable_hot%253D1%2526filter_type%253Drealtimehot","card_type":4},{"desc_extr":572190,"icon":"https:\/\/simg.s.weibo.com\/moter\/flags\/2_0.png","pic":"https:\/\/simg.s.weibo.com\/wb_search_img_search_11.png","itemid":"seqid:16876538895570640278|c_type:31|key:#\u4f53\u80b2\u9986\u56de\u5e94\u6881\u9759\u8339\u6f14\u5531\u4f1a\u89c2\u4f17\u9f50\u558a\u5f00\u7a7a\u8c03#|cate:5001|t:31|qtime:1687653889|pos:1-1-11|type:25|srid:7bd33e3c6e04148aa87eca12e45a2a54","icon_height":24,"icon_width":24,"actionlog":{"fid":"106003type=25&t=3&disable_hot=1&filter_type=realtimehot","lfid":"","act_type":1,"act_code":554,"ext":"seqid:16876538895570640278|srid:7bd33e3c6e04148aa87eca12e45a2a54|c_type:31|key:#\u4f53\u80b2\u9986\u56de\u5e94\u6881\u9759\u8339\u6f14\u5531\u4f1a\u89c2\u4f17\u9f50\u558a\u5f00\u7a7a\u8c03#|cate:5001|t:31|qtime:1687653889|pos:1_11|page:1|type:25|dgr:0","uicode":"","luicode":""},"desc":"\u4f53\u80b2\u9986\u56de\u5e94\u6881\u9759\u8339\u6f14\u5531\u4f1a\u89c2\u4f17\u9f50\u558a\u5f00\u7a7a\u8c03","scheme":"https:\/\/m.weibo.cn\/search?containerid=100103type%3D1%26t%3D10%26q%3D%23%E4%BD%93%E8%82%B2%E9%A6%86%E5%9B%9E%E5%BA%94%E6%A2%81%E9%9D%99%E8%8C%B9%E6%BC%94%E5%94%B1%E4%BC%9A%E8%A7%82%E4%BC%97%E9%BD%90%E5%96%8A%E5%BC%80%E7%A9%BA%E8%B0%83%23&stream_entry_id=31&isnewpage=1&extparam=seat%3D1%26band_rank%3D11%26flag%3D2%26dgr%3D0%26c_type%3D31%26lcate%3D5001%26cate%3D5001%26stream_entry_id%3D31%26q%3D%2523%25E4%25BD%2593%25E8%2582%25B2%25E9%25A6%2586%25E5%259B%259E%25E5%25BA%2594%25E6%25A2%2581%25E9%259D%2599%25E8%258C%25B9%25E6%25BC%2594%25E5%2594%25B1%25E4%25BC%259A%25E8%25A7%2582%25E4%25BC%2597%25E9%25BD%2590%25E5%2596%258A%25E5%25BC%2580%25E7%25A9%25BA%25E8%25B0%2583%2523%26filter_type%3Drealtimehot%26realpos%3D11%26pos%3D11%26display_time%3D1687653889%26pre_seqid%3D16876538895570640278&luicode=10000011&lfid=106003type%253D25%2526t%253D3%2526disable_hot%253D1%2526filter_type%253Drealtimehot","card_type":4},{"desc_extr":555130,"icon":"https:\/\/simg.s.weibo.com\/moter\/flags\/1_0.png","pic":"https:\/\/simg.s.weibo.com\/wb_search_img_search_12.png","itemid":"seqid:16876538895570640278|c_type:31|key:#\u74e6\u683c\u7eb3\u96c6\u56e2\u5230\u5e95\u4ec0\u4e48\u6765\u5934#|cate:5001|t:31|qtime:1687653889|pos:1-1-12|type:25|srid:7bd33e3c6e04148aa87eca12e45a2a54","icon_height":24,"icon_width":24,"actionlog":{"fid":"106003type=25&t=3&disable_hot=1&filter_type=realtimehot","lfid":"","act_type":1,"act_code":554,"ext":"seqid:16876538895570640278|srid:7bd33e3c6e04148aa87eca12e45a2a54|c_type:31|key:#\u74e6\u683c\u7eb3\u96c6\u56e2\u5230\u5e95\u4ec0\u4e48\u6765\u5934#|cate:5001|t:31|qtime:1687653889|pos:1_12|page:1|type:25|dgr:0","uicode":"","luicode":""},"desc":"\u74e6\u683c\u7eb3\u96c6\u56e2\u5230\u5e95\u4ec0\u4e48\u6765\u5934","scheme":"https:\/\/m.weibo.cn\/search?containerid=100103type%3D1%26t%3D10%26q%3D%23%E7%93%A6%E6%A0%BC%E7%BA%B3%E9%9B%86%E5%9B%A2%E5%88%B0%E5%BA%95%E4%BB%80%E4%B9%88%E6%9D%A5%E5%A4%B4%23&stream_entry_id=31&isnewpage=1&extparam=seat%3D1%26band_rank%3D12%26flag%3D1%26dgr%3D0%26c_type%3D31%26lcate%3D5001%26cate%3D5001%26stream_entry_id%3D31%26q%3D%2523%25E7%2593%25A6%25E6%25A0%25BC%25E7%25BA%25B3%25E9%259B%2586%25E5%259B%25A2%25E5%2588%25B0%25E5%25BA%2595%25E4%25BB%2580%25E4%25B9%2588%25E6%259D%25A5%25E5%25A4%25B4%2523%26filter_type%3Drealtimehot%26realpos%3D12%26pos%3D12%26display_time%3D1687653889%26pre_seqid%3D16876538895570640278&luicode=10000011&lfid=106003type%253D25%2526t%253D3%2526disable_hot%253D1%2526filter_type%253Drealtimehot","card_type":4},{"desc_extr":525802,"icon":"https:\/\/simg.s.weibo.com\/moter\/flags\/2_0.png","pic":"https:\/\/simg.s.weibo.com\/wb_search_img_search_13.png","itemid":"seqid:16876538895570640278|c_type:31|key:#\u767d\u4fc4\u7f57\u65af#|cate:5001|t:31|qtime:1687653889|pos:1-1-13|type:25|srid:7bd33e3c6e04148aa87eca12e45a2a54","icon_height":24,"icon_width":24,"actionlog":{"fid":"106003type=25&t=3&disable_hot=1&filter_type=realtimehot","lfid":"","act_type":1,"act_code":554,"ext":"seqid:16876538895570640278|srid:7bd33e3c6e04148aa87eca12e45a2a54|c_type:31|key:#\u767d\u4fc4\u7f57\u65af#|cate:5001|t:31|qtime:1687653889|pos:1_13|page:1|type:25|dgr:0","uicode":"","luicode":""},"desc":"\u767d\u4fc4\u7f57\u65af","scheme":"https:\/\/m.weibo.cn\/search?containerid=100103type%3D1%26t%3D10%26q%3D%23%E7%99%BD%E4%BF%84%E7%BD%97%E6%96%AF%23&stream_entry_id=31&isnewpage=1&extparam=seat%3D1%26band_rank%3D13%26flag%3D2%26dgr%3D0%26c_type%3D31%26lcate%3D5001%26cate%3D5001%26stream_entry_id%3D31%26q%3D%2523%25E7%2599%25BD%25E4%25BF%2584%25E7%25BD%2597%25E6%2596%25AF%2523%26filter_type%3Drealtimehot%26realpos%3D13%26pos%3D13%26display_time%3D1687653889%26pre_seqid%3D16876538895570640278&luicode=10000011&lfid=106003type%253D25%2526t%253D3%2526disable_hot%253D1%2526filter_type%253Drealtimehot","card_type":4},{"desc_extr":"\u97f3\u4e50 498949","icon":"https:\/\/simg.s.weibo.com\/moter\/flags\/2_0.png","pic":"https:\/\/simg.s.weibo.com\/wb_search_img_search_14.png","itemid":"seqid:16876538895570640278|c_type:31|key:#\u9e7f\u6657\u6f14\u5531\u4f1a\u7684\u5973\u5b89\u68c0\u5458#|cate:5001|t:31|qtime:1687653889|pos:1-1-14|type:25|srid:7bd33e3c6e04148aa87eca12e45a2a54","icon_height":24,"icon_width":24,"actionlog":{"fid":"106003type=25&t=3&disable_hot=1&filter_type=realtimehot","lfid":"","act_type":1,"act_code":554,"ext":"seqid:16876538895570640278|srid:7bd33e3c6e04148aa87eca12e45a2a54|c_type:31|key:#\u9e7f\u6657\u6f14\u5531\u4f1a\u7684\u5973\u5b89\u68c0\u5458#|cate:5001|t:31|qtime:1687653889|pos:1_14|page:1|type:25|dgr:0","uicode":"","luicode":""},"desc":"\u9e7f\u6657\u6f14\u5531\u4f1a\u7684\u5973\u5b89\u68c0\u5458","scheme":"https:\/\/m.weibo.cn\/search?containerid=100103type%3D1%26t%3D10%26q%3D%23%E9%B9%BF%E6%99%97%E6%BC%94%E5%94%B1%E4%BC%9A%E7%9A%84%E5%A5%B3%E5%AE%89%E6%A3%80%E5%91%98%23&stream_entry_id=31&isnewpage=1&extparam=seat%3D1%26band_rank%3D14%26flag%3D2%26dgr%3D0%26c_type%3D31%26lcate%3D5001%26cate%3D5001%26stream_entry_id%3D31%26q%3D%2523%25E9%25B9%25BF%25E6%2599%2597%25E6%25BC%2594%25E5%2594%25B1%25E4%25BC%259A%25E7%259A%2584%25E5%25A5%25B3%25E5%25AE%2589%25E6%25A3%2580%25E5%2591%2598%2523%26filter_type%3Drealtimehot%26realpos%3D14%26pos%3D14%26display_time%3D1687653889%26pre_seqid%3D16876538895570640278&luicode=10000011&lfid=106003type%253D25%2526t%253D3%2526disable_hot%253D1%2526filter_type%253Drealtimehot","card_type":4},{"desc_extr":496207,"desc":"\u666e\u4eac\u6307\u8d23\u74e6\u683c\u7eb3\u8d1f\u8d23\u4eba\u53db\u56fd","pic":"https:\/\/simg.s.weibo.com\/wb_search_img_search_15.png","itemid":"seqid:16876538895570640278|c_type:31|key:#\u666e\u4eac\u6307\u8d23\u74e6\u683c\u7eb3\u8d1f\u8d23\u4eba\u53db\u56fd#|cate:5001|t:31|qtime:1687653889|pos:1-1-15|type:25|srid:7bd33e3c6e04148aa87eca12e45a2a54","actionlog":{"fid":"106003type=25&t=3&disable_hot=1&filter_type=realtimehot","lfid":"","act_type":1,"act_code":554,"ext":"seqid:16876538895570640278|srid:7bd33e3c6e04148aa87eca12e45a2a54|c_type:31|key:#\u666e\u4eac\u6307\u8d23\u74e6\u683c\u7eb3\u8d1f\u8d23\u4eba\u53db\u56fd#|cate:5001|t:31|qtime:1687653889|pos:1_15|page:1|type:25|dgr:0","uicode":"","luicode":""},"scheme":"https:\/\/m.weibo.cn\/search?containerid=100103type%3D1%26t%3D10%26q%3D%23%E6%99%AE%E4%BA%AC%E6%8C%87%E8%B4%A3%E7%93%A6%E6%A0%BC%E7%BA%B3%E8%B4%9F%E8%B4%A3%E4%BA%BA%E5%8F%9B%E5%9B%BD%23&stream_entry_id=31&isnewpage=1&extparam=seat%3D1%26band_rank%3D15%26flag%3D0%26dgr%3D0%26c_type%3D31%26lcate%3D5001%26cate%3D5001%26stream_entry_id%3D31%26q%3D%2523%25E6%2599%25AE%25E4%25BA%25AC%25E6%258C%2587%25E8%25B4%25A3%25E7%2593%25A6%25E6%25A0%25BC%25E7%25BA%25B3%25E8%25B4%259F%25E8%25B4%25A3%25E4%25BA%25BA%25E5%258F%259B%25E5%259B%25BD%2523%26filter_type%3Drealtimehot%26realpos%3D15%26pos%3D15%26display_time%3D1687653889%26pre_seqid%3D16876538895570640278&luicode=10000011&lfid=106003type%253D25%2526t%253D3%2526disable_hot%253D1%2526filter_type%253Drealtimehot","card_type":4},{"desc_extr":447331,"icon":"https:\/\/simg.s.weibo.com\/moter\/flags\/32768_0.png","pic":"https:\/\/simg.s.weibo.com\/wb_search_img_search_16.png","itemid":"seqid:16876538895570640278|c_type:31|key:#95\u540e\u5973\u751f\u65366\u5c81\u5c0f\u5f92\u5f1f\u4f20\u627f\u975e\u9057#|cate:5001|t:31|qtime:1687653889|pos:1-1-16|type:25|srid:7bd33e3c6e04148aa87eca12e45a2a54","icon_height":24,"icon_width":24,"actionlog":{"fid":"106003type=25&t=3&disable_hot=1&filter_type=realtimehot","lfid":"","act_type":1,"act_code":554,"ext":"seqid:16876538895570640278|srid:7bd33e3c6e04148aa87eca12e45a2a54|c_type:31|key:#95\u540e\u5973\u751f\u65366\u5c81\u5c0f\u5f92\u5f1f\u4f20\u627f\u975e\u9057#|cate:5001|t:31|qtime:1687653889|pos:1_16|page:1|type:25|dgr:0","uicode":"","luicode":""},"desc":"95\u540e\u5973\u751f\u65366\u5c81\u5c0f\u5f92\u5f1f\u4f20\u627f\u975e\u9057","scheme":"https:\/\/m.weibo.cn\/search?containerid=100103type%3D1%26t%3D10%26q%3D%2395%E5%90%8E%E5%A5%B3%E7%94%9F%E6%94%B66%E5%B2%81%E5%B0%8F%E5%BE%92%E5%BC%9F%E4%BC%A0%E6%89%BF%E9%9D%9E%E9%81%97%23&stream_entry_id=31&isnewpage=1&extparam=seat%3D1%26band_rank%3D16%26flag%3D32768%26dgr%3D0%26c_type%3D31%26lcate%3D5001%26cate%3D5001%26stream_entry_id%3D31%26q%3D%252395%25E5%2590%258E%25E5%25A5%25B3%25E7%2594%259F%25E6%2594%25B66%25E5%25B2%2581%25E5%25B0%258F%25E5%25BE%2592%25E5%25BC%259F%25E4%25BC%25A0%25E6%2589%25BF%25E9%259D%259E%25E9%2581%2597%2523%26filter_type%3Drealtimehot%26realpos%3D16%26pos%3D16%26display_time%3D1687653889%26pre_seqid%3D16876538895570640278&luicode=10000011&lfid=106003type%253D25%2526t%253D3%2526disable_hot%253D1%2526filter_type%253Drealtimehot","card_type":4},{"desc_extr":438749,"icon":"https:\/\/simg.s.weibo.com\/moter\/flags\/1_0.png","pic":"https:\/\/simg.s.weibo.com\/wb_search_img_search_17.png","itemid":"seqid:16876538895570640278|c_type:31|key:\u6e56\u5317\u5206\u6570\u7ebf \u780d\u4e00\u5200|cate:5001|t:31|qtime:1687653889|pos:1-1-17|type:25|srid:7bd33e3c6e04148aa87eca12e45a2a54","icon_height":24,"icon_width":24,"actionlog":{"fid":"106003type=25&t=3&disable_hot=1&filter_type=realtimehot","lfid":"","act_type":1,"act_code":554,"ext":"seqid:16876538895570640278|srid:7bd33e3c6e04148aa87eca12e45a2a54|c_type:31|key:\u6e56\u5317\u5206\u6570\u7ebf \u780d\u4e00\u5200|cate:5001|t:31|qtime:1687653889|pos:1_17|page:1|type:25|dgr:0","uicode":"","luicode":""},"desc":"\u6e56\u5317\u5206\u6570\u7ebf \u780d\u4e00\u5200","scheme":"https:\/\/m.weibo.cn\/search?containerid=100103type%3D1%26t%3D10%26q%3D%E6%B9%96%E5%8C%97%E5%88%86%E6%95%B0%E7%BA%BF+%E7%A0%8D%E4%B8%80%E5%88%80&stream_entry_id=31&isnewpage=1&extparam=seat%3D1%26band_rank%3D17%26flag%3D1%26dgr%3D0%26c_type%3D31%26lcate%3D5001%26cate%3D5001%26stream_entry_id%3D31%26q%3D%25E6%25B9%2596%25E5%258C%2597%25E5%2588%2586%25E6%2595%25B0%25E7%25BA%25BF%2520%25E7%25A0%258D%25E4%25B8%2580%25E5%2588%2580%26filter_type%3Drealtimehot%26realpos%3D17%26pos%3D17%26display_time%3D1687653889%26pre_seqid%3D16876538895570640278&luicode=10000011&lfid=106003type%253D25%2526t%253D3%2526disable_hot%253D1%2526filter_type%253Drealtimehot","card_type":4},{"desc_extr":434133,"icon":"https:\/\/simg.s.weibo.com\/moter\/flags\/32768_0.png","pic":"https:\/\/simg.s.weibo.com\/wb_search_img_search_18.png","itemid":"seqid:16876538895570640278|c_type:31|key:#\u7981\u6bd2\u8b66\u62cd\u5bb6\u5ead\u5408\u7167\u65f6\u4e0b\u610f\u8bc6\u80cc\u8fc7\u8eab#|cate:5001|t:31|qtime:1687653889|pos:1-1-18|type:25|srid:7bd33e3c6e04148aa87eca12e45a2a54","icon_height":24,"icon_width":24,"actionlog":{"fid":"106003type=25&t=3&disable_hot=1&filter_type=realtimehot","lfid":"","act_type":1,"act_code":554,"ext":"seqid:16876538895570640278|srid:7bd33e3c6e04148aa87eca12e45a2a54|c_type:31|key:#\u7981\u6bd2\u8b66\u62cd\u5bb6\u5ead\u5408\u7167\u65f6\u4e0b\u610f\u8bc6\u80cc\u8fc7\u8eab#|cate:5001|t:31|qtime:1687653889|pos:1_18|page:1|type:25|dgr:0","uicode":"","luicode":""},"desc":"\u7981\u6bd2\u8b66\u62cd\u5bb6\u5ead\u5408\u7167\u65f6\u4e0b\u610f\u8bc6\u80cc\u8fc7\u8eab","scheme":"https:\/\/m.weibo.cn\/search?containerid=100103type%3D1%26t%3D10%26q%3D%23%E7%A6%81%E6%AF%92%E8%AD%A6%E6%8B%8D%E5%AE%B6%E5%BA%AD%E5%90%88%E7%85%A7%E6%97%B6%E4%B8%8B%E6%84%8F%E8%AF%86%E8%83%8C%E8%BF%87%E8%BA%AB%23&stream_entry_id=31&isnewpage=1&extparam=seat%3D1%26band_rank%3D18%26flag%3D32768%26dgr%3D0%26c_type%3D31%26lcate%3D5001%26cate%3D5001%26stream_entry_id%3D31%26q%3D%2523%25E7%25A6%2581%25E6%25AF%2592%25E8%25AD%25A6%25E6%258B%258D%25E5%25AE%25B6%25E5%25BA%25AD%25E5%2590%2588%25E7%2585%25A7%25E6%2597%25B6%25E4%25B8%258B%25E6%2584%258F%25E8%25AF%2586%25E8%2583%258C%25E8%25BF%2587%25E8%25BA%25AB%2523%26filter_type%3Drealtimehot%26realpos%3D18%26pos%3D18%26display_time%3D1687653889%26pre_seqid%3D16876538895570640278&luicode=10000011&lfid=106003type%253D25%2526t%253D3%2526disable_hot%253D1%2526filter_type%253Drealtimehot","card_type":4},{"desc_extr":423509,"icon":"https:\/\/simg.s.weibo.com\/moter\/flags\/1_0.png","pic":"https:\/\/simg.s.weibo.com\/wb_search_img_search_19.png","itemid":"seqid:16876538895570640278|c_type:31|key:#\u6cf0\u598d\u53d6\u5173official\u8d26\u53f7#|cate:5001|t:31|qtime:1687653889|pos:1-1-19|type:25|srid:7bd33e3c6e04148aa87eca12e45a2a54","icon_height":24,"icon_width":24,"actionlog":{"fid":"106003type=25&t=3&disable_hot=1&filter_type=realtimehot","lfid":"","act_type":1,"act_code":554,"ext":"seqid:16876538895570640278|srid:7bd33e3c6e04148aa87eca12e45a2a54|c_type:31|key:#\u6cf0\u598d\u53d6\u5173official\u8d26\u53f7#|cate:5001|t:31|qtime:1687653889|pos:1_19|page:1|type:25|dgr:0","uicode":"","luicode":""},"desc":"\u6cf0\u598d\u53d6\u5173official\u8d26\u53f7","scheme":"https:\/\/m.weibo.cn\/search?containerid=100103type%3D1%26t%3D10%26q%3D%23%E6%B3%B0%E5%A6%8D%E5%8F%96%E5%85%B3official%E8%B4%A6%E5%8F%B7%23&stream_entry_id=31&isnewpage=1&extparam=seat%3D1%26band_rank%3D19%26flag%3D1%26dgr%3D0%26c_type%3D31%26lcate%3D5001%26cate%3D5001%26stream_entry_id%3D31%26q%3D%2523%25E6%25B3%25B0%25E5%25A6%258D%25E5%258F%2596%25E5%2585%25B3official%25E8%25B4%25A6%25E5%258F%25B7%2523%26filter_type%3Drealtimehot%26realpos%3D19%26pos%3D19%26display_time%3D1687653889%26pre_seqid%3D16876538895570640278&luicode=10000011&lfid=106003type%253D25%2526t%253D3%2526disable_hot%253D1%2526filter_type%253Drealtimehot","card_type":4},{"desc_extr":"\u7efc\u827a 387681","icon":"https:\/\/simg.s.weibo.com\/moter\/flags\/1_0.png","pic":"https:\/\/simg.s.weibo.com\/wb_search_img_search_20.png","itemid":"seqid:16876538895570640278|c_type:31|key:\u7f57\u6770\u592b \u62ab\u8346\u65a9\u68d8\u7684\u54e5\u54e5|cate:5001|t:31|qtime:1687653889|pos:1-1-20|type:25|srid:7bd33e3c6e04148aa87eca12e45a2a54","icon_height":24,"icon_width":24,"actionlog":{"fid":"106003type=25&t=3&disable_hot=1&filter_type=realtimehot","lfid":"","act_type":1,"act_code":554,"ext":"seqid:16876538895570640278|srid:7bd33e3c6e04148aa87eca12e45a2a54|c_type:31|key:\u7f57\u6770\u592b \u62ab\u8346\u65a9\u68d8\u7684\u54e5\u54e5|cate:5001|t:31|qtime:1687653889|pos:1_20|page:1|type:25|dgr:0","uicode":"","luicode":""},"desc":"\u7f57\u6770\u592b \u62ab\u8346\u65a9\u68d8\u7684\u54e5\u54e5","scheme":"https:\/\/m.weibo.cn\/search?containerid=100103type%3D1%26t%3D10%26q%3D%E7%BD%97%E6%9D%B0%E5%A4%AB+%E6%8A%AB%E8%8D%86%E6%96%A9%E6%A3%98%E7%9A%84%E5%93%A5%E5%93%A5&stream_entry_id=31&isnewpage=1&extparam=seat%3D1%26band_rank%3D20%26flag%3D1%26dgr%3D0%26c_type%3D31%26lcate%3D5001%26cate%3D5001%26stream_entry_id%3D31%26q%3D%25E7%25BD%2597%25E6%259D%25B0%25E5%25A4%25AB%2520%25E6%258A%25AB%25E8%258D%2586%25E6%2596%25A9%25E6%25A3%2598%25E7%259A%2584%25E5%2593%25A5%25E5%2593%25A5%26filter_type%3Drealtimehot%26realpos%3D20%26pos%3D20%26display_time%3D1687653889%26pre_seqid%3D16876538895570640278&luicode=10000011&lfid=106003type%253D25%2526t%253D3%2526disable_hot%253D1%2526filter_type%253Drealtimehot","card_type":4},{"desc_extr":387499,"icon":"https:\/\/simg.s.weibo.com\/moter\/flags\/1_0.png","pic":"https:\/\/simg.s.weibo.com\/wb_search_img_search_21.png","itemid":"seqid:16876538895570640278|c_type:31|key:#\u7537\u670b\u53cb\u5bf9\u6bcf\u4e00\u4efb\u5973\u670b\u53cb\u90fd\u5f88\u597d#|cate:5001|t:31|qtime:1687653889|pos:1-1-21|type:25|srid:7bd33e3c6e04148aa87eca12e45a2a54","icon_height":24,"icon_width":24,"actionlog":{"fid":"106003type=25&t=3&disable_hot=1&filter_type=realtimehot","lfid":"","act_type":1,"act_code":554,"ext":"seqid:16876538895570640278|srid:7bd33e3c6e04148aa87eca12e45a2a54|c_type:31|key:#\u7537\u670b\u53cb\u5bf9\u6bcf\u4e00\u4efb\u5973\u670b\u53cb\u90fd\u5f88\u597d#|cate:5001|t:31|qtime:1687653889|pos:1_21|page:1|type:25|dgr:0","uicode":"","luicode":""},"desc":"\u7537\u670b\u53cb\u5bf9\u6bcf\u4e00\u4efb\u5973\u670b\u53cb\u90fd\u5f88\u597d","scheme":"https:\/\/m.weibo.cn\/search?containerid=100103type%3D1%26t%3D10%26q%3D%23%E7%94%B7%E6%9C%8B%E5%8F%8B%E5%AF%B9%E6%AF%8F%E4%B8%80%E4%BB%BB%E5%A5%B3%E6%9C%8B%E5%8F%8B%E9%83%BD%E5%BE%88%E5%A5%BD%23&stream_entry_id=31&isnewpage=1&extparam=seat%3D1%26band_rank%3D21%26flag%3D1%26dgr%3D0%26c_type%3D31%26lcate%3D5001%26cate%3D5001%26stream_entry_id%3D31%26q%3D%2523%25E7%2594%25B7%25E6%259C%258B%25E5%258F%258B%25E5%25AF%25B9%25E6%25AF%258F%25E4%25B8%2580%25E4%25BB%25BB%25E5%25A5%25B3%25E6%259C%258B%25E5%258F%258B%25E9%2583%25BD%25E5%25BE%2588%25E5%25A5%25BD%2523%26filter_type%3Drealtimehot%26realpos%3D21%26pos%3D21%26display_time%3D1687653889%26pre_seqid%3D16876538895570640278&luicode=10000011&lfid=106003type%253D25%2526t%253D3%2526disable_hot%253D1%2526filter_type%253Drealtimehot","card_type":4},{"desc_extr":386371,"icon":"https:\/\/simg.s.weibo.com\/moter\/flags\/1_0.png","pic":"https:\/\/simg.s.weibo.com\/wb_search_img_search_22.png","itemid":"seqid:16876538895570640278|c_type:31|key:#\u95fa\u871c\u770b\u5b8c\u6d88\u5931\u7684\u5979\u548c\u5bf9\u8c61\u5206\u624b\u4e86#|cate:5001|t:31|qtime:1687653889|pos:1-1-22|type:25|srid:7bd33e3c6e04148aa87eca12e45a2a54","icon_height":24,"icon_width":24,"actionlog":{"fid":"106003type=25&t=3&disable_hot=1&filter_type=realtimehot","lfid":"","act_type":1,"act_code":554,"ext":"seqid:16876538895570640278|srid:7bd33e3c6e04148aa87eca12e45a2a54|c_type:31|key:#\u95fa\u871c\u770b\u5b8c\u6d88\u5931\u7684\u5979\u548c\u5bf9\u8c61\u5206\u624b\u4e86#|cate:5001|t:31|qtime:1687653889|pos:1_22|page:1|type:25|dgr:0","uicode":"","luicode":""},"desc":"\u95fa\u871c\u770b\u5b8c\u6d88\u5931\u7684\u5979\u548c\u5bf9\u8c61\u5206\u624b\u4e86","scheme":"https:\/\/m.weibo.cn\/search?containerid=100103type%3D1%26t%3D10%26q%3D%23%E9%97%BA%E8%9C%9C%E7%9C%8B%E5%AE%8C%E6%B6%88%E5%A4%B1%E7%9A%84%E5%A5%B9%E5%92%8C%E5%AF%B9%E8%B1%A1%E5%88%86%E6%89%8B%E4%BA%86%23&stream_entry_id=31&isnewpage=1&extparam=seat%3D1%26band_rank%3D22%26flag%3D1%26dgr%3D0%26c_type%3D31%26lcate%3D5001%26cate%3D5001%26stream_entry_id%3D31%26q%3D%2523%25E9%2597%25BA%25E8%259C%259C%25E7%259C%258B%25E5%25AE%258C%25E6%25B6%2588%25E5%25A4%25B1%25E7%259A%2584%25E5%25A5%25B9%25E5%2592%258C%25E5%25AF%25B9%25E8%25B1%25A1%25E5%2588%2586%25E6%2589%258B%25E4%25BA%2586%2523%26filter_type%3Drealtimehot%26realpos%3D22%26pos%3D22%26display_time%3D1687653889%26pre_seqid%3D16876538895570640278&luicode=10000011&lfid=106003type%253D25%2526t%253D3%2526disable_hot%253D1%2526filter_type%253Drealtimehot","card_type":4},{"desc_extr":"\u7535\u5f71 381269","icon":"https:\/\/simg.s.weibo.com\/moter\/flags\/2_0.png","pic":"https:\/\/simg.s.weibo.com\/wb_search_img_search_23.png","itemid":"seqid:16876538895570640278|c_type:31|key:#\u9648\u601d\u8bda\u900f\u9732\u8bef\u67403\u548c\u5510\u63a2\u65b0\u7247\u8fdb\u5ea6#|cate:5001|t:31|qtime:1687653889|pos:1-1-23|type:25|srid:7bd33e3c6e04148aa87eca12e45a2a54","icon_height":24,"icon_width":24,"actionlog":{"fid":"106003type=25&t=3&disable_hot=1&filter_type=realtimehot","lfid":"","act_type":1,"act_code":554,"ext":"seqid:16876538895570640278|srid:7bd33e3c6e04148aa87eca12e45a2a54|c_type:31|key:#\u9648\u601d\u8bda\u900f\u9732\u8bef\u67403\u548c\u5510\u63a2\u65b0\u7247\u8fdb\u5ea6#|cate:5001|t:31|qtime:1687653889|pos:1_23|page:1|type:25|dgr:0","uicode":"","luicode":""},"desc":"\u9648\u601d\u8bda\u900f\u9732\u8bef\u67403\u548c\u5510\u63a2\u65b0\u7247\u8fdb\u5ea6","scheme":"https:\/\/m.weibo.cn\/search?containerid=100103type%3D1%26t%3D10%26q%3D%23%E9%99%88%E6%80%9D%E8%AF%9A%E9%80%8F%E9%9C%B2%E8%AF%AF%E6%9D%803%E5%92%8C%E5%94%90%E6%8E%A2%E6%96%B0%E7%89%87%E8%BF%9B%E5%BA%A6%23&stream_entry_id=31&isnewpage=1&extparam=seat%3D1%26band_rank%3D23%26flag%3D2%26dgr%3D0%26c_type%3D31%26lcate%3D5001%26cate%3D5001%26stream_entry_id%3D31%26q%3D%2523%25E9%2599%2588%25E6%2580%259D%25E8%25AF%259A%25E9%2580%258F%25E9%259C%25B2%25E8%25AF%25AF%25E6%259D%25803%25E5%2592%258C%25E5%2594%2590%25E6%258E%25A2%25E6%2596%25B0%25E7%2589%2587%25E8%25BF%259B%25E5%25BA%25A6%2523%26filter_type%3Drealtimehot%26realpos%3D23%26pos%3D23%26display_time%3D1687653889%26pre_seqid%3D16876538895570640278&luicode=10000011&lfid=106003type%253D25%2526t%253D3%2526disable_hot%253D1%2526filter_type%253Drealtimehot","card_type":4},{"desc_extr":"\u97f3\u4e50 374945","icon":"https:\/\/simg.s.weibo.com\/moter\/flags\/1_0.png","pic":"https:\/\/simg.s.weibo.com\/wb_search_img_search_24.png","itemid":"seqid:16876538895570640278|c_type:31|key:#\u516d\u516c\u4e3b\u53d1\u7684\u9e7f\u6657\u76f4\u62cd#|cate:5001|t:31|qtime:1687653889|pos:1-1-24|type:25|srid:7bd33e3c6e04148aa87eca12e45a2a54","icon_height":24,"icon_width":24,"actionlog":{"fid":"106003type=25&t=3&disable_hot=1&filter_type=realtimehot","lfid":"","act_type":1,"act_code":554,"ext":"seqid:16876538895570640278|srid:7bd33e3c6e04148aa87eca12e45a2a54|c_type:31|key:#\u516d\u516c\u4e3b\u53d1\u7684\u9e7f\u6657\u76f4\u62cd#|cate:5001|t:31|qtime:1687653889|pos:1_24|page:1|type:25|dgr:0","uicode":"","luicode":""},"desc":"\u516d\u516c\u4e3b\u53d1\u7684\u9e7f\u6657\u76f4\u62cd","scheme":"https:\/\/m.weibo.cn\/search?containerid=100103type%3D1%26t%3D10%26q%3D%23%E5%85%AD%E5%85%AC%E4%B8%BB%E5%8F%91%E7%9A%84%E9%B9%BF%E6%99%97%E7%9B%B4%E6%8B%8D%23&stream_entry_id=31&isnewpage=1&extparam=seat%3D1%26band_rank%3D24%26flag%3D1%26dgr%3D0%26c_type%3D31%26lcate%3D5001%26cate%3D5001%26stream_entry_id%3D31%26q%3D%2523%25E5%2585%25AD%25E5%2585%25AC%25E4%25B8%25BB%25E5%258F%2591%25E7%259A%2584%25E9%25B9%25BF%25E6%2599%2597%25E7%259B%25B4%25E6%258B%258D%2523%26filter_type%3Drealtimehot%26realpos%3D24%26pos%3D24%26display_time%3D1687653889%26pre_seqid%3D16876538895570640278&luicode=10000011&lfid=106003type%253D25%2526t%253D3%2526disable_hot%253D1%2526filter_type%253Drealtimehot","card_type":4},{"desc_extr":"\u5267\u96c6 331661","icon":"https:\/\/simg.s.weibo.com\/moter\/flags\/2_0.png","pic":"https:\/\/simg.s.weibo.com\/wb_search_img_search_25.png","itemid":"seqid:16876538895570640278|c_type:31|key:#\u767d\u656c\u4ead\u5b8b\u8f76\u8138\u988a\u6bd4\u5fc3#|cate:5001|t:31|qtime:1687653889|pos:1-1-25|type:25|srid:7bd33e3c6e04148aa87eca12e45a2a54","icon_height":24,"icon_width":24,"actionlog":{"fid":"106003type=25&t=3&disable_hot=1&filter_type=realtimehot","lfid":"","act_type":1,"act_code":554,"ext":"seqid:16876538895570640278|srid:7bd33e3c6e04148aa87eca12e45a2a54|c_type:31|key:#\u767d\u656c\u4ead\u5b8b\u8f76\u8138\u988a\u6bd4\u5fc3#|cate:5001|t:31|qtime:1687653889|pos:1_25|page:1|type:25|dgr:0","uicode":"","luicode":""},"desc":"\u767d\u656c\u4ead\u5b8b\u8f76\u8138\u988a\u6bd4\u5fc3","scheme":"https:\/\/m.weibo.cn\/search?containerid=100103type%3D1%26t%3D10%26q%3D%23%E7%99%BD%E6%95%AC%E4%BA%AD%E5%AE%8B%E8%BD%B6%E8%84%B8%E9%A2%8A%E6%AF%94%E5%BF%83%23&stream_entry_id=31&isnewpage=1&extparam=seat%3D1%26band_rank%3D25%26flag%3D2%26dgr%3D0%26c_type%3D31%26lcate%3D5001%26cate%3D5001%26stream_entry_id%3D31%26q%3D%2523%25E7%2599%25BD%25E6%2595%25AC%25E4%25BA%25AD%25E5%25AE%258B%25E8%25BD%25B6%25E8%2584%25B8%25E9%25A2%258A%25E6%25AF%2594%25E5%25BF%2583%2523%26filter_type%3Drealtimehot%26realpos%3D25%26pos%3D25%26display_time%3D1687653889%26pre_seqid%3D16876538895570640278&luicode=10000011&lfid=106003type%253D25%2526t%253D3%2526disable_hot%253D1%2526filter_type%253Drealtimehot","card_type":4},{"desc_extr":331341,"icon":"https:\/\/simg.s.weibo.com\/moter\/flags\/1_0.png","pic":"https:\/\/simg.s.weibo.com\/wb_search_img_search_26.png","itemid":"seqid:16876538895570640278|c_type:31|key:#\u5de5\u4f5c\u540e\u50cf\u53d8\u4e86\u4e2a\u4eba#|cate:5001|t:31|qtime:1687653889|pos:1-1-26|type:25|srid:7bd33e3c6e04148aa87eca12e45a2a54","icon_height":24,"icon_width":24,"actionlog":{"fid":"106003type=25&t=3&disable_hot=1&filter_type=realtimehot","lfid":"","act_type":1,"act_code":554,"ext":"seqid:16876538895570640278|srid:7bd33e3c6e04148aa87eca12e45a2a54|c_type:31|key:#\u5de5\u4f5c\u540e\u50cf\u53d8\u4e86\u4e2a\u4eba#|cate:5001|t:31|qtime:1687653889|pos:1_26|page:1|type:25|dgr:0","uicode":"","luicode":""},"desc":"\u5de5\u4f5c\u540e\u50cf\u53d8\u4e86\u4e2a\u4eba","scheme":"https:\/\/m.weibo.cn\/search?containerid=100103type%3D1%26t%3D10%26q%3D%23%E5%B7%A5%E4%BD%9C%E5%90%8E%E5%83%8F%E5%8F%98%E4%BA%86%E4%B8%AA%E4%BA%BA%23&stream_entry_id=31&isnewpage=1&extparam=seat%3D1%26band_rank%3D26%26flag%3D1%26dgr%3D0%26c_type%3D31%26lcate%3D5001%26cate%3D5001%26stream_entry_id%3D31%26q%3D%2523%25E5%25B7%25A5%25E4%25BD%259C%25E5%2590%258E%25E5%2583%258F%25E5%258F%2598%25E4%25BA%2586%25E4%25B8%25AA%25E4%25BA%25BA%2523%26filter_type%3Drealtimehot%26realpos%3D26%26pos%3D26%26display_time%3D1687653889%26pre_seqid%3D16876538895570640278&luicode=10000011&lfid=106003type%253D25%2526t%253D3%2526disable_hot%253D1%2526filter_type%253Drealtimehot","card_type":4},{"desc_extr":303354,"desc":"\u60c5\u4fa3\u591a\u4e45\u4e0d\u8054\u7cfb\u7b97\u5206\u624b","pic":"https:\/\/simg.s.weibo.com\/wb_search_img_search_27.png","itemid":"seqid:16876538895570640278|c_type:31|key:\u60c5\u4fa3\u591a\u4e45\u4e0d\u8054\u7cfb\u7b97\u5206\u624b|cate:5001|t:31|qtime:1687653889|pos:1-1-27|type:25|srid:7bd33e3c6e04148aa87eca12e45a2a54","actionlog":{"fid":"106003type=25&t=3&disable_hot=1&filter_type=realtimehot","lfid":"","act_type":1,"act_code":554,"ext":"seqid:16876538895570640278|srid:7bd33e3c6e04148aa87eca12e45a2a54|c_type:31|key:\u60c5\u4fa3\u591a\u4e45\u4e0d\u8054\u7cfb\u7b97\u5206\u624b|cate:5001|t:31|qtime:1687653889|pos:1_27|page:1|type:25|dgr:0","uicode":"","luicode":""},"scheme":"https:\/\/m.weibo.cn\/search?containerid=100103type%3D1%26t%3D10%26q%3D%E6%83%85%E4%BE%A3%E5%A4%9A%E4%B9%85%E4%B8%8D%E8%81%94%E7%B3%BB%E7%AE%97%E5%88%86%E6%89%8B&stream_entry_id=31&isnewpage=1&extparam=seat%3D1%26band_rank%3D27%26flag%3D0%26dgr%3D0%26c_type%3D31%26lcate%3D5001%26cate%3D5001%26stream_entry_id%3D31%26q%3D%25E6%2583%2585%25E4%25BE%25A3%25E5%25A4%259A%25E4%25B9%2585%25E4%25B8%258D%25E8%2581%2594%25E7%25B3%25BB%25E7%25AE%2597%25E5%2588%2586%25E6%2589%258B%26filter_type%3Drealtimehot%26realpos%3D27%26pos%3D27%26display_time%3D1687653889%26pre_seqid%3D16876538895570640278&luicode=10000011&lfid=106003type%253D25%2526t%253D3%2526disable_hot%253D1%2526filter_type%253Drealtimehot","card_type":4},{"desc_extr":295327,"icon":"https:\/\/simg.s.weibo.com\/moter\/flags\/1_0.png","pic":"https:\/\/simg.s.weibo.com\/wb_search_img_search_28.png","itemid":"seqid:16876538895570640278|c_type:31|key:#\u5982\u4f55\u4e24\u4e2a\u6708\u5185\u5feb\u901f\u6539\u53d8\u81ea\u5df1#|cate:5001|t:31|qtime:1687653889|pos:1-1-28|type:25|srid:7bd33e3c6e04148aa87eca12e45a2a54","icon_height":24,"icon_width":24,"actionlog":{"fid":"106003type=25&t=3&disable_hot=1&filter_type=realtimehot","lfid":"","act_type":1,"act_code":554,"ext":"seqid:16876538895570640278|srid:7bd33e3c6e04148aa87eca12e45a2a54|c_type:31|key:#\u5982\u4f55\u4e24\u4e2a\u6708\u5185\u5feb\u901f\u6539\u53d8\u81ea\u5df1#|cate:5001|t:31|qtime:1687653889|pos:1_28|page:1|type:25|dgr:0","uicode":"","luicode":""},"desc":"\u5982\u4f55\u4e24\u4e2a\u6708\u5185\u5feb\u901f\u6539\u53d8\u81ea\u5df1","scheme":"https:\/\/m.weibo.cn\/search?containerid=100103type%3D1%26t%3D10%26q%3D%23%E5%A6%82%E4%BD%95%E4%B8%A4%E4%B8%AA%E6%9C%88%E5%86%85%E5%BF%AB%E9%80%9F%E6%94%B9%E5%8F%98%E8%87%AA%E5%B7%B1%23&stream_entry_id=31&isnewpage=1&extparam=seat%3D1%26band_rank%3D28%26flag%3D1%26dgr%3D0%26c_type%3D31%26lcate%3D5001%26cate%3D5001%26stream_entry_id%3D31%26q%3D%2523%25E5%25A6%2582%25E4%25BD%2595%25E4%25B8%25A4%25E4%25B8%25AA%25E6%259C%2588%25E5%2586%2585%25E5%25BF%25AB%25E9%2580%259F%25E6%2594%25B9%25E5%258F%2598%25E8%2587%25AA%25E5%25B7%25B1%2523%26filter_type%3Drealtimehot%26realpos%3D28%26pos%3D28%26display_time%3D1687653889%26pre_seqid%3D16876538895570640278&luicode=10000011&lfid=106003type%253D25%2526t%253D3%2526disable_hot%253D1%2526filter_type%253Drealtimehot","card_type":4},{"desc_extr":292177,"icon":"https:\/\/simg.s.weibo.com\/moter\/flags\/1_0.png","pic":"https:\/\/simg.s.weibo.com\/wb_search_img_search_29.png","itemid":"seqid:16876538895570640278|c_type:31|key:#\u738b\u5609\u5c14\u628a\u897f\u6e38\u8bb0\u7eb9\u8eab\u4e0a#|cate:5001|t:31|qtime:1687653889|pos:1-1-29|type:25|srid:7bd33e3c6e04148aa87eca12e45a2a54","icon_height":24,"icon_width":24,"actionlog":{"fid":"106003type=25&t=3&disable_hot=1&filter_type=realtimehot","lfid":"","act_type":1,"act_code":554,"ext":"seqid:16876538895570640278|srid:7bd33e3c6e04148aa87eca12e45a2a54|c_type:31|key:#\u738b\u5609\u5c14\u628a\u897f\u6e38\u8bb0\u7eb9\u8eab\u4e0a#|cate:5001|t:31|qtime:1687653889|pos:1_29|page:1|type:25|dgr:0","uicode":"","luicode":""},"desc":"\u738b\u5609\u5c14\u628a\u897f\u6e38\u8bb0\u7eb9\u8eab\u4e0a","scheme":"https:\/\/m.weibo.cn\/search?containerid=100103type%3D1%26t%3D10%26q%3D%23%E7%8E%8B%E5%98%89%E5%B0%94%E6%8A%8A%E8%A5%BF%E6%B8%B8%E8%AE%B0%E7%BA%B9%E8%BA%AB%E4%B8%8A%23&stream_entry_id=31&isnewpage=1&extparam=seat%3D1%26band_rank%3D29%26flag%3D1%26dgr%3D0%26c_type%3D31%26lcate%3D5001%26cate%3D5001%26stream_entry_id%3D31%26q%3D%2523%25E7%258E%258B%25E5%2598%2589%25E5%25B0%2594%25E6%258A%258A%25E8%25A5%25BF%25E6%25B8%25B8%25E8%25AE%25B0%25E7%25BA%25B9%25E8%25BA%25AB%25E4%25B8%258A%2523%26filter_type%3Drealtimehot%26realpos%3D29%26pos%3D29%26display_time%3D1687653889%26pre_seqid%3D16876538895570640278&luicode=10000011&lfid=106003type%253D25%2526t%253D3%2526disable_hot%253D1%2526filter_type%253Drealtimehot","card_type":4},{"desc_extr":278117,"desc":"\u6c5f\u82cf\u9ad8\u8003687\u5206\u53ca\u4ee5\u4e0a116\u4eba","pic":"https:\/\/simg.s.weibo.com\/wb_search_img_search_30.png","itemid":"seqid:16876538895570640278|c_type:31|key:#\u6c5f\u82cf\u9ad8\u8003687\u5206\u53ca\u4ee5\u4e0a116\u4eba#|cate:5001|t:31|qtime:1687653889|pos:1-1-30|type:25|srid:7bd33e3c6e04148aa87eca12e45a2a54","actionlog":{"fid":"106003type=25&t=3&disable_hot=1&filter_type=realtimehot","lfid":"","act_type":1,"act_code":554,"ext":"seqid:16876538895570640278|srid:7bd33e3c6e04148aa87eca12e45a2a54|c_type:31|key:#\u6c5f\u82cf\u9ad8\u8003687\u5206\u53ca\u4ee5\u4e0a116\u4eba#|cate:5001|t:31|qtime:1687653889|pos:1_30|page:1|type:25|dgr:0","uicode":"","luicode":""},"scheme":"https:\/\/m.weibo.cn\/search?containerid=100103type%3D1%26t%3D10%26q%3D%23%E6%B1%9F%E8%8B%8F%E9%AB%98%E8%80%83687%E5%88%86%E5%8F%8A%E4%BB%A5%E4%B8%8A116%E4%BA%BA%23&stream_entry_id=31&isnewpage=1&extparam=seat%3D1%26band_rank%3D30%26flag%3D0%26dgr%3D0%26c_type%3D31%26lcate%3D5001%26cate%3D5001%26stream_entry_id%3D31%26q%3D%2523%25E6%25B1%259F%25E8%258B%258F%25E9%25AB%2598%25E8%2580%2583687%25E5%2588%2586%25E5%258F%258A%25E4%25BB%25A5%25E4%25B8%258A116%25E4%25BA%25BA%2523%26filter_type%3Drealtimehot%26realpos%3D30%26pos%3D30%26display_time%3D1687653889%26pre_seqid%3D16876538895570640278&luicode=10000011&lfid=106003type%253D25%2526t%253D3%2526disable_hot%253D1%2526filter_type%253Drealtimehot","card_type":4},{"desc_extr":274895,"icon":"https:\/\/simg.s.weibo.com\/moter\/flags\/1_0.png","pic":"https:\/\/simg.s.weibo.com\/wb_search_img_search_31.png","itemid":"seqid:16876538895570640278|c_type:31|key:\u65b0\u534e\u4e66\u5e97\u624d\u662f\u9690\u85cf\u7684\u7ec8\u6781\u5927\u4f6c|cate:5001|t:31|qtime:1687653889|pos:1-1-31|type:25|srid:7bd33e3c6e04148aa87eca12e45a2a54","icon_height":24,"icon_width":24,"actionlog":{"fid":"106003type=25&t=3&disable_hot=1&filter_type=realtimehot","lfid":"","act_type":1,"act_code":554,"ext":"seqid:16876538895570640278|srid:7bd33e3c6e04148aa87eca12e45a2a54|c_type:31|key:\u65b0\u534e\u4e66\u5e97\u624d\u662f\u9690\u85cf\u7684\u7ec8\u6781\u5927\u4f6c|cate:5001|t:31|qtime:1687653889|pos:1_31|page:1|type:25|dgr:0","uicode":"","luicode":""},"desc":"\u65b0\u534e\u4e66\u5e97\u624d\u662f\u9690\u85cf\u7684\u7ec8\u6781\u5927\u4f6c","scheme":"https:\/\/m.weibo.cn\/search?containerid=100103type%3D1%26t%3D10%26q%3D%E6%96%B0%E5%8D%8E%E4%B9%A6%E5%BA%97%E6%89%8D%E6%98%AF%E9%9A%90%E8%97%8F%E7%9A%84%E7%BB%88%E6%9E%81%E5%A4%A7%E4%BD%AC&stream_entry_id=31&isnewpage=1&extparam=seat%3D1%26band_rank%3D31%26flag%3D1%26dgr%3D0%26c_type%3D31%26lcate%3D5001%26cate%3D5001%26stream_entry_id%3D31%26q%3D%25E6%2596%25B0%25E5%258D%258E%25E4%25B9%25A6%25E5%25BA%2597%25E6%2589%258D%25E6%2598%25AF%25E9%259A%2590%25E8%2597%258F%25E7%259A%2584%25E7%25BB%2588%25E6%259E%2581%25E5%25A4%25A7%25E4%25BD%25AC%26filter_type%3Drealtimehot%26realpos%3D31%26pos%3D31%26display_time%3D1687653889%26pre_seqid%3D16876538895570640278&luicode=10000011&lfid=106003type%253D25%2526t%253D3%2526disable_hot%253D1%2526filter_type%253Drealtimehot","card_type":4},{"desc_extr":271130,"desc":"\u4fc4\u5a92\u79f0\u4fc4\u519b\u5df2\u5728\u83ab\u65af\u79d1\u5e02\u90ca\u67b6\u8bbe\u673a\u67aa\u9635\u5730","pic":"https:\/\/simg.s.weibo.com\/wb_search_img_search_32.png","itemid":"seqid:16876538895570640278|c_type:31|key:#\u4fc4\u5a92\u79f0\u4fc4\u519b\u5df2\u5728\u83ab\u65af\u79d1\u5e02\u90ca\u67b6\u8bbe\u673a\u67aa\u9635\u5730#|cate:5001|t:31|qtime:1687653889|pos:1-1-32|type:25|srid:7bd33e3c6e04148aa87eca12e45a2a54","actionlog":{"fid":"106003type=25&t=3&disable_hot=1&filter_type=realtimehot","lfid":"","act_type":1,"act_code":554,"ext":"seqid:16876538895570640278|srid:7bd33e3c6e04148aa87eca12e45a2a54|c_type:31|key:#\u4fc4\u5a92\u79f0\u4fc4\u519b\u5df2\u5728\u83ab\u65af\u79d1\u5e02\u90ca\u67b6\u8bbe\u673a\u67aa\u9635\u5730#|cate:5001|t:31|qtime:1687653889|pos:1_32|page:1|type:25|dgr:0","uicode":"","luicode":""},"scheme":"https:\/\/m.weibo.cn\/search?containerid=100103type%3D1%26t%3D10%26q%3D%23%E4%BF%84%E5%AA%92%E7%A7%B0%E4%BF%84%E5%86%9B%E5%B7%B2%E5%9C%A8%E8%8E%AB%E6%96%AF%E7%A7%91%E5%B8%82%E9%83%8A%E6%9E%B6%E8%AE%BE%E6%9C%BA%E6%9E%AA%E9%98%B5%E5%9C%B0%23&stream_entry_id=31&isnewpage=1&extparam=seat%3D1%26band_rank%3D32%26flag%3D0%26dgr%3D0%26c_type%3D31%26lcate%3D5001%26cate%3D5001%26stream_entry_id%3D31%26q%3D%2523%25E4%25BF%2584%25E5%25AA%2592%25E7%25A7%25B0%25E4%25BF%2584%25E5%2586%259B%25E5%25B7%25B2%25E5%259C%25A8%25E8%258E%25AB%25E6%2596%25AF%25E7%25A7%2591%25E5%25B8%2582%25E9%2583%258A%25E6%259E%25B6%25E8%25AE%25BE%25E6%259C%25BA%25E6%259E%25AA%25E9%2598%25B5%25E5%259C%25B0%2523%26filter_type%3Drealtimehot%26realpos%3D32%26pos%3D32%26display_time%3D1687653889%26pre_seqid%3D16876538895570640278&luicode=10000011&lfid=106003type%253D25%2526t%253D3%2526disable_hot%253D1%2526filter_type%253Drealtimehot","card_type":4},{"desc_extr":265755,"desc":"\u5185\u5411\u548c\u5916\u5411\u7684\u5c0f\u72d7\u592a\u660e\u663e\u4e86","pic":"https:\/\/simg.s.weibo.com\/wb_search_img_search_33.png","itemid":"seqid:16876538895570640278|c_type:31|key:\u5185\u5411\u548c\u5916\u5411\u7684\u5c0f\u72d7\u592a\u660e\u663e\u4e86|cate:5001|t:31|qtime:1687653889|pos:1-1-33|type:25|srid:7bd33e3c6e04148aa87eca12e45a2a54","actionlog":{"fid":"106003type=25&t=3&disable_hot=1&filter_type=realtimehot","lfid":"","act_type":1,"act_code":554,"ext":"seqid:16876538895570640278|srid:7bd33e3c6e04148aa87eca12e45a2a54|c_type:31|key:\u5185\u5411\u548c\u5916\u5411\u7684\u5c0f\u72d7\u592a\u660e\u663e\u4e86|cate:5001|t:31|qtime:1687653889|pos:1_33|page:1|type:25|dgr:0","uicode":"","luicode":""},"scheme":"https:\/\/m.weibo.cn\/search?containerid=100103type%3D1%26t%3D10%26q%3D%E5%86%85%E5%90%91%E5%92%8C%E5%A4%96%E5%90%91%E7%9A%84%E5%B0%8F%E7%8B%97%E5%A4%AA%E6%98%8E%E6%98%BE%E4%BA%86&stream_entry_id=31&isnewpage=1&extparam=seat%3D1%26band_rank%3D33%26flag%3D0%26dgr%3D0%26c_type%3D31%26lcate%3D5001%26cate%3D5001%26stream_entry_id%3D31%26q%3D%25E5%2586%2585%25E5%2590%2591%25E5%2592%258C%25E5%25A4%2596%25E5%2590%2591%25E7%259A%2584%25E5%25B0%258F%25E7%258B%2597%25E5%25A4%25AA%25E6%2598%258E%25E6%2598%25BE%25E4%25BA%2586%26filter_type%3Drealtimehot%26realpos%3D33%26pos%3D33%26display_time%3D1687653889%26pre_seqid%3D16876538895570640278&luicode=10000011&lfid=106003type%253D25%2526t%253D3%2526disable_hot%253D1%2526filter_type%253Drealtimehot","card_type":4},{"desc_extr":262827,"icon":"https:\/\/simg.s.weibo.com\/moter\/flags\/1_0.png","pic":"https:\/\/simg.s.weibo.com\/wb_search_img_search_34.png","itemid":"seqid:16876538895570640278|c_type:31|key:#\u767d\u4fc4\u7f57\u65af\u79f0\u666e\u91cc\u6208\u4efb\u63a5\u53d7\u5362\u5361\u7533\u79d1\u63d0\u8bae#|cate:5001|t:31|qtime:1687653889|pos:1-1-34|type:25|srid:7bd33e3c6e04148aa87eca12e45a2a54","icon_height":24,"icon_width":24,"actionlog":{"fid":"106003type=25&t=3&disable_hot=1&filter_type=realtimehot","lfid":"","act_type":1,"act_code":554,"ext":"seqid:16876538895570640278|srid:7bd33e3c6e04148aa87eca12e45a2a54|c_type:31|key:#\u767d\u4fc4\u7f57\u65af\u79f0\u666e\u91cc\u6208\u4efb\u63a5\u53d7\u5362\u5361\u7533\u79d1\u63d0\u8bae#|cate:5001|t:31|qtime:1687653889|pos:1_34|page:1|type:25|dgr:0","uicode":"","luicode":""},"desc":"\u767d\u4fc4\u7f57\u65af\u79f0\u666e\u91cc\u6208\u4efb\u63a5\u53d7\u5362\u5361\u7533\u79d1\u63d0\u8bae","scheme":"https:\/\/m.weibo.cn\/search?containerid=100103type%3D1%26t%3D10%26q%3D%23%E7%99%BD%E4%BF%84%E7%BD%97%E6%96%AF%E7%A7%B0%E6%99%AE%E9%87%8C%E6%88%88%E4%BB%BB%E6%8E%A5%E5%8F%97%E5%8D%A2%E5%8D%A1%E7%94%B3%E7%A7%91%E6%8F%90%E8%AE%AE%23&stream_entry_id=31&isnewpage=1&extparam=seat%3D1%26band_rank%3D34%26flag%3D1%26dgr%3D0%26c_type%3D31%26lcate%3D5001%26cate%3D5001%26stream_entry_id%3D31%26q%3D%2523%25E7%2599%25BD%25E4%25BF%2584%25E7%25BD%2597%25E6%2596%25AF%25E7%25A7%25B0%25E6%2599%25AE%25E9%2587%258C%25E6%2588%2588%25E4%25BB%25BB%25E6%258E%25A5%25E5%258F%2597%25E5%258D%25A2%25E5%258D%25A1%25E7%2594%25B3%25E7%25A7%2591%25E6%258F%2590%25E8%25AE%25AE%2523%26filter_type%3Drealtimehot%26realpos%3D34%26pos%3D34%26display_time%3D1687653889%26pre_seqid%3D16876538895570640278&luicode=10000011&lfid=106003type%253D25%2526t%253D3%2526disable_hot%253D1%2526filter_type%253Drealtimehot","card_type":4},{"desc_extr":260899,"desc":"\u94f6\u5ddd31\u6b7b\u7206\u70b8\u4e8b\u6545\u539f\u56e0\u516c\u5e03","pic":"https:\/\/simg.s.weibo.com\/wb_search_img_search_35.png","itemid":"seqid:16876538895570640278|c_type:31|key:#\u94f6\u5ddd31\u6b7b\u7206\u70b8\u4e8b\u6545\u539f\u56e0\u516c\u5e03#|cate:5001|t:31|qtime:1687653889|pos:1-1-35|type:25|srid:7bd33e3c6e04148aa87eca12e45a2a54","actionlog":{"fid":"106003type=25&t=3&disable_hot=1&filter_type=realtimehot","lfid":"","act_type":1,"act_code":554,"ext":"seqid:16876538895570640278|srid:7bd33e3c6e04148aa87eca12e45a2a54|c_type:31|key:#\u94f6\u5ddd31\u6b7b\u7206\u70b8\u4e8b\u6545\u539f\u56e0\u516c\u5e03#|cate:5001|t:31|qtime:1687653889|pos:1_35|page:1|type:25|dgr:0","uicode":"","luicode":""},"scheme":"https:\/\/m.weibo.cn\/search?containerid=100103type%3D1%26t%3D10%26q%3D%23%E9%93%B6%E5%B7%9D31%E6%AD%BB%E7%88%86%E7%82%B8%E4%BA%8B%E6%95%85%E5%8E%9F%E5%9B%A0%E5%85%AC%E5%B8%83%23&stream_entry_id=31&isnewpage=1&extparam=seat%3D1%26band_rank%3D35%26flag%3D0%26dgr%3D0%26c_type%3D31%26lcate%3D5001%26cate%3D5001%26stream_entry_id%3D31%26q%3D%2523%25E9%2593%25B6%25E5%25B7%259D31%25E6%25AD%25BB%25E7%2588%2586%25E7%2582%25B8%25E4%25BA%258B%25E6%2595%2585%25E5%258E%259F%25E5%259B%25A0%25E5%2585%25AC%25E5%25B8%2583%2523%26filter_type%3Drealtimehot%26realpos%3D35%26pos%3D35%26display_time%3D1687653889%26pre_seqid%3D16876538895570640278&luicode=10000011&lfid=106003type%253D25%2526t%253D3%2526disable_hot%253D1%2526filter_type%253Drealtimehot","card_type":4},{"desc_extr":"\u97f3\u4e50 241460","icon":"https:\/\/simg.s.weibo.com\/moter\/flags\/1_0.png","pic":"https:\/\/simg.s.weibo.com\/wb_search_img_search_36.png","itemid":"seqid:16876538895570640278|c_type:31|key:#\u9e7f\u6657\u6f14\u5531\u4f1a\u6563\u573a\u540e\u6ca1\u6709\u5783\u573e#|cate:5001|t:31|qtime:1687653889|pos:1-1-36|type:25|srid:7bd33e3c6e04148aa87eca12e45a2a54","icon_height":24,"icon_width":24,"actionlog":{"fid":"106003type=25&t=3&disable_hot=1&filter_type=realtimehot","lfid":"","act_type":1,"act_code":554,"ext":"seqid:16876538895570640278|srid:7bd33e3c6e04148aa87eca12e45a2a54|c_type:31|key:#\u9e7f\u6657\u6f14\u5531\u4f1a\u6563\u573a\u540e\u6ca1\u6709\u5783\u573e#|cate:5001|t:31|qtime:1687653889|pos:1_36|page:1|type:25|dgr:0","uicode":"","luicode":""},"desc":"\u9e7f\u6657\u6f14\u5531\u4f1a\u6563\u573a\u540e\u6ca1\u6709\u5783\u573e","scheme":"https:\/\/m.weibo.cn\/search?containerid=100103type%3D1%26t%3D10%26q%3D%23%E9%B9%BF%E6%99%97%E6%BC%94%E5%94%B1%E4%BC%9A%E6%95%A3%E5%9C%BA%E5%90%8E%E6%B2%A1%E6%9C%89%E5%9E%83%E5%9C%BE%23&stream_entry_id=31&isnewpage=1&extparam=seat%3D1%26band_rank%3D36%26flag%3D1%26dgr%3D0%26c_type%3D31%26lcate%3D5001%26cate%3D5001%26stream_entry_id%3D31%26q%3D%2523%25E9%25B9%25BF%25E6%2599%2597%25E6%25BC%2594%25E5%2594%25B1%25E4%25BC%259A%25E6%2595%25A3%25E5%259C%25BA%25E5%2590%258E%25E6%25B2%25A1%25E6%259C%2589%25E5%259E%2583%25E5%259C%25BE%2523%26filter_type%3Drealtimehot%26realpos%3D36%26pos%3D36%26display_time%3D1687653889%26pre_seqid%3D16876538895570640278&luicode=10000011&lfid=106003type%253D25%2526t%253D3%2526disable_hot%253D1%2526filter_type%253Drealtimehot","card_type":4},{"desc_extr":240788,"icon":"https:\/\/simg.s.weibo.com\/moter\/flags\/1_0.png","pic":"https:\/\/simg.s.weibo.com\/wb_search_img_search_37.png","itemid":"seqid:16876538895570640278|c_type:31|key:#\u4f69\u65af\u79d1\u592b\u79f0\u5c06\u64a4\u9500\u5bf9\u666e\u91cc\u6208\u4efb\u5211\u4e8b\u7acb\u6848#|cate:5001|t:31|qtime:1687653889|pos:1-1-37|type:25|srid:7bd33e3c6e04148aa87eca12e45a2a54","icon_height":24,"icon_width":24,"actionlog":{"fid":"106003type=25&t=3&disable_hot=1&filter_type=realtimehot","lfid":"","act_type":1,"act_code":554,"ext":"seqid:16876538895570640278|srid:7bd33e3c6e04148aa87eca12e45a2a54|c_type:31|key:#\u4f69\u65af\u79d1\u592b\u79f0\u5c06\u64a4\u9500\u5bf9\u666e\u91cc\u6208\u4efb\u5211\u4e8b\u7acb\u6848#|cate:5001|t:31|qtime:1687653889|pos:1_37|page:1|type:25|dgr:0","uicode":"","luicode":""},"desc":"\u4f69\u65af\u79d1\u592b\u79f0\u5c06\u64a4\u9500\u5bf9\u666e\u91cc\u6208\u4efb\u5211\u4e8b\u7acb\u6848","scheme":"https:\/\/m.weibo.cn\/search?containerid=100103type%3D1%26t%3D10%26q%3D%23%E4%BD%A9%E6%96%AF%E7%A7%91%E5%A4%AB%E7%A7%B0%E5%B0%86%E6%92%A4%E9%94%80%E5%AF%B9%E6%99%AE%E9%87%8C%E6%88%88%E4%BB%BB%E5%88%91%E4%BA%8B%E7%AB%8B%E6%A1%88%23&stream_entry_id=31&isnewpage=1&extparam=seat%3D1%26band_rank%3D37%26flag%3D1%26dgr%3D0%26c_type%3D31%26lcate%3D5001%26cate%3D5001%26stream_entry_id%3D31%26q%3D%2523%25E4%25BD%25A9%25E6%2596%25AF%25E7%25A7%2591%25E5%25A4%25AB%25E7%25A7%25B0%25E5%25B0%2586%25E6%2592%25A4%25E9%2594%2580%25E5%25AF%25B9%25E6%2599%25AE%25E9%2587%258C%25E6%2588%2588%25E4%25BB%25BB%25E5%2588%2591%25E4%25BA%258B%25E7%25AB%258B%25E6%25A1%2588%2523%26filter_type%3Drealtimehot%26realpos%3D37%26pos%3D37%26display_time%3D1687653889%26pre_seqid%3D16876538895570640278&luicode=10000011&lfid=106003type%253D25%2526t%253D3%2526disable_hot%253D1%2526filter_type%253Drealtimehot","card_type":4},{"desc_extr":"\u5267\u96c6 239738","icon":"https:\/\/simg.s.weibo.com\/moter\/flags\/1_0.png","pic":"https:\/\/simg.s.weibo.com\/wb_search_img_search_38.png","itemid":"seqid:16876538895570640278|c_type:31|key:#\u767d\u8f76\u8865\u8d34\u597d\u751c#|cate:5001|t:31|qtime:1687653889|pos:1-1-38|type:25|srid:7bd33e3c6e04148aa87eca12e45a2a54","icon_height":24,"icon_width":24,"actionlog":{"fid":"106003type=25&t=3&disable_hot=1&filter_type=realtimehot","lfid":"","act_type":1,"act_code":554,"ext":"seqid:16876538895570640278|srid:7bd33e3c6e04148aa87eca12e45a2a54|c_type:31|key:#\u767d\u8f76\u8865\u8d34\u597d\u751c#|cate:5001|t:31|qtime:1687653889|pos:1_38|page:1|type:25|dgr:0","uicode":"","luicode":""},"desc":"\u767d\u8f76\u8865\u8d34\u597d\u751c","scheme":"https:\/\/m.weibo.cn\/search?containerid=100103type%3D1%26t%3D10%26q%3D%23%E7%99%BD%E8%BD%B6%E8%A1%A5%E8%B4%B4%E5%A5%BD%E7%94%9C%23&stream_entry_id=31&isnewpage=1&extparam=seat%3D1%26band_rank%3D38%26flag%3D1%26dgr%3D0%26c_type%3D31%26lcate%3D5001%26cate%3D5001%26stream_entry_id%3D31%26q%3D%2523%25E7%2599%25BD%25E8%25BD%25B6%25E8%25A1%25A5%25E8%25B4%25B4%25E5%25A5%25BD%25E7%2594%259C%2523%26filter_type%3Drealtimehot%26realpos%3D38%26pos%3D38%26display_time%3D1687653889%26pre_seqid%3D16876538895570640278&luicode=10000011&lfid=106003type%253D25%2526t%253D3%2526disable_hot%253D1%2526filter_type%253Drealtimehot","card_type":4},{"desc_extr":"\u7535\u5f71 233897","desc":"\u6d88\u5931\u7684\u5979","pic":"https:\/\/simg.s.weibo.com\/wb_search_img_search_39.png","itemid":"seqid:16876538895570640278|c_type:31|key:\u6d88\u5931\u7684\u5979|cate:5001|t:31|qtime:1687653889|pos:1-1-39|type:25|srid:7bd33e3c6e04148aa87eca12e45a2a54","actionlog":{"fid":"106003type=25&t=3&disable_hot=1&filter_type=realtimehot","lfid":"","act_type":1,"act_code":554,"ext":"seqid:16876538895570640278|srid:7bd33e3c6e04148aa87eca12e45a2a54|c_type:31|key:\u6d88\u5931\u7684\u5979|cate:5001|t:31|qtime:1687653889|pos:1_39|page:1|type:25|dgr:0","uicode":"","luicode":""},"scheme":"https:\/\/m.weibo.cn\/search?containerid=100103type%3D1%26t%3D10%26q%3D%E6%B6%88%E5%A4%B1%E7%9A%84%E5%A5%B9&stream_entry_id=31&isnewpage=1&extparam=seat%3D1%26band_rank%3D39%26flag%3D0%26dgr%3D0%26c_type%3D31%26lcate%3D5001%26cate%3D5001%26stream_entry_id%3D31%26q%3D%25E6%25B6%2588%25E5%25A4%25B1%25E7%259A%2584%25E5%25A5%25B9%26filter_type%3Drealtimehot%26realpos%3D39%26pos%3D39%26display_time%3D1687653889%26pre_seqid%3D16876538895570640278&luicode=10000011&lfid=106003type%253D25%2526t%253D3%2526disable_hot%253D1%2526filter_type%253Drealtimehot","card_type":4},{"desc_extr":222254,"icon":"https:\/\/simg.s.weibo.com\/moter\/flags\/32768_0.png","pic":"https:\/\/simg.s.weibo.com\/wb_search_img_search_40.png","itemid":"seqid:16876538895570640278|c_type:31|key:#\u590d\u8bfb\u5973\u751f\u6da861\u5206\u5750\u5730\u568e\u5555\u5927\u54ed#|cate:5001|t:31|qtime:1687653889|pos:1-1-40|type:25|srid:7bd33e3c6e04148aa87eca12e45a2a54","icon_height":24,"icon_width":24,"actionlog":{"fid":"106003type=25&t=3&disable_hot=1&filter_type=realtimehot","lfid":"","act_type":1,"act_code":554,"ext":"seqid:16876538895570640278|srid:7bd33e3c6e04148aa87eca12e45a2a54|c_type:31|key:#\u590d\u8bfb\u5973\u751f\u6da861\u5206\u5750\u5730\u568e\u5555\u5927\u54ed#|cate:5001|t:31|qtime:1687653889|pos:1_40|page:1|type:25|dgr:0","uicode":"","luicode":""},"desc":"\u590d\u8bfb\u5973\u751f\u6da861\u5206\u5750\u5730\u568e\u5555\u5927\u54ed","scheme":"https:\/\/m.weibo.cn\/search?containerid=100103type%3D1%26t%3D10%26q%3D%23%E5%A4%8D%E8%AF%BB%E5%A5%B3%E7%94%9F%E6%B6%A861%E5%88%86%E5%9D%90%E5%9C%B0%E5%9A%8E%E5%95%95%E5%A4%A7%E5%93%AD%23&stream_entry_id=31&isnewpage=1&extparam=seat%3D1%26band_rank%3D40%26flag%3D32768%26dgr%3D0%26c_type%3D31%26lcate%3D5001%26cate%3D5001%26stream_entry_id%3D31%26q%3D%2523%25E5%25A4%258D%25E8%25AF%25BB%25E5%25A5%25B3%25E7%2594%259F%25E6%25B6%25A861%25E5%2588%2586%25E5%259D%2590%25E5%259C%25B0%25E5%259A%258E%25E5%2595%2595%25E5%25A4%25A7%25E5%2593%25AD%2523%26filter_type%3Drealtimehot%26realpos%3D40%26pos%3D40%26display_time%3D1687653889%26pre_seqid%3D16876538895570640278&luicode=10000011&lfid=106003type%253D25%2526t%253D3%2526disable_hot%253D1%2526filter_type%253Drealtimehot","card_type":4},{"desc_extr":219794,"icon":"https:\/\/simg.s.weibo.com\/moter\/flags\/1_0.png","pic":"https:\/\/simg.s.weibo.com\/wb_search_img_search_41.png","itemid":"seqid:16876538895570640278|c_type:31|key:\u6709\u4e0d\u626b\u5174\u7684\u7236\u6bcd\u662f\u4ec0\u4e48\u4f53\u9a8c|cate:5001|t:31|qtime:1687653889|pos:1-1-41|type:25|srid:7bd33e3c6e04148aa87eca12e45a2a54","icon_height":24,"icon_width":24,"actionlog":{"fid":"106003type=25&t=3&disable_hot=1&filter_type=realtimehot","lfid":"","act_type":1,"act_code":554,"ext":"seqid:16876538895570640278|srid:7bd33e3c6e04148aa87eca12e45a2a54|c_type:31|key:\u6709\u4e0d\u626b\u5174\u7684\u7236\u6bcd\u662f\u4ec0\u4e48\u4f53\u9a8c|cate:5001|t:31|qtime:1687653889|pos:1_41|page:1|type:25|dgr:0","uicode":"","luicode":""},"desc":"\u6709\u4e0d\u626b\u5174\u7684\u7236\u6bcd\u662f\u4ec0\u4e48\u4f53\u9a8c","scheme":"https:\/\/m.weibo.cn\/search?containerid=100103type%3D1%26t%3D10%26q%3D%E6%9C%89%E4%B8%8D%E6%89%AB%E5%85%B4%E7%9A%84%E7%88%B6%E6%AF%8D%E6%98%AF%E4%BB%80%E4%B9%88%E4%BD%93%E9%AA%8C&stream_entry_id=31&isnewpage=1&extparam=seat%3D1%26band_rank%3D41%26flag%3D1%26dgr%3D0%26c_type%3D31%26lcate%3D5001%26cate%3D5001%26stream_entry_id%3D31%26q%3D%25E6%259C%2589%25E4%25B8%258D%25E6%2589%25AB%25E5%2585%25B4%25E7%259A%2584%25E7%2588%25B6%25E6%25AF%258D%25E6%2598%25AF%25E4%25BB%2580%25E4%25B9%2588%25E4%25BD%2593%25E9%25AA%258C%26filter_type%3Drealtimehot%26realpos%3D41%26pos%3D41%26display_time%3D1687653889%26pre_seqid%3D16876538895570640278&luicode=10000011&lfid=106003type%253D25%2526t%253D3%2526disable_hot%253D1%2526filter_type%253Drealtimehot","card_type":4},{"desc_extr":"\u7efc\u827a 217900","icon":"https:\/\/simg.s.weibo.com\/moter\/flags\/1_0.png","pic":"https:\/\/simg.s.weibo.com\/wb_search_img_search_42.png","itemid":"seqid:16876538895570640278|c_type:31|key:#\u4e54\u6b23\u5986\u53d1\u767d\u505a\u4e86#|cate:5001|t:31|qtime:1687653889|pos:1-1-42|type:25|srid:7bd33e3c6e04148aa87eca12e45a2a54","icon_height":24,"icon_width":24,"actionlog":{"fid":"106003type=25&t=3&disable_hot=1&filter_type=realtimehot","lfid":"","act_type":1,"act_code":554,"ext":"seqid:16876538895570640278|srid:7bd33e3c6e04148aa87eca12e45a2a54|c_type:31|key:#\u4e54\u6b23\u5986\u53d1\u767d\u505a\u4e86#|cate:5001|t:31|qtime:1687653889|pos:1_42|page:1|type:25|dgr:0","uicode":"","luicode":""},"desc":"\u4e54\u6b23\u5986\u53d1\u767d\u505a\u4e86","scheme":"https:\/\/m.weibo.cn\/search?containerid=100103type%3D1%26t%3D10%26q%3D%23%E4%B9%94%E6%AC%A3%E5%A6%86%E5%8F%91%E7%99%BD%E5%81%9A%E4%BA%86%23&stream_entry_id=31&isnewpage=1&extparam=seat%3D1%26band_rank%3D42%26flag%3D1%26dgr%3D0%26c_type%3D31%26lcate%3D5001%26cate%3D5001%26stream_entry_id%3D31%26q%3D%2523%25E4%25B9%2594%25E6%25AC%25A3%25E5%25A6%2586%25E5%258F%2591%25E7%2599%25BD%25E5%2581%259A%25E4%25BA%2586%2523%26filter_type%3Drealtimehot%26realpos%3D42%26pos%3D42%26display_time%3D1687653889%26pre_seqid%3D16876538895570640278&luicode=10000011&lfid=106003type%253D25%2526t%253D3%2526disable_hot%253D1%2526filter_type%253Drealtimehot","card_type":4},{"desc_extr":"\u7efc\u827a 217676","desc":"\u6881\u5bb6\u8f89\u8bf4\u81ea\u5df1\u4fdd\u6301\u6d3b\u529b\u5168\u9760\u5403\u866b","pic":"https:\/\/simg.s.weibo.com\/wb_search_img_search_43.png","itemid":"seqid:16876538895570640278|c_type:31|key:#\u6881\u5bb6\u8f89\u8bf4\u81ea\u5df1\u4fdd\u6301\u6d3b\u529b\u5168\u9760\u5403\u866b#|cate:5001|t:31|qtime:1687653889|pos:1-1-43|type:25|srid:7bd33e3c6e04148aa87eca12e45a2a54","actionlog":{"fid":"106003type=25&t=3&disable_hot=1&filter_type=realtimehot","lfid":"","act_type":1,"act_code":554,"ext":"seqid:16876538895570640278|srid:7bd33e3c6e04148aa87eca12e45a2a54|c_type:31|key:#\u6881\u5bb6\u8f89\u8bf4\u81ea\u5df1\u4fdd\u6301\u6d3b\u529b\u5168\u9760\u5403\u866b#|cate:5001|t:31|qtime:1687653889|pos:1_43|page:1|type:25|dgr:0","uicode":"","luicode":""},"scheme":"https:\/\/m.weibo.cn\/search?containerid=100103type%3D1%26t%3D10%26q%3D%23%E6%A2%81%E5%AE%B6%E8%BE%89%E8%AF%B4%E8%87%AA%E5%B7%B1%E4%BF%9D%E6%8C%81%E6%B4%BB%E5%8A%9B%E5%85%A8%E9%9D%A0%E5%90%83%E8%99%AB%23&stream_entry_id=31&isnewpage=1&extparam=seat%3D1%26band_rank%3D43%26flag%3D0%26dgr%3D0%26c_type%3D31%26lcate%3D5001%26cate%3D5001%26stream_entry_id%3D31%26q%3D%2523%25E6%25A2%2581%25E5%25AE%25B6%25E8%25BE%2589%25E8%25AF%25B4%25E8%2587%25AA%25E5%25B7%25B1%25E4%25BF%259D%25E6%258C%2581%25E6%25B4%25BB%25E5%258A%259B%25E5%2585%25A8%25E9%259D%25A0%25E5%2590%2583%25E8%2599%25AB%2523%26filter_type%3Drealtimehot%26realpos%3D43%26pos%3D43%26display_time%3D1687653889%26pre_seqid%3D16876538895570640278&luicode=10000011&lfid=106003type%253D25%2526t%253D3%2526disable_hot%253D1%2526filter_type%253Drealtimehot","card_type":4},{"desc_extr":"\u7efc\u827a 216843","desc":"\u738b\u9e64\u68e3\u8d75\u9732\u601d\u5408\u5f71","pic":"https:\/\/simg.s.weibo.com\/wb_search_img_search_44.png","itemid":"seqid:16876538895570640278|c_type:31|key:#\u738b\u9e64\u68e3\u8d75\u9732\u601d\u5408\u5f71#|cate:5001|t:31|qtime:1687653889|pos:1-1-44|type:25|srid:7bd33e3c6e04148aa87eca12e45a2a54","actionlog":{"fid":"106003type=25&t=3&disable_hot=1&filter_type=realtimehot","lfid":"","act_type":1,"act_code":554,"ext":"seqid:16876538895570640278|srid:7bd33e3c6e04148aa87eca12e45a2a54|c_type:31|key:#\u738b\u9e64\u68e3\u8d75\u9732\u601d\u5408\u5f71#|cate:5001|t:31|qtime:1687653889|pos:1_44|page:1|type:25|dgr:0","uicode":"","luicode":""},"scheme":"https:\/\/m.weibo.cn\/search?containerid=100103type%3D1%26t%3D10%26q%3D%23%E7%8E%8B%E9%B9%A4%E6%A3%A3%E8%B5%B5%E9%9C%B2%E6%80%9D%E5%90%88%E5%BD%B1%23&stream_entry_id=31&isnewpage=1&extparam=seat%3D1%26band_rank%3D44%26flag%3D0%26dgr%3D0%26c_type%3D31%26lcate%3D5001%26cate%3D5001%26stream_entry_id%3D31%26q%3D%2523%25E7%258E%258B%25E9%25B9%25A4%25E6%25A3%25A3%25E8%25B5%25B5%25E9%259C%25B2%25E6%2580%259D%25E5%2590%2588%25E5%25BD%25B1%2523%26filter_type%3Drealtimehot%26realpos%3D44%26pos%3D44%26display_time%3D1687653889%26pre_seqid%3D16876538895570640278&luicode=10000011&lfid=106003type%253D25%2526t%253D3%2526disable_hot%253D1%2526filter_type%253Drealtimehot","card_type":4},{"desc_extr":205190,"desc":"\u74e6\u683c\u7eb3\u8f66\u961f\u79bb\u5f00\u7f57\u65af\u6258\u592b\u5dde","pic":"https:\/\/simg.s.weibo.com\/wb_search_img_search_45.png","itemid":"seqid:16876538895570640278|c_type:31|key:#\u74e6\u683c\u7eb3\u8f66\u961f\u79bb\u5f00\u7f57\u65af\u6258\u592b\u5dde#|cate:5001|t:31|qtime:1687653889|pos:1-1-45|type:25|srid:7bd33e3c6e04148aa87eca12e45a2a54","actionlog":{"fid":"106003type=25&t=3&disable_hot=1&filter_type=realtimehot","lfid":"","act_type":1,"act_code":554,"ext":"seqid:16876538895570640278|srid:7bd33e3c6e04148aa87eca12e45a2a54|c_type:31|key:#\u74e6\u683c\u7eb3\u8f66\u961f\u79bb\u5f00\u7f57\u65af\u6258\u592b\u5dde#|cate:5001|t:31|qtime:1687653889|pos:1_45|page:1|type:25|dgr:0","uicode":"","luicode":""},"scheme":"https:\/\/m.weibo.cn\/search?containerid=100103type%3D1%26t%3D10%26q%3D%23%E7%93%A6%E6%A0%BC%E7%BA%B3%E8%BD%A6%E9%98%9F%E7%A6%BB%E5%BC%80%E7%BD%97%E6%96%AF%E6%89%98%E5%A4%AB%E5%B7%9E%23&stream_entry_id=31&isnewpage=1&extparam=seat%3D1%26band_rank%3D45%26flag%3D0%26dgr%3D0%26c_type%3D31%26lcate%3D5001%26cate%3D5001%26stream_entry_id%3D31%26q%3D%2523%25E7%2593%25A6%25E6%25A0%25BC%25E7%25BA%25B3%25E8%25BD%25A6%25E9%2598%259F%25E7%25A6%25BB%25E5%25BC%2580%25E7%25BD%2597%25E6%2596%25AF%25E6%2589%2598%25E5%25A4%25AB%25E5%25B7%259E%2523%26filter_type%3Drealtimehot%26realpos%3D45%26pos%3D45%26display_time%3D1687653889%26pre_seqid%3D16876538895570640278&luicode=10000011&lfid=106003type%253D25%2526t%253D3%2526disable_hot%253D1%2526filter_type%253Drealtimehot","card_type":4},{"desc_extr":197879,"icon":"https:\/\/simg.s.weibo.com\/moter\/flags\/1_0.png","pic":"https:\/\/simg.s.weibo.com\/wb_search_img_search_46.png","itemid":"seqid:16876538895570640278|c_type:31|key:WBG\u5931\u8bef|cate:5001|t:31|qtime:1687653889|pos:1-1-46|type:25|srid:7bd33e3c6e04148aa87eca12e45a2a54","icon_height":24,"icon_width":24,"actionlog":{"fid":"106003type=25&t=3&disable_hot=1&filter_type=realtimehot","lfid":"","act_type":1,"act_code":554,"ext":"seqid:16876538895570640278|srid:7bd33e3c6e04148aa87eca12e45a2a54|c_type:31|key:WBG\u5931\u8bef|cate:5001|t:31|qtime:1687653889|pos:1_46|page:1|type:25|dgr:0","uicode":"","luicode":""},"desc":"WBG\u5931\u8bef","scheme":"https:\/\/m.weibo.cn\/search?containerid=100103type%3D1%26t%3D10%26q%3DWBG%E5%A4%B1%E8%AF%AF&stream_entry_id=31&isnewpage=1&extparam=seat%3D1%26band_rank%3D46%26flag%3D1%26dgr%3D0%26c_type%3D31%26lcate%3D5001%26cate%3D5001%26stream_entry_id%3D31%26q%3DWBG%25E5%25A4%25B1%25E8%25AF%25AF%26filter_type%3Drealtimehot%26realpos%3D46%26pos%3D46%26display_time%3D1687653889%26pre_seqid%3D16876538895570640278&luicode=10000011&lfid=106003type%253D25%2526t%253D3%2526disable_hot%253D1%2526filter_type%253Drealtimehot","card_type":4},{"desc_extr":193466,"icon":"https:\/\/simg.s.weibo.com\/moter\/flags\/1_0.png","pic":"https:\/\/simg.s.weibo.com\/wb_search_img_search_47.png","itemid":"seqid:16876538895570640278|c_type:31|key:\u4e4c\u514b\u5170|cate:5001|t:31|qtime:1687653889|pos:1-1-47|type:25|srid:7bd33e3c6e04148aa87eca12e45a2a54","icon_height":24,"icon_width":24,"actionlog":{"fid":"106003type=25&t=3&disable_hot=1&filter_type=realtimehot","lfid":"","act_type":1,"act_code":554,"ext":"seqid:16876538895570640278|srid:7bd33e3c6e04148aa87eca12e45a2a54|c_type:31|key:\u4e4c\u514b\u5170|cate:5001|t:31|qtime:1687653889|pos:1_47|page:1|type:25|dgr:0","uicode":"","luicode":""},"desc":"\u4e4c\u514b\u5170","scheme":"https:\/\/m.weibo.cn\/search?containerid=100103type%3D1%26t%3D10%26q%3D%E4%B9%8C%E5%85%8B%E5%85%B0&stream_entry_id=31&isnewpage=1&extparam=seat%3D1%26band_rank%3D47%26flag%3D1%26dgr%3D0%26c_type%3D31%26lcate%3D5001%26cate%3D5001%26stream_entry_id%3D31%26q%3D%25E4%25B9%258C%25E5%2585%258B%25E5%2585%25B0%26filter_type%3Drealtimehot%26realpos%3D47%26pos%3D47%26display_time%3D1687653889%26pre_seqid%3D16876538895570640278&luicode=10000011&lfid=106003type%253D25%2526t%253D3%2526disable_hot%253D1%2526filter_type%253Drealtimehot","card_type":4},{"desc_extr":185852,"icon":"https:\/\/simg.s.weibo.com\/moter\/flags\/1_0.png","pic":"https:\/\/simg.s.weibo.com\/wb_search_img_search_48.png","itemid":"seqid:16876538895570640278|c_type:31|key:\u4eba\u7ec8\u4f1a\u88ab\u5e74\u5c11\u4e0d\u53ef\u5f97\u4e4b\u7269\u56f0\u5176\u4e00\u751f|cate:5001|t:31|qtime:1687653889|pos:1-1-48|type:25|srid:7bd33e3c6e04148aa87eca12e45a2a54","icon_height":24,"icon_width":24,"actionlog":{"fid":"106003type=25&t=3&disable_hot=1&filter_type=realtimehot","lfid":"","act_type":1,"act_code":554,"ext":"seqid:16876538895570640278|srid:7bd33e3c6e04148aa87eca12e45a2a54|c_type:31|key:\u4eba\u7ec8\u4f1a\u88ab\u5e74\u5c11\u4e0d\u53ef\u5f97\u4e4b\u7269\u56f0\u5176\u4e00\u751f|cate:5001|t:31|qtime:1687653889|pos:1_48|page:1|type:25|dgr:0","uicode":"","luicode":""},"desc":"\u4eba\u7ec8\u4f1a\u88ab\u5e74\u5c11\u4e0d\u53ef\u5f97\u4e4b\u7269\u56f0\u5176\u4e00\u751f","scheme":"https:\/\/m.weibo.cn\/search?containerid=100103type%3D1%26t%3D10%26q%3D%E4%BA%BA%E7%BB%88%E4%BC%9A%E8%A2%AB%E5%B9%B4%E5%B0%91%E4%B8%8D%E5%8F%AF%E5%BE%97%E4%B9%8B%E7%89%A9%E5%9B%B0%E5%85%B6%E4%B8%80%E7%94%9F&stream_entry_id=31&isnewpage=1&extparam=seat%3D1%26band_rank%3D48%26flag%3D1%26dgr%3D0%26c_type%3D31%26lcate%3D5001%26cate%3D5001%26stream_entry_id%3D31%26q%3D%25E4%25BA%25BA%25E7%25BB%2588%25E4%25BC%259A%25E8%25A2%25AB%25E5%25B9%25B4%25E5%25B0%2591%25E4%25B8%258D%25E5%258F%25AF%25E5%25BE%2597%25E4%25B9%258B%25E7%2589%25A9%25E5%259B%25B0%25E5%2585%25B6%25E4%25B8%2580%25E7%2594%259F%26filter_type%3Drealtimehot%26realpos%3D48%26pos%3D48%26display_time%3D1687653889%26pre_seqid%3D16876538895570640278&luicode=10000011&lfid=106003type%253D25%2526t%253D3%2526disable_hot%253D1%2526filter_type%253Drealtimehot","card_type":4},{"desc_extr":185709,"desc":"\u4e3a\u4ec0\u4e48\u5976\u8336\u5e97\u7684\u51b0\u5757\u5316\u5f97\u6162","pic":"https:\/\/simg.s.weibo.com\/wb_search_img_search_49.png","itemid":"seqid:16876538895570640278|c_type:31|key:#\u4e3a\u4ec0\u4e48\u5976\u8336\u5e97\u7684\u51b0\u5757\u5316\u5f97\u6162#|cate:5001|t:31|qtime:1687653889|pos:1-1-49|type:25|srid:7bd33e3c6e04148aa87eca12e45a2a54","actionlog":{"fid":"106003type=25&t=3&disable_hot=1&filter_type=realtimehot","lfid":"","act_type":1,"act_code":554,"ext":"seqid:16876538895570640278|srid:7bd33e3c6e04148aa87eca12e45a2a54|c_type:31|key:#\u4e3a\u4ec0\u4e48\u5976\u8336\u5e97\u7684\u51b0\u5757\u5316\u5f97\u6162#|cate:5001|t:31|qtime:1687653889|pos:1_49|page:1|type:25|dgr:0","uicode":"","luicode":""},"scheme":"https:\/\/m.weibo.cn\/search?containerid=100103type%3D1%26t%3D10%26q%3D%23%E4%B8%BA%E4%BB%80%E4%B9%88%E5%A5%B6%E8%8C%B6%E5%BA%97%E7%9A%84%E5%86%B0%E5%9D%97%E5%8C%96%E5%BE%97%E6%85%A2%23&stream_entry_id=31&isnewpage=1&extparam=seat%3D1%26band_rank%3D49%26flag%3D0%26dgr%3D0%26c_type%3D31%26lcate%3D5001%26cate%3D5001%26stream_entry_id%3D31%26q%3D%2523%25E4%25B8%25BA%25E4%25BB%2580%25E4%25B9%2588%25E5%25A5%25B6%25E8%258C%25B6%25E5%25BA%2597%25E7%259A%2584%25E5%2586%25B0%25E5%259D%2597%25E5%258C%2596%25E5%25BE%2597%25E6%2585%25A2%2523%26filter_type%3Drealtimehot%26realpos%3D49%26pos%3D49%26display_time%3D1687653889%26pre_seqid%3D16876538895570640278&luicode=10000011&lfid=106003type%253D25%2526t%253D3%2526disable_hot%253D1%2526filter_type%253Drealtimehot","card_type":4},{"desc_extr":185656,"desc":"TheShy","pic":"https:\/\/simg.s.weibo.com\/wb_search_img_search_50.png","itemid":"seqid:16876538895570640278|c_type:31|key:TheShy|cate:5001|t:31|qtime:1687653889|pos:1-1-50|type:25|srid:7bd33e3c6e04148aa87eca12e45a2a54","actionlog":{"fid":"106003type=25&t=3&disable_hot=1&filter_type=realtimehot","lfid":"","act_type":1,"act_code":554,"ext":"seqid:16876538895570640278|srid:7bd33e3c6e04148aa87eca12e45a2a54|c_type:31|key:TheShy|cate:5001|t:31|qtime:1687653889|pos:1_50|page:1|type:25|dgr:0","uicode":"","luicode":""},"scheme":"https:\/\/m.weibo.cn\/search?containerid=100103type%3D1%26t%3D10%26q%3DTheShy&stream_entry_id=31&isnewpage=1&extparam=seat%3D1%26band_rank%3D50%26flag%3D0%26dgr%3D0%26c_type%3D31%26lcate%3D5001%26cate%3D5001%26stream_entry_id%3D31%26q%3DTheShy%26filter_type%3Drealtimehot%26realpos%3D50%26pos%3D50%26display_time%3D1687653889%26pre_seqid%3D16876538895570640278&luicode=10000011&lfid=106003type%253D25%2526t%253D3%2526disable_hot%253D1%2526filter_type%253Drealtimehot","card_type":4}],"itemid":"hotword","show_type":0,"card_type":11}],"cardlistInfo":{"v_p":"42","containerid":"106003type=25&t=3&disable_hot=1&filter_type=realtimehot","config":{"effective_cache_duration":12},"headbg_animation":"scale","total":40,"select_id":"106003type=25&t=3&disable_hot=1&filter_type=realtimehot","title_top":"\u5fae\u535a\u70ed\u641c","show_style":1,"starttime":1687653889,"can_shared":0,"cardlist_menus":[],"page_size":20,"page_type":"08","cardlist_head_cards":[{"head_data":{"cover_url":"https:\/\/simg.s.weibo.com\/20210521_hot_banner_h5.png","show_navi_mask":false,"data_type":2001,"show_title":false,"scheme":"https:\/\/m.weibo.cn\/feature\/applink?scheme=sinaweibo%3A%2F%2Fabc"},"title_top":"\u5fae\u535a\u70ed\u641c","head_type":1,"show_menu":true,"head_type_name":"immersive"},{"head_type":0,"channel_list":[{"actionlog":{"fid":"106003type=25&t=3&disable_hot=1&filter_type=realtimehot","lfid":"","act_type":1,"act_code":554,"ext":"seqid:16876538895570640278|srid:7bd33e3c6e04148aa87eca12e45a2a54|c_type:31|cate:5092|t:31|qtime:1687653889|nav_tab:mineband|page:1|type:25|dgr:0","uicode":"","luicode":""},"default_add":1,"containerid":"106003_-_type:25_-_filter_type:mineband","id":1,"name":"\u6211\u7684","scheme":"sinaweibo:\/\/pageinfo?containerid=106003_-_type:25_-_filter_type:mineband&title=\u70ed\u641c\u699c&extparam=","must_show":1},{"actionlog":{"fid":"106003type=25&t=3&disable_hot=1&filter_type=realtimehot","lfid":"","act_type":1,"act_code":554,"ext":"seqid:16876538895570640278|srid:7bd33e3c6e04148aa87eca12e45a2a54|c_type:31|cate:5092|t:31|qtime:1687653889|nav_tab:realtimehot|page:1|type:25|dgr:0","uicode":"","luicode":""},"default_add":1,"containerid":"106003type=25&t=3&disable_hot=1&filter_type=realtimehot","id":2,"name":"\u70ed\u641c","scheme":"sinaweibo:\/\/pageinfo?containerid=106003type=25&t=3&disable_hot=1&filter_type=realtimehot&title=\u70ed\u641c\u699c&extparam=","must_show":1},{"actionlog":{"fid":"106003type=25&t=3&disable_hot=1&filter_type=realtimehot","lfid":"","act_type":1,"act_code":554,"ext":"seqid:16876538895570640278|srid:7bd33e3c6e04148aa87eca12e45a2a54|c_type:31|cate:5092|t:31|qtime:1687653889|nav_tab:fun|page:1|type:25|dgr:0","uicode":"","luicode":""},"default_add":1,"containerid":"106003type=25&t=3&disable_hot=1&filter_type=fun","id":3,"name":"\u6587\u5a31","scheme":"sinaweibo:\/\/pageinfo?containerid=106003type=25&t=3&disable_hot=1&filter_type=fun&title=\u70ed\u641c\u699c&extparam=","must_show":1},{"actionlog":{"fid":"106003type=25&t=3&disable_hot=1&filter_type=realtimehot","lfid":"","act_type":1,"act_code":554,"ext":"seqid:16876538895570640278|srid:7bd33e3c6e04148aa87eca12e45a2a54|c_type:31|cate:5092|t:31|qtime:1687653889|nav_tab:231648_-_3|page:1|type:25|dgr:0","uicode":"","luicode":""},"default_add":1,"containerid":"231648_-_3","id":4,"name":"\u8981\u95fb","scheme":"sinaweibo:\/\/pageinfo?containerid=231648_-_3&title=\u70ed\u641c\u699c&extparam=","must_show":1},{"actionlog":{"fid":"106003type=25&t=3&disable_hot=1&filter_type=realtimehot","lfid":"","act_type":1,"act_code":554,"ext":"seqid:16876538895570640278|srid:7bd33e3c6e04148aa87eca12e45a2a54|c_type:31|cate:5092|t:31|qtime:1687653889|nav_tab:more|page:1|type:25|dgr:0","uicode":"","luicode":""},"default_add":1,"containerid":"106003type=25&t=3&disable_hot=1&filter_type=more","id":5,"name":"\u66f4\u591a","scheme":"sinaweibo:\/\/pageinfo?containerid=106003type=25&t=3&disable_hot=1&filter_type=more&title=\u70ed\u641c\u699c&extparam=","must_show":1}],"show_menu":false,"head_type_name":"channel_list"}],"enable_load_imge_scrolling":1,"nick":"\u5fae\u535a\u70ed\u641c","page_title":"\u5fae\u535a\u70ed\u641c","search_request_id":"7bd33e3c6e04148aa87eca12e45a2a54","page_common_ext":"last_enter_time=1687653890","load_more_threshold":20,"auto_refresh_config":{"106003type=25&t=3&disable_hot=1&filter_type=realtimehot":{"tab_and_background_expire_min":5,"page_resume_expire_sec":600},"106003type=25&t=3&disable_hot=1&filter_type=more":{"tab_and_background_expire_min":5,"page_resume_expire_sec":600},"106003_-_type:25_-_filter_type:mineband":{"tab_and_background_expire_min":5,"page_resume_expire_sec":600},"231648_-_3":{"tab_and_background_expire_min":5,"page_resume_expire_sec":600},"106003type=25&t=3&disable_hot=1&filter_type=fun":{"tab_and_background_expire_min":5,"page_resume_expire_sec":600}},"refresh_configs":{"106003type=25&t=3&disable_hot=1&filter_type=realtimehot":5,"106003type=25&t=3&disable_hot=1&filter_type=more":5,"106003_-_type:25_-_filter_type:mineband":5,"231648_-_3":5,"106003type=25&t=3&disable_hot=1&filter_type=fun":5},"page":2},"scheme":"sinaweibo:\/\/pageinfo?containerid=106003type%253D25%2526t%253D3%2526disable_hot%253D1%2526filter_type%253Drealtimehot&extparam=filter_type%253Drealtimehot%2526mi_cid%253D100103%2526pos%253D0_0%2526c_type%253D30%2526display_time%253D1550505541&luicode=10000011&lfid=231583&_T_WM=86820004768&v_p=42","showAppTips":0}}